Workbook

Sheet Overview
A1: Category | B1: Details
A2: Document Name | B2: EMI Manual Test Cases — B2B — By Feature
A3: Epic / Story Ref | B3: Full EMI manual suite: project docs + this audit + AIO (Jira)
A4: Release Number | B4: All releases to V 6.6.0 / Sprint 74
A5: Environment | B5: UAT
A6: Testing Period | B6: Sprint Test Execution Cycle
A9: EMI Manual Test Cases — B2B — Results by Feature
A11: Feature | B11: Passed | C11: Failed | D11: Partially Passed | E11: Not Tested | F11: Not Implemented | G11: Total Checks | H11: Pass Rate %
A12: Technical Updates | B12: =COUNTIF('Technical Updates'!$I:$I,"Passed") -> 0 | C12: =COUNTIF('Technical Updates'!$I:$I,"Failed") -> 0 | D12: =COUNTIF('Technical Updates'!$I:$I,"Partially Passed") -> 0 | E12: =COUNTIF('Technical Updates'!$I:$I,"Not Tested") -> 1247 | F12: =COUNTIF('Technical Updates'!$I:$I,"Not Implemented") -> 0 | G12: =SUM(B12:F12) -> 1247 | H12: =IF(G12>0,B12/G12,0) -> 0
A13: Deep Payment | B13: =COUNTIF('Deep Payment'!$I:$I,"Passed") -> 0 | C13: =COUNTIF('Deep Payment'!$I:$I,"Failed") -> 0 | D13: =COUNTIF('Deep Payment'!$I:$I,"Partially Passed") -> 0 | E13: =COUNTIF('Deep Payment'!$I:$I,"Not Tested") -> 701 | F13: =COUNTIF('Deep Payment'!$I:$I,"Not Implemented") -> 0 | G13: =SUM(B13:F13) -> 701 | H13: =IF(G13>0,B13/G13,0) -> 0
A14: PoS Transactions | B14: =COUNTIF('PoS Transactions'!$I:$I,"Passed") -> 0 | C14: =COUNTIF('PoS Transactions'!$I:$I,"Failed") -> 0 | D14: =COUNTIF('PoS Transactions'!$I:$I,"Partially Passed") -> 0 | E14: =COUNTIF('PoS Transactions'!$I:$I,"Not Tested") -> 420 | F14: =COUNTIF('PoS Transactions'!$I:$I,"Not Implemented") -> 0 | G14: =SUM(B14:F14) -> 420 | H14: =IF(G14>0,B14/G14,0) -> 0
A15: Setup & Admin | B15: =COUNTIF('Setup & Admin'!$I:$I,"Passed") -> 0 | C15: =COUNTIF('Setup & Admin'!$I:$I,"Failed") -> 0 | D15: =COUNTIF('Setup & Admin'!$I:$I,"Partially Passed") -> 0 | E15: =COUNTIF('Setup & Admin'!$I:$I,"Not Tested") -> 567 | F15: =COUNTIF('Setup & Admin'!$I:$I,"Not Implemented") -> 0 | G15: =SUM(B15:F15) -> 567 | H15: =IF(G15>0,B15/G15,0) -> 0
A16: Transaction Operations | B16: =COUNTIF('Transaction Operations'!$I:$I,"Passed") -> 0 | C16: =COUNTIF('Transaction Operations'!$I:$I,"Failed") -> 0 | D16: =COUNTIF('Transaction Operations'!$I:$I,"Partially Passed") -> 0 | E16: =COUNTIF('Transaction Operations'!$I:$I,"Not Tested") -> 516 | F16: =COUNTIF('Transaction Operations'!$I:$I,"Not Implemented") -> 0 | G16: =SUM(B16:F16) -> 516 | H16: =IF(G16>0,B16/G16,0) -> 0
A17: Registration | B17: =COUNTIF(Registration!$I:$I,"Passed") -> 0 | C17: =COUNTIF(Registration!$I:$I,"Failed") -> 0 | D17: =COUNTIF(Registration!$I:$I,"Partially Passed") -> 0 | E17: =COUNTIF(Registration!$I:$I,"Not Tested") -> 494 | F17: =COUNTIF(Registration!$I:$I,"Not Implemented") -> 0 | G17: =SUM(B17:F17) -> 494 | H17: =IF(G17>0,B17/G17,0) -> 0
A18: Balances & Wallet Consistency | B18: =COUNTIF('Balances & Wallet Consistency'!$I:$I,"Passed") -> 0 | C18: =COUNTIF('Balances & Wallet Consistency'!$I:$I,"Failed") -> 0 | D18: =COUNTIF('Balances & Wallet Consistency'!$I:$I,"Partially Passed") -> 0 | E18: =COUNTIF('Balances & Wallet Consistency'!$I:$I,"Not Tested") -> 330 | F18: =COUNTIF('Balances & Wallet Consistency'!$I:$I,"Not Implemented") -> 0 | G18: =SUM(B18:F18) -> 330 | H18: =IF(G18>0,B18/G18,0) -> 0
A19: Products | B19: =COUNTIF(Products!$I:$I,"Passed") -> 0 | C19: =COUNTIF(Products!$I:$I,"Failed") -> 0 | D19: =COUNTIF(Products!$I:$I,"Partially Passed") -> 0 | E19: =COUNTIF(Products!$I:$I,"Not Tested") -> 300 | F19: =COUNTIF(Products!$I:$I,"Not Implemented") -> 0 | G19: =SUM(B19:F19) -> 300 | H19: =IF(G19>0,B19/G19,0) -> 0
A20: Integrations | B20: =COUNTIF(Integrations!$I:$I,"Passed") -> 0 | C20: =COUNTIF(Integrations!$I:$I,"Failed") -> 0 | D20: =COUNTIF(Integrations!$I:$I,"Partially Passed") -> 0 | E20: =COUNTIF(Integrations!$I:$I,"Not Tested") -> 264 | F20: =COUNTIF(Integrations!$I:$I,"Not Implemented") -> 0 | G20: =SUM(B20:F20) -> 264 | H20: =IF(G20>0,B20/G20,0) -> 0
A21: Login | B21: =COUNTIF(Login!$I:$I,"Passed") -> 0 | C21: =COUNTIF(Login!$I:$I,"Failed") -> 0 | D21: =COUNTIF(Login!$I:$I,"Partially Passed") -> 0 | E21: =COUNTIF(Login!$I:$I,"Not Tested") -> 253 | F21: =COUNTIF(Login!$I:$I,"Not Implemented") -> 0 | G21: =SUM(B21:F21) -> 253 | H21: =IF(G21>0,B21/G21,0) -> 0
A22: RMS | B22: =COUNTIF(RMS!$I:$I,"Passed") -> 0 | C22: =COUNTIF(RMS!$I:$I,"Failed") -> 0 | D22: =COUNTIF(RMS!$I:$I,"Partially Passed") -> 0 | E22: =COUNTIF(RMS!$I:$I,"Not Tested") -> 240 | F22: =COUNTIF(RMS!$I:$I,"Not Implemented") -> 0 | G22: =SUM(B22:F22) -> 240 | H22: =IF(G22>0,B22/G22,0) -> 0
A23: Multi-Omnibus | B23: =COUNTIF('Multi-Omnibus'!$I:$I,"Passed") -> 0 | C23: =COUNTIF('Multi-Omnibus'!$I:$I,"Failed") -> 0 | D23: =COUNTIF('Multi-Omnibus'!$I:$I,"Partially Passed") -> 0 | E23: =COUNTIF('Multi-Omnibus'!$I:$I,"Not Tested") -> 196 | F23: =COUNTIF('Multi-Omnibus'!$I:$I,"Not Implemented") -> 0 | G23: =SUM(B23:F23) -> 196 | H23: =IF(G23>0,B23/G23,0) -> 0
A24: Roles & Permissions | B24: =COUNTIF('Roles & Permissions'!$I:$I,"Passed") -> 0 | C24: =COUNTIF('Roles & Permissions'!$I:$I,"Failed") -> 0 | D24: =COUNTIF('Roles & Permissions'!$I:$I,"Partially Passed") -> 0 | E24: =COUNTIF('Roles & Permissions'!$I:$I,"Not Tested") -> 193 | F24: =COUNTIF('Roles & Permissions'!$I:$I,"Not Implemented") -> 0 | G24: =SUM(B24:F24) -> 193 | H24: =IF(G24>0,B24/G24,0) -> 0
A25: Dashboard & Wallets | B25: =COUNTIF('Dashboard & Wallets'!$I:$I,"Passed") -> 0 | C25: =COUNTIF('Dashboard & Wallets'!$I:$I,"Failed") -> 0 | D25: =COUNTIF('Dashboard & Wallets'!$I:$I,"Partially Passed") -> 0 | E25: =COUNTIF('Dashboard & Wallets'!$I:$I,"Not Tested") -> 189 | F25: =COUNTIF('Dashboard & Wallets'!$I:$I,"Not Implemented") -> 0 | G25: =SUM(B25:F25) -> 189 | H25: =IF(G25>0,B25/G25,0) -> 0
A26: Sub-Wallets | B26: =COUNTIF('Sub-Wallets'!$I:$I,"Passed") -> 0 | C26: =COUNTIF('Sub-Wallets'!$I:$I,"Failed") -> 0 | D26: =COUNTIF('Sub-Wallets'!$I:$I,"Partially Passed") -> 0 | E26: =COUNTIF('Sub-Wallets'!$I:$I,"Not Tested") -> 182 | F26: =COUNTIF('Sub-Wallets'!$I:$I,"Not Implemented") -> 0 | G26: =SUM(B26:F26) -> 182 | H26: =IF(G26>0,B26/G26,0) -> 0
A27: Top Up & Cash In | B27: =COUNTIF('Top Up & Cash In'!$I:$I,"Passed") -> 0 | C27: =COUNTIF('Top Up & Cash In'!$I:$I,"Failed") -> 0 | D27: =COUNTIF('Top Up & Cash In'!$I:$I,"Partially Passed") -> 0 | E27: =COUNTIF('Top Up & Cash In'!$I:$I,"Not Tested") -> 169 | F27: =COUNTIF('Top Up & Cash In'!$I:$I,"Not Implemented") -> 0 | G27: =SUM(B27:F27) -> 169 | H27: =IF(G27>0,B27/G27,0) -> 0
A28: Adjustments & Reversals | B28: =COUNTIF('Adjustments & Reversals'!$I:$I,"Passed") -> 0 | C28: =COUNTIF('Adjustments & Reversals'!$I:$I,"Failed") -> 0 | D28: =COUNTIF('Adjustments & Reversals'!$I:$I,"Partially Passed") -> 0 | E28: =COUNTIF('Adjustments & Reversals'!$I:$I,"Not Tested") -> 136 | F28: =COUNTIF('Adjustments & Reversals'!$I:$I,"Not Implemented") -> 0 | G28: =SUM(B28:F28) -> 136 | H28: =IF(G28>0,B28/G28,0) -> 0
A29: Reconciliation | B29: =COUNTIF(Reconciliation!$I:$I,"Passed") -> 0 | C29: =COUNTIF(Reconciliation!$I:$I,"Failed") -> 0 | D29: =COUNTIF(Reconciliation!$I:$I,"Partially Passed") -> 0 | E29: =COUNTIF(Reconciliation!$I:$I,"Not Tested") -> 132 | F29: =COUNTIF(Reconciliation!$I:$I,"Not Implemented") -> 0 | G29: =SUM(B29:F29) -> 132 | H29: =IF(G29>0,B29/G29,0) -> 0
A30: Profile & Manage Accounts | B30: =COUNTIF('Profile & Manage Accounts'!$I:$I,"Passed") -> 0 | C30: =COUNTIF('Profile & Manage Accounts'!$I:$I,"Failed") -> 0 | D30: =COUNTIF('Profile & Manage Accounts'!$I:$I,"Partially Passed") -> 0 | E30: =COUNTIF('Profile & Manage Accounts'!$I:$I,"Not Tested") -> 130 | F30: =COUNTIF('Profile & Manage Accounts'!$I:$I,"Not Implemented") -> 0 | G30: =SUM(B30:F30) -> 130 | H30: =IF(G30>0,B30/G30,0) -> 0
A31: Money Request | B31: =COUNTIF('Money Request'!$I:$I,"Passed") -> 0 | C31: =COUNTIF('Money Request'!$I:$I,"Failed") -> 0 | D31: =COUNTIF('Money Request'!$I:$I,"Partially Passed") -> 0 | E31: =COUNTIF('Money Request'!$I:$I,"Not Tested") -> 127 | F31: =COUNTIF('Money Request'!$I:$I,"Not Implemented") -> 0 | G31: =SUM(B31:F31) -> 127 | H31: =IF(G31>0,B31/G31,0) -> 0
A32: Forgot Password | B32: =COUNTIF('Forgot Password'!$I:$I,"Passed") -> 0 | C32: =COUNTIF('Forgot Password'!$I:$I,"Failed") -> 0 | D32: =COUNTIF('Forgot Password'!$I:$I,"Partially Passed") -> 0 | E32: =COUNTIF('Forgot Password'!$I:$I,"Not Tested") -> 115 | F32: =COUNTIF('Forgot Password'!$I:$I,"Not Implemented") -> 0 | G32: =SUM(B32:F32) -> 115 | H32: =IF(G32>0,B32/G32,0) -> 0
A33: Bill Payment | B33: =COUNTIF('Bill Payment'!$I:$I,"Passed") -> 0 | C33: =COUNTIF('Bill Payment'!$I:$I,"Failed") -> 0 | D33: =COUNTIF('Bill Payment'!$I:$I,"Partially Passed") -> 0 | E33: =COUNTIF('Bill Payment'!$I:$I,"Not Tested") -> 111 | F33: =COUNTIF('Bill Payment'!$I:$I,"Not Implemented") -> 0 | G33: =SUM(B33:F33) -> 111 | H33: =IF(G33>0,B33/G33,0) -> 0
A34: Platform & System | B34: =COUNTIF('Platform & System'!$I:$I,"Passed") -> 0 | C34: =COUNTIF('Platform & System'!$I:$I,"Failed") -> 0 | D34: =COUNTIF('Platform & System'!$I:$I,"Partially Passed") -> 0 | E34: =COUNTIF('Platform & System'!$I:$I,"Not Tested") -> 111 | F34: =COUNTIF('Platform & System'!$I:$I,"Not Implemented") -> 0 | G34: =SUM(B34:F34) -> 111 | H34: =IF(G34>0,B34/G34,0) -> 0
A35: Bill Management (Creation) | B35: =COUNTIF('Bill Management (Creation)'!$I:$I,"Passed") -> 0 | C35: =COUNTIF('Bill Management (Creation)'!$I:$I,"Failed") -> 0 | D35: =COUNTIF('Bill Management (Creation)'!$I:$I,"Partially Passed") -> 0 | E35: =COUNTIF('Bill Management (Creation)'!$I:$I,"Not Tested") -> 107 | F35: =COUNTIF('Bill Management (Creation)'!$I:$I,"Not Implemented") -> 0 | G35: =SUM(B35:F35) -> 107 | H35: =IF(G35>0,B35/G35,0) -> 0
A36: Transaction Log | B36: =COUNTIF('Transaction Log'!$I:$I,"Passed") -> 0 | C36: =COUNTIF('Transaction Log'!$I:$I,"Failed") -> 0 | D36: =COUNTIF('Transaction Log'!$I:$I,"Partially Passed") -> 0 | E36: =COUNTIF('Transaction Log'!$I:$I,"Not Tested") -> 96 | F36: =COUNTIF('Transaction Log'!$I:$I,"Not Implemented") -> 0 | G36: =SUM(B36:F36) -> 96 | H36: =IF(G36>0,B36/G36,0) -> 0
A37: KYC - KYB - AML | B37: =COUNTIF('KYC - KYB - AML'!$I:$I,"Passed") -> 0 | C37: =COUNTIF('KYC - KYB - AML'!$I:$I,"Failed") -> 0 | D37: =COUNTIF('KYC - KYB - AML'!$I:$I,"Partially Passed") -> 0 | E37: =COUNTIF('KYC - KYB - AML'!$I:$I,"Not Tested") -> 93 | F37: =COUNTIF('KYC - KYB - AML'!$I:$I,"Not Implemented") -> 0 | G37: =SUM(B37:F37) -> 93 | H37: =IF(G37>0,B37/G37,0) -> 0
A38: QR Payment | B38: =COUNTIF('QR Payment'!$I:$I,"Passed") -> 0 | C38: =COUNTIF('QR Payment'!$I:$I,"Failed") -> 0 | D38: =COUNTIF('QR Payment'!$I:$I,"Partially Passed") -> 0 | E38: =COUNTIF('QR Payment'!$I:$I,"Not Tested") -> 87 | F38: =COUNTIF('QR Payment'!$I:$I,"Not Implemented") -> 0 | G38: =SUM(B38:F38) -> 87 | H38: =IF(G38>0,B38/G38,0) -> 0
A39: Bank Transfer & Cash Out | B39: =COUNTIF('Bank Transfer & Cash Out'!$I:$I,"Passed") -> 0 | C39: =COUNTIF('Bank Transfer & Cash Out'!$I:$I,"Failed") -> 0 | D39: =COUNTIF('Bank Transfer & Cash Out'!$I:$I,"Partially Passed") -> 0 | E39: =COUNTIF('Bank Transfer & Cash Out'!$I:$I,"Not Tested") -> 83 | F39: =COUNTIF('Bank Transfer & Cash Out'!$I:$I,"Not Implemented") -> 0 | G39: =SUM(B39:F39) -> 83 | H39: =IF(G39>0,B39/G39,0) -> 0
A40: JIT | B40: =COUNTIF(JIT!$I:$I,"Passed") -> 0 | C40: =COUNTIF(JIT!$I:$I,"Failed") -> 0 | D40: =COUNTIF(JIT!$I:$I,"Partially Passed") -> 0 | E40: =COUNTIF(JIT!$I:$I,"Not Tested") -> 83 | F40: =COUNTIF(JIT!$I:$I,"Not Implemented") -> 0 | G40: =SUM(B40:F40) -> 83 | H40: =IF(G40>0,B40/G40,0) -> 0
A41: Notifications | B41: =COUNTIF(Notifications!$I:$I,"Passed") -> 0 | C41: =COUNTIF(Notifications!$I:$I,"Failed") -> 0 | D41: =COUNTIF(Notifications!$I:$I,"Partially Passed") -> 0 | E41: =COUNTIF(Notifications!$I:$I,"Not Tested") -> 77 | F41: =COUNTIF(Notifications!$I:$I,"Not Implemented") -> 0 | G41: =SUM(B41:F41) -> 77 | H41: =IF(G41>0,B41/G41,0) -> 0
A42: Wallet Configuration | B42: =COUNTIF('Wallet Configuration'!$I:$I,"Passed") -> 0 | C42: =COUNTIF('Wallet Configuration'!$I:$I,"Failed") -> 0 | D42: =COUNTIF('Wallet Configuration'!$I:$I,"Partially Passed") -> 0 | E42: =COUNTIF('Wallet Configuration'!$I:$I,"Not Tested") -> 77 | F42: =COUNTIF('Wallet Configuration'!$I:$I,"Not Implemented") -> 0 | G42: =SUM(B42:F42) -> 77 | H42: =IF(G42>0,B42/G42,0) -> 0
A43: Reports | B43: =COUNTIF(Reports!$I:$I,"Passed") -> 0 | C43: =COUNTIF(Reports!$I:$I,"Failed") -> 0 | D43: =COUNTIF(Reports!$I:$I,"Partially Passed") -> 0 | E43: =COUNTIF(Reports!$I:$I,"Not Tested") -> 69 | F43: =COUNTIF(Reports!$I:$I,"Not Implemented") -> 0 | G43: =SUM(B43:F43) -> 69 | H43: =IF(G43>0,B43/G43,0) -> 0
A44: PoS Device Management | B44: =COUNTIF('PoS Device Management'!$I:$I,"Passed") -> 0 | C44: =COUNTIF('PoS Device Management'!$I:$I,"Failed") -> 0 | D44: =COUNTIF('PoS Device Management'!$I:$I,"Partially Passed") -> 0 | E44: =COUNTIF('PoS Device Management'!$I:$I,"Not Tested") -> 56 | F44: =COUNTIF('PoS Device Management'!$I:$I,"Not Implemented") -> 0 | G44: =SUM(B44:F44) -> 56 | H44: =IF(G44>0,B44/G44,0) -> 0
A45: Wallet Transfer (W2W) | B45: =COUNTIF('Wallet Transfer (W2W)'!$I:$I,"Passed") -> 0 | C45: =COUNTIF('Wallet Transfer (W2W)'!$I:$I,"Failed") -> 0 | D45: =COUNTIF('Wallet Transfer (W2W)'!$I:$I,"Partially Passed") -> 0 | E45: =COUNTIF('Wallet Transfer (W2W)'!$I:$I,"Not Tested") -> 45 | F45: =COUNTIF('Wallet Transfer (W2W)'!$I:$I,"Not Implemented") -> 0 | G45: =SUM(B45:F45) -> 45 | H45: =IF(G45>0,B45/G45,0) -> 0
A46: Wallet Snapshot Pipeline | B46: =COUNTIF('Wallet Snapshot Pipeline'!$I:$I,"Passed") -> 0 | C46: =COUNTIF('Wallet Snapshot Pipeline'!$I:$I,"Failed") -> 0 | D46: =COUNTIF('Wallet Snapshot Pipeline'!$I:$I,"Partially Passed") -> 0 | E46: =COUNTIF('Wallet Snapshot Pipeline'!$I:$I,"Not Tested") -> 44 | F46: =COUNTIF('Wallet Snapshot Pipeline'!$I:$I,"Not Implemented") -> 0 | G46: =SUM(B46:F46) -> 44 | H46: =IF(G46>0,B46/G46,0) -> 0
A47: Other | B47: =COUNTIF(Other!$I:$I,"Passed") -> 0 | C47: =COUNTIF(Other!$I:$I,"Failed") -> 0 | D47: =COUNTIF(Other!$I:$I,"Partially Passed") -> 0 | E47: =COUNTIF(Other!$I:$I,"Not Tested") -> 43 | F47: =COUNTIF(Other!$I:$I,"Not Implemented") -> 0 | G47: =SUM(B47:F47) -> 43 | H47: =IF(G47>0,B47/G47,0) -> 0
A48: Payments TTL & Invalidation | B48: =COUNTIF('Payments TTL & Invalidation'!$I:$I,"Passed") -> 0 | C48: =COUNTIF('Payments TTL & Invalidation'!$I:$I,"Failed") -> 0 | D48: =COUNTIF('Payments TTL & Invalidation'!$I:$I,"Partially Passed") -> 0 | E48: =COUNTIF('Payments TTL & Invalidation'!$I:$I,"Not Tested") -> 41 | F48: =COUNTIF('Payments TTL & Invalidation'!$I:$I,"Not Implemented") -> 0 | G48: =SUM(B48:F48) -> 41 | H48: =IF(G48>0,B48/G48,0) -> 0
A49: Wallet Snapshot Admin | B49: =COUNTIF('Wallet Snapshot Admin'!$I:$I,"Passed") -> 0 | C49: =COUNTIF('Wallet Snapshot Admin'!$I:$I,"Failed") -> 0 | D49: =COUNTIF('Wallet Snapshot Admin'!$I:$I,"Partially Passed") -> 0 | E49: =COUNTIF('Wallet Snapshot Admin'!$I:$I,"Not Tested") -> 24 | F49: =COUNTIF('Wallet Snapshot Admin'!$I:$I,"Not Implemented") -> 0 | G49: =SUM(B49:F49) -> 24 | H49: =IF(G49>0,B49/G49,0) -> 0
A50: End-to-End Journeys | B50: =COUNTIF('End-to-End Journeys'!$I:$I,"Passed") -> 0 | C50: =COUNTIF('End-to-End Journeys'!$I:$I,"Failed") -> 0 | D50: =COUNTIF('End-to-End Journeys'!$I:$I,"Partially Passed") -> 0 | E50: =COUNTIF('End-to-End Journeys'!$I:$I,"Not Tested") -> 22 | F50: =COUNTIF('End-to-End Journeys'!$I:$I,"Not Implemented") -> 0 | G50: =SUM(B50:F50) -> 22 | H50: =IF(G50>0,B50/G50,0) -> 0
A51: Customer App | B51: =COUNTIF('Customer App'!$I:$I,"Passed") -> 0 | C51: =COUNTIF('Customer App'!$I:$I,"Failed") -> 0 | D51: =COUNTIF('Customer App'!$I:$I,"Partially Passed") -> 0 | E51: =COUNTIF('Customer App'!$I:$I,"Not Tested") -> 17 | F51: =COUNTIF('Customer App'!$I:$I,"Not Implemented") -> 0 | G51: =SUM(B51:F51) -> 17 | H51: =IF(G51>0,B51/G51,0) -> 0
A52: Cards | B52: =COUNTIF(Cards!$I:$I,"Passed") -> 0 | C52: =COUNTIF(Cards!$I:$I,"Failed") -> 0 | D52: =COUNTIF(Cards!$I:$I,"Partially Passed") -> 0 | E52: =COUNTIF(Cards!$I:$I,"Not Tested") -> 5 | F52: =COUNTIF(Cards!$I:$I,"Not Implemented") -> 0 | G52: =SUM(B52:F52) -> 5 | H52: =IF(G52>0,B52/G52,0) -> 0
A53: Total | B53: =SUM(B12:B52) -> 0 | C53: =SUM(C12:C52) -> 0 | D53: =SUM(D12:D52) -> 0 | E53: =SUM(E12:E52) -> 8192 | F53: =SUM(F12:F52) -> 0 | G53: =SUM(G12:G52) -> 8192 | H53: =IF(G53>0,B53/G53,0) -> 0
A55: Source | B55: Test Cases | C55: Notes
A56: Project docs | B56: 1554 | C56: data/ManualTestCases.xlsx — run npm run build:manual-testcases first if any .md changed
A57: New (this audit) | B57: 1060 | C57: Per-epic workbooks in docs/manual-test-cases/*/
A58: AIO (Jira) | B58: 6926 | C58: 7 export files from C:\Users\SondosHamdan\Downloads
A59: End-to-end journeys | B59: 22 | C59: docs/manual-test-cases/e2e-journeys.json — flows that cross module boundaries
A61: Driven through the interface | B61: 7812 | C61: Interface = Web — run in a browser
A62: Driven against the API | B62: 610 | C62: Interface = API — run with a request client
A64: Automation traceability | B64: 721 | C64: 2124 automated tests read from test-case-exports\All-Automated-Test-Cases.xlsx
A66: Generated | B66: 2026-09-30T07:34:14.276Z

Sheet Technical Updates
A1: TC ID | B1: Sub-Area | C1: Source ID | D1: Title | E1: Priority | F1: Preconditions | G1: Steps | H1: Expected Result | I1: Status | J1: Test Type | K1: Interface | L1: Source | M1: Jira Ref | N1: Automated | O1: Automated By | P1: Channel
A2: EMI-B2B-6750 | B2: 5.1.0 | C2: EMI-TC-5033 | D2: Checking the VAT checkbox applies VAT to the bill total | E2: Critical | F2: Edit bill form is open. VAT checkbox is unchecked. | G2: Check the VAT checkbox and observe the bill total. | H2: Bill total updates to include the applicable VAT amount. VAT line is shown in the bill summary. Change is reflected immediately without a page reload. | I2: Not Tested | J2: Functional | K2: Web | L2: AIO (Jira) | N2: No | P2: B2B
A3: EMI-B2B-6755 | B3: 5.1.0 | C3: EMI-TC-5038 | D3: Issue Date field is removed from the edit bill form | E3: Critical | F3: Edit bill form is open. | G3: Inspect the edit bill form for the Issue Date field. | H3: Issue Date field is not present in the form. It is fully removed, not disabled. No greyed-out or read-only date input remains. | I3: Not Tested | J3: Functional | K3: Web | L3: AIO (Jira) | M3: EMI-5199 | N3: No | P3: B2B
A4: EMI-B2B-6758 | B4: 5.1.0 | C4: EMI-TC-5041 | D4: VAT checkbox and field removals are applied in the single bill edit view | E4: Critical | F4: A single bill is open in edit mode. | G4: Inspect the single bill edit form for VAT field type and presence of Select Beneficiary and Issue Date. | H4: VAT is a checkbox. Select Beneficiary and Issue Date are absent. All other editable fields are present and functional. | I4: Not Tested | J4: Functional | K4: Web | L4: AIO (Jira) | M4: EMI-5199 | N4: No | P4: B2B
A5: EMI-B2B-6761 | B5: 5.1.0 | C5: EMI-TC-5044 | D5: VAT checkbox and field removals are applied in the detailed bill edit view | E5: Critical | F5: A detailed (multi-line) bill is open in edit mode. | G5: Inspect the detailed bill edit form for VAT field type and presence of Select Beneficiary and Issue Date. | H5: VAT is a checkbox. Select Beneficiary and Issue Date are absent. All line-item editable fields are present and functional. | I5: Not Tested | J5: Functional | K5: Web | L5: AIO (Jira) | M5: EMI-5199 | N5: No | P5: B2B
A6: EMI-B2B-6709 | B6: 5.1.0 | C6: EMI-TC-4640 | D6: SessionManager initialises correctly as a singleton via Koin | E6: High | F6: App is launched. Koin dependency modules are configured with SessionManager provided as singleton. | G6: 1. Launch the application 2. Resolve SessionManager from Koin in two separate places 3. Compare both instances | H6: Both resolved instances are the same object reference (singleton). SessionManager is not recreated on each resolution. | I6: Not Tested | J6: Functional | K6: Web | L6: AIO (Jira) | M6: EMI-5213 | N6: No | P6: B2B
A7: EMI-B2B-6710 | B7: 5.1.0 | C7: EMI-TC-4641 | D7: SessionManager starts session timeout coroutine on user login | E7: High | F7: User is on the login screen. SessionManager is initialised. | G7: 1. Complete user login successfully 2. Observe SessionManager coroutine state | H7: Session timeout coroutine is launched and running after login. Coroutine is scoped correctly and does not run before login. | I7: Not Tested | J7: Functional | K7: Web | L7: AIO (Jira) | M7: EMI-5213 | N7: No | P7: B2B
A8: EMI-B2B-6720 | B8: 5.1.0 | C8: EMI-TC-4651 | D8: Session handling in MainActivity behaves equivalently to former BaseActivity | E8: High | F8: Previous session behaviour documented. App is running with new architecture. | G8: 1. Perform a full user session: login, idle, timeout, re-login 2. Compare behaviour to pre-refactor baseline | H8: Session timeout, logout, and re-authentication behave identically to before. No regression in session lifecycle behaviour. | I8: Not Tested | J8: Functional | K8: Web | L8: AIO (Jira) | M8: EMI-5213 | N8: No | P8: B2B
A9: EMI-B2B-6721 | B9: 5.1.0 | C9: EMI-TC-4652 | D9: SessionTimeOutService is removed and no longer invoked | E9: High | F9: Refactor is complete. | G9: 1. Verify SessionTimeOutService does not exist in the codebase 2. Trigger session timeout scenario 3. Observe how timeout is handled | H9: SessionTimeOutService is absent. Timeout is handled entirely by SessionManager coroutine. No service binding or service lifecycle calls occur. | I9: Not Tested | J9: Functional | K9: Web | L9: AIO (Jira) | M9: EMI-5213 | N9: No | P9: B2B
A10: EMI-B2B-6722 | B10: 5.1.0 | C10: EMI-TC-4653 | D10: IdleTimerReceiver is removed and no broadcast intents are used for idle tracking | E10: High | F10: Refactor is complete. | G10: 1. Verify IdleTimerReceiver does not exist 2. Monitor system broadcast intents during app use 3. Trigger idle timeout | H10: IdleTimerReceiver is absent. No broadcast intents sent or received for idle timer. Idle tracking handled entirely within SessionManager. | I10: Not Tested | J10: Functional | K10: Web | L10: AIO (Jira) | M10: EMI-5213 | N10: No | P10: B2B
A11: EMI-B2B-6727 | B11: 5.1.0 | C11: EMI-TC-4658 | D11: SessionManager is provided as singleton in Koin modules | E11: High | F11: App is launched with updated Koin configuration. | G11: 1. Resolve SessionManager from Koin in MainActivity 2. Resolve SessionManager from Koin in another component 3. Compare instances | H11: Both resolutions return the same singleton instance. Koin module declares SessionManager with single() scope. | I11: Not Tested | J11: Functional | K11: Web | L11: AIO (Jira) | M11: EMI-5213 | N11: No | P11: B2B
A12: EMI-B2B-6728 | B12: 5.1.0 | C12: EMI-TC-4659 | D12: AppCoreModule caches environment settings — not re-read on every access | E12: High | F12: App is running. AppCoreModule is initialised. | G12: 1. Access environment settings multiple times via AppCoreModule 2. Monitor how often settings are read from source (file/prefs/network) | H12: Environment settings are read once and cached. Subsequent accesses return the cached value without re-reading the source. | I12: Not Tested | J12: Functional | K12: Web | L12: AIO (Jira) | M12: EMI-5213 | N12: No | P12: B2B
A13: EMI-B2B-6732 | B13: 5.1.0 | C13: EMI-TC-4663 | D13: Full session lifecycle: login, background app, foreground before timeout | E13: High | F13: User is logged in. | G13: 1. Log in 2. Background the app 3. Return to foreground before timeout elapses 4. Observe session state | H13: Session remains active on foreground return. Idle timer is handled correctly across background/foreground transitions. No unintended logout. | I13: Not Tested | J13: Functional | K13: Web | L13: AIO (Jira) | M13: EMI-5213 | N13: No | P13: B2B
A14: EMI-B2B-6751 | B14: 5.1.0 | C14: EMI-TC-5034 | D14: Unchecking the VAT checkbox removes VAT from the bill total | E14: High | F14: Edit bill form is open. VAT checkbox is currently checked. | G14: Uncheck the VAT checkbox. | H14: VAT is removed from the bill total. Total recalculates immediately. VAT line disappears from the bill summary. | I14: Not Tested | J14: Functional | K14: Web | L14: AIO (Jira) | N14: No | P14: B2B
A15: EMI-B2B-6752 | B15: 5.1.0 | C15: EMI-TC-5035 | D15: VAT checkbox state is saved correctly on form submission | E15: High | F15: Edit bill form is open. VAT checkbox toggled to a new state. | G15: Submit the edit bill form. | H15: Saved bill reflects the new VAT checkbox state. Re-opening the bill shows the checkbox in the saved position. Total matches the expected amount with or without VAT. | I15: Not Tested | J15: Functional | K15: Web | L15: AIO (Jira) | N15: No | P15: B2B
A16: EMI-B2B-6753 | B16: 5.1.0 | C16: EMI-TC-5036 | D16: Old VAT input or dropdown is no longer present in the edit form | E16: High | F16: Edit bill form is open after the update has been deployed. | G16: Inspect the form for any text input, number field, or dropdown previously used for VAT entry. | H16: No VAT text input or dropdown exists. Only the checkbox is present. No legacy VAT field remains in the DOM. | I16: Not Tested | J16: Functional | K16: Web | L16: AIO (Jira) | N16: No | P16: B2B
A17: EMI-B2B-6756 | B17: 5.1.0 | C17: EMI-TC-5039 | D17: Removing uneditable fields does not affect other editable fields | E17: High | F17: Edit bill form is open after removal of uneditable fields. | G17: Inspect and interact with the remaining editable fields (e.g. amount, description, VAT checkbox). | H17: All remaining editable fields are functional and properly laid out. No field shifts, overlaps, or broken spacing caused by the removal. | I17: Not Tested | J17: Functional | K17: Web | L17: AIO (Jira) | M17: EMI-5199 | N17: No | P17: B2B
A18: EMI-B2B-6763 | B18: 5.1.0 | C18: EMI-TC-5046 | D18: VAT checkbox state applies consistently across all line items in detailed view | E18: High | F18: Detailed bill with multiple line items is in edit mode. VAT checkbox is at the bill level. | G18: Toggle the VAT checkbox and inspect all line-item totals. | H18: VAT is applied or removed consistently across all line items. No line item retains a conflicting VAT state. Grand total recalculates correctly. | I18: Not Tested | J18: Functional | K18: Web | L18: AIO (Jira) | M18: EMI-5199 | N18: No | P18: B2B
A19: EMI-B2B-6730 | B19: 5.1.0 | C19: EMI-TC-4661 | D19: Unused constants are removed — no dead code references in modules | E19: Medium | F19: Refactor is complete. | G19: 1. Review Koin modules and AppCoreModule for any unused constants 2. Run static analysis / lint | H19: No unused constants in the updated modules. Lint passes without unused symbol warnings for removed items. | I19: Not Tested | J19: Functional | K19: Web | L19: AIO (Jira) | M19: EMI-5213 | N19: No | P19: B2B
A20: EMI-B2B-6759 | B20: 5.1.0 | C20: EMI-TC-5042 | D20: Single bill edit saves correctly with the new form structure | E20: Critical | F20: Single bill edit form open. User modifies amount and toggles VAT checkbox. | G20: Submit the form. | H20: Bill is saved successfully. Updated amount and VAT state are reflected when the bill is reopened. No error from missing removed fields. | I20: Not Tested | J20: Negative | K20: Web | L20: AIO (Jira) | M20: EMI-5199 | N20: No | P20: B2B
A21: EMI-B2B-6762 | B21: 5.1.0 | C21: EMI-TC-5045 | D21: Detailed bill edit saves correctly with the new form structure | E21: Critical | F21: Detailed bill edit form open. User modifies a line-item amount and checks the VAT checkbox. | G21: Submit the form. | H21: Bill is saved successfully. All changes persist on re-open. No error from missing removed fields. Line-item totals reflect the VAT state. | I21: Not Tested | J21: Negative | K21: Web | L21: AIO (Jira) | M21: EMI-5199 | N21: No | P21: B2B
A22: EMI-B2B-6713 | B22: 5.1.0 | C22: EMI-TC-4644 | D22: Reset flag mechanism prevents unnecessary coroutine restarts | E22: High | F22: User is actively using the app. Multiple rapid interactions occur. | G22: 1. Rapidly trigger multiple user interaction events 2. Observe coroutine job count and reset flag state | H22: Reset flag is set on first interaction and coroutine is restarted only once per idle cycle. No coroutine churn — multiple rapid events do not spawn multiple coroutine jobs. | I22: Not Tested | J22: Negative | K22: Web | L22: AIO (Jira) | M22: EMI-5213 | N22: No | P22: B2B
A23: EMI-B2B-6719 | B23: 5.1.0 | C23: EMI-TC-4650 | D23: BaseActivity is fully removed — no residual references exist | E23: High | F23: Refactor is complete. | G23: 1. Search codebase for any references to BaseActivity 2. Verify no classes extend BaseActivity | H23: BaseActivity does not exist. No classes extend or reference BaseActivity. Build succeeds without errors. | I23: Not Tested | J23: Negative | K23: Web | L23: AIO (Jira) | M23: EMI-5213 | N23: No | P23: B2B
A24: EMI-B2B-6735 | B24: 5.1.0 | C24: EMI-TC-4666 | D24: Multiple rapid session resets do not cause coroutine job accumulation | E24: High | F24: User is logged in. Rapid interactions occur. | G24: 1. Rapidly trigger 50+ user interaction events within a second 2. Monitor active coroutine job count | H24: Coroutine job count remains at 1 (the active timeout job). No job accumulation occurs. Reset flag mechanism prevents redundant restarts. | I24: Not Tested | J24: Negative | K24: Web | L24: AIO (Jira) | M24: EMI-5213 | N24: No | P24: B2B
A25: EMI-B2B-6729 | B25: 5.1.0 | C25: EMI-TC-4660 | D25: AppCoreModule cache is invalidated correctly when environment changes | E25: Medium | F25: App is running. Cached environment settings exist. | G25: 1. Change the environment configuration 2. Access environment settings via AppCoreModule | H25: Cache is refreshed after environment change. Stale cached values are not returned after a config update. | I25: Not Tested | J25: Negative | K25: Web | L25: AIO (Jira) | M25: EMI-5213 | N25: No | P25: B2B
A26: EMI-B2B-6754 | B26: 5.1.0 | C26: EMI-TC-5037 | D26: Select Beneficiary field is removed from the edit bill form | E26: Critical | F26: Edit bill form is open. | G26: Inspect the edit bill form for the Select Beneficiary field. | H26: The Select Beneficiary field is not present in the form. It is not disabled or read-only — it is completely absent. No empty placeholder remains. | I26: Not Tested | J26: Edge / Boundary | K26: Web | L26: AIO (Jira) | N26: No | P26: B2B
A27: EMI-B2B-6757 | B27: 5.1.0 | C27: EMI-TC-5040 | D27: Disabled fields are not sent in the form payload when submitting | E27: High | F27: Edit bill form submitted after removal of uneditable fields. | G27: Submit the form and inspect the API request payload. | H27: The payload does not include Select Beneficiary or Issue Date fields. No null or empty values for removed fields are sent to the backend. | I27: Not Tested | J27: Edge / Boundary | K27: Web | L27: AIO (Jira) | M27: EMI-5199 | N27: No | P27: B2B
A28: EMI-B2B-6736 | B28: 5.1.0 | C28: EMI-TC-4856 | D28: Annotated method executes when user holds the required privilege | E28: Critical | F28: Repository method annotated @RequiresPrivilege(ADMIN). User session carries ADMIN privilege. | G28: Call the annotated repository method. | H28: Method executes successfully. Guard intercepts, confirms privilege, and delegates to the real implementation. | I28: Not Tested | J28: Security | K28: Web | L28: AIO (Jira) | N28: No | P28: B2B
A29: EMI-B2B-6739 | B29: 5.1.0 | C29: EMI-TC-4859 | D29: Guard blocks call and throws when required privilege is missing | E29: Critical | F29: Repository method requires WRITE. Current user has READ only. | G29: Call the WRITE-guarded method as a READ-only user. | H29: Guard throws an access-denied exception before the real method body is entered. No data is read or written. | I29: Not Tested | J29: Security | K29: Web | L29: AIO (Jira) | M29: EMI-5208 | N29: No | P29: B2B
A30: EMI-B2B-6740 | B30: 5.1.0 | C30: EMI-TC-4860 | D30: Guard delegates call with original arguments when privilege passes | E30: Critical | F30: Repository method requires READ. User has READ. Method expects arguments (userId=42). | G30: Call the guarded method with userId=42. | H30: Real method is invoked with userId=42 unchanged. Return value is passed back to the caller unmodified. | I30: Not Tested | J30: Security | K30: Web | L30: AIO (Jira) | M30: EMI-5208 | N30: No | P30: B2B
A31: EMI-B2B-6741 | B31: 5.1.0 | C31: EMI-TC-4861 | D31: Privilege is evaluated at call time, not at proxy creation time | E31: Critical | F31: Proxy created while user has ADMIN. User privilege is downgraded to READ before the call. | G31: Call an ADMIN-required method after the privilege downgrade. | H31: Guard uses the current session context and throws access-denied. Construction-time privilege is not cached or reused. | I31: Not Tested | J31: Security | K31: Web | L31: AIO (Jira) | M31: EMI-5208 | N31: No | P31: B2B
A32: EMI-B2B-6744 | B32: 5.1.0 | C32: EMI-TC-4864 | D32: guardedSingleOf registers a singleton guarded proxy in Koin | E32: Critical | F32: Koin module uses guardedSingleOf(::UserRepositoryImpl) bind UserRepository::class. | G32: Resolve UserRepository from Koin twice. | H32: Both resolutions return the same instance. The resolved object is a PrivilegeGuard proxy, not the raw implementation. | I32: Not Tested | J32: Security | K32: Web | L32: AIO (Jira) | M32: EMI-5208 | N32: No | P32: B2B
A33: EMI-B2B-6714 | B33: 5.1.0 | C33: EMI-TC-4645 | D33: SessionManager cancels coroutine cleanly on user logout | E33: High | F33: User is logged in. Session timeout coroutine is active. | G33: 1. User manually logs out 2. Inspect coroutine state | H33: Session timeout coroutine is cancelled on logout. No timeout fires after logout. No memory leaks or dangling coroutine jobs. | I33: Not Tested | J33: Security | K33: Web | L33: AIO (Jira) | M33: EMI-5213 | N33: No | P33: B2B
A34: EMI-B2B-6715 | B34: 5.1.0 | C34: EMI-TC-4646 | D34: SessionManager handles token refresh before expiry | E34: High | F34: User is logged in. Access token is nearing expiry. | G34: 1. Allow token to approach expiry threshold 2. Observe SessionManager behaviour | H34: SessionManager initiates token refresh before expiry. User session continues uninterrupted. New token is stored and used for subsequent requests. | I34: Not Tested | J34: Security | K34: Web | L34: AIO (Jira) | M34: EMI-5213 | N34: No | P34: B2B
A35: EMI-B2B-6716 | B35: 5.1.0 | C35: EMI-TC-4647 | D35: SessionManager logs out user when token refresh fails | E35: High | F35: User is logged in. Access token is expired. Refresh attempt fails (e.g., network error or revoked token). | G35: 1. Allow token to expire 2. Simulate refresh failure 3. Observe app behaviour | H35: SessionManager detects refresh failure. User is redirected to login screen. Session is fully cleared. | I35: Not Tested | J35: Security | K35: Web | L35: AIO (Jira) | M35: EMI-5213 | N35: No | P35: B2B
A36: EMI-B2B-6717 | B36: 5.1.0 | C36: EMI-TC-4648 | D36: Token lifecycle is managed in MainActivity, not BaseActivity | E36: High | F36: Code review / instrumentation confirms BaseActivity has been removed. | G36: 1. Verify BaseActivity no longer exists in the codebase 2. Verify token handling logic is present in MainActivity 3. Run a session scenario end-to-end | H36: No BaseActivity class exists. Token refresh and session expiry handling operate correctly from MainActivity. No regressions in token behaviour. | I36: Not Tested | J36: Security | K36: Web | L36: AIO (Jira) | M36: EMI-5213 | N36: No | P36: B2B
A37: EMI-B2B-6718 | B37: 5.1.0 | C37: EMI-TC-4649 | D37: Token expiry during background state triggers correct session handling on resume | E37: High | F37: User puts app in background. Token expires while app is backgrounded. | G37: 1. Log in and background the app 2. Wait for token to expire 3. Bring app to foreground | H37: On resume, SessionManager detects expired token. User is redirected to login screen. No crash or undefined behaviour on resume. | I37: Not Tested | J37: Security | K37: Web | L37: AIO (Jira) | M37: EMI-5213 | N37: No | P37: B2B
A38: EMI-B2B-6737 | B38: 5.1.0 | C38: EMI-TC-4857 | D38: Unannotated method bypasses the guard with no privilege check | E38: High | F38: Same repository has a second method with no annotation. User has no privileges. | G38: Call the unannotated method. | H38: Method executes normally. No privilege check is performed and no exception is thrown. | I38: Not Tested | J38: Security | K38: Web | L38: AIO (Jira) | N38: No | P38: B2B
A39: EMI-B2B-6738 | B39: 5.1.0 | C39: EMI-TC-4858 | D39: Invalid privilege value on annotation fails at startup | E39: High | F39: A repository method is annotated with an undefined privilege constant. | G39: Start the application with @RequiresPrivilege(UNDEFINED) on a repository method. | H39: Application throws a configuration exception naming the invalid privilege. It does not start silently. | I39: Not Tested | J39: Security | K39: Web | L39: AIO (Jira) | N39: No | P39: B2B
A40: EMI-B2B-6743 | B40: 5.1.0 | C40: EMI-TC-4863 | D40: Guard correctly intercepts Kotlin suspend functions | E40: High | F40: Repository has a suspend fun annotated with @RequiresPrivilege. User lacks the privilege. | G40: Call the suspend function from a coroutine scope without the required privilege. | H40: Guard throws access-denied within the coroutine. Exception propagates to the coroutine's exception handler without context corruption. | I40: Not Tested | J40: Security | K40: Web | L40: AIO (Jira) | M40: EMI-5208 | N40: No | P40: B2B
A41: EMI-B2B-6745 | B41: 5.1.0 | C41: EMI-TC-4865 | D41: Koin throws a clear error when PrivilegeGuard dependency is missing | E41: High | F41: guardedSingleOf is used in a module but PrivilegeGuard is not registered as a Koin dependency. | G41: Start the Koin application. | H41: Koin throws NoBeanDefFoundException at startup identifying the missing PrivilegeGuard. Application does not start silently. | I41: Not Tested | J41: Security | K41: Web | L41: AIO (Jira) | M41: EMI-5208 | N41: No | P41: B2B
A42: EMI-B2B-6746 | B42: 5.1.0 | C42: EMI-TC-4866 | D42: AppSettingsProvider returns correct localised message for active locale | E42: High | F42: AppSettingsProvider configured. App locale set to EN. | G42: Call getPrivilegeDeniedMessage() with locale EN, then switch to AR and call again. | H42: EN call returns a non-null English string. AR call returns a non-null Arabic string. Neither contains placeholder tokens or falls back to the wrong language. | I42: Not Tested | J42: Security | K42: Web | L42: AIO (Jira) | M42: EMI-5208 | N42: No | P42: B2B
A43: EMI-B2B-6747 | B43: 5.1.0 | C43: EMI-TC-4867 | D43: Guard exception message comes from AppSettingsProvider, not a hardcoded string | E43: High | F43: AppSettingsProvider registered in Koin. Locale EN. User lacks required privilege. | G43: Trigger access-denied by calling a guarded method without the required privilege. | H43: The exception message exactly matches AppSettingsProvider.getPrivilegeDeniedMessage(EN). No hardcoded string is present in the exception. | I43: Not Tested | J43: Security | K43: Web | L43: AIO (Jira) | M43: EMI-5208 | N43: No | P43: B2B
A44: EMI-B2B-6742 | B44: 5.1.0 | C44: EMI-TC-4862 | D44: Real repository exception propagates through the proxy unchanged | E44: Medium | F44: User has required privilege. Real repository method throws DatabaseException. | G44: Call the guarded method where the underlying implementation throws. | H44: Caller receives the original DatabaseException with its original message. It is not wrapped in a PrivilegeException. | I44: Not Tested | J44: Security | K44: Web | L44: AIO (Jira) | M44: EMI-5208 | N44: No | P44: B2B
A45: EMI-B2B-6748 | B45: 5.1.0 | C45: EMI-TC-4868 | D45: AppSettingsProvider falls back to English for an unsupported locale | E45: Medium | F45: AppSettingsProvider supports EN and AR only. App locale set to FR. | G45: Call getPrivilegeDeniedMessage() with locale FR. | H45: Returns the English fallback string. Does not throw. Does not return null or empty. | I45: Not Tested | J45: Security | K45: Web | L45: AIO (Jira) | M45: EMI-5208 | N45: No | P45: B2B
A46: EMI-B2B-6711 | B46: 5.1.0 | C46: EMI-TC-4642 | D46: SessionManager triggers session timeout after idle period elapses | E46: High | F46: User is logged in. App is idle (no user interaction). | G46: 1. Log in and remain idle for the configured timeout duration 2. Observe app behaviour | H46: Session timeout is triggered by SessionManager. User is navigated to the login/lock screen. Timeout callback fires exactly once. | I46: Not Tested | J46: Integration | K46: Web | L46: AIO (Jira) | M46: EMI-5213 | N46: No | P46: B2B
A47: EMI-B2B-6712 | B47: 5.1.0 | C47: EMI-TC-4643 | D47: SessionManager cancels and restarts timeout coroutine on user activity | E47: High | F47: User is logged in. Idle timer is running. | G47: 1. Interact with the app before timeout elapses 2. Observe coroutine behaviour | H47: Existing timeout coroutine is cancelled. New coroutine starts fresh from zero. No duplicate coroutine jobs running simultaneously. | I47: Not Tested | J47: Integration | K47: Web | L47: AIO (Jira) | M47: EMI-5213 | N47: No | P47: B2B
A48: EMI-B2B-6723 | B48: 5.1.0 | C48: EMI-TC-4654 | D48: MainNavigation communicates session events via direct callbacks to SessionManager | E48: High | F48: App is running. User is navigating between screens. | G48: 1. Navigate between screens in the app 2. Observe how navigation events are reported to SessionManager | H48: Navigation events are communicated via direct callbacks. No broadcast intents or event buses are used for session-related navigation events. | I48: Not Tested | J48: Integration | K48: Web | L48: AIO (Jira) | M48: EMI-5213 | N48: No | P48: B2B
A49: EMI-B2B-6724 | B49: 5.1.0 | C49: EMI-TC-4655 | D49: MainScreen communicates user interaction to SessionManager via direct callbacks | E49: High | F49: User is interacting with MainScreen content. | G49: 1. Perform user interactions on MainScreen (tap, scroll, input) 2. Verify idle timer is reset via SessionManager callback | H49: Each interaction triggers the appropriate SessionManager callback directly. Idle timer resets as expected without using broadcast mechanism. | I49: Not Tested | J49: Integration | K49: Web | L49: AIO (Jira) | M49: EMI-5213 | N49: No | P49: B2B
A50: EMI-B2B-6726 | B50: 5.1.0 | C50: EMI-TC-4657 | D50: Session timeout navigates user to login screen via MainNavigation callback | E50: High | F50: User is logged in. App is idle. | G50: 1. Allow idle timeout to elapse 2. Observe navigation outcome | H50: SessionManager invokes the registered callback. MainNavigation routes user to the login screen. No broadcast or service used for this navigation. | I50: Not Tested | J50: Integration | K50: Web | L50: AIO (Jira) | M50: EMI-5213 | N50: No | P50: B2B
A51: EMI-B2B-6725 | B51: 5.1.0 | C51: EMI-TC-4656 | D51: Redundant navigation listeners are removed — no duplicate event handling | E51: Medium | F51: Refactor is complete. | G51: 1. Review navigation listener registrations 2. Navigate through the app and monitor listener calls | H51: No redundant or duplicate navigation listeners exist. Each navigation event is handled exactly once. | I51: Not Tested | J51: Integration | K51: Web | L51: AIO (Jira) | M51: EMI-5213 | N51: No | P51: B2B
A52: EMI-B2B-6734 | B52: 5.1.0 | C52: EMI-TC-4665 | D52: App performance is not degraded compared to pre-refactor baseline | E52: Medium | F52: Performance baseline captured from previous architecture. | G52: 1. Run standard user journey on new architecture 2. Measure startup time, memory usage, and frame rate 3. Compare to baseline | H52: Startup time is equal or improved. Memory usage is equal or reduced (no legacy broadcast components). No new jank or dropped frames introduced. | I52: Not Tested | J52: Performance / NFR | K52: Web | L52: AIO (Jira) | M52: EMI-5213 | N52: No | P52: B2B
A53: EMI-B2B-6749 | B53: 5.1.0 | C53: EMI-TC-5032 | D53: VAT field is rendered as a checkbox in the edit bill form | E53: Critical | F53: An editable bill exists. User opens the edit bill form. | G53: Open the edit bill form and inspect the VAT field. | H53: VAT is displayed as a checkbox, not a text input or dropdown. The checkbox is interactive and reflects the current VAT state of the bill. | I53: Not Tested | J53: Usability | K53: Web | L53: AIO (Jira) | N53: No | P53: B2B
A54: EMI-B2B-6731 | B54: 5.1.0 | C54: EMI-TC-4662 | D54: Full session lifecycle: login, active use, idle timeout, re-login | E54: High | F54: Fresh app launch. User credentials available. | G54: 1. Launch app and log in 2. Perform active use for a period 3. Leave app idle until timeout 4. Observe timeout behaviour 5. Re-authenticate | H54: Login succeeds. Idle timer resets on activity. Timeout triggers navigation to login screen. Re-login restarts a fresh session with new timeout coroutine. | I54: Not Tested | J54: Usability | K54: Web | L54: AIO (Jira) | M54: EMI-5213 | N54: No | P54: B2B
A55: EMI-B2B-6733 | B55: 5.1.0 | C55: EMI-TC-4664 | D55: No crash or ANR during session timeout under normal conditions | E55: High | F55: App running normally. No errors in logs. | G55: 1. Allow session to time out naturally 2. Monitor crash reports and ANR logs | H55: No crash or ANR occurs during or after timeout. App transitions to login screen smoothly. | I55: Not Tested | J55: Usability | K55: Web | L55: AIO (Jira) | M55: EMI-5213 | N55: No | P55: B2B
A56: EMI-B2B-6760 | B56: 5.1.0 | C56: EMI-TC-5043 | D56: Single bill view displays beneficiary and issue date as read-only info, not form fields | E56: Medium | F56: Single bill detail view is open (non-edit mode). | G56: Inspect how beneficiary and issue date are shown in the read-only detail view. | H56: Beneficiary and issue date are displayed as static text in the bill detail. They are informational only and not rendered as form inputs anywhere in the view. | I56: Not Tested | J56: Usability | K56: Web | L56: AIO (Jira) | M56: EMI-5199 | N56: No | P56: B2B
A57: EMI-B2B-6862 | B57: 5.2.0 | C57: EMI-TC-5798 | D57: Home page does not regress existing functionality | E57: Critical | G57: Review each existing Home page feature against the pre-redesign list. | H57: All previously working features are still present and functional; no regressions identified. | I57: Not Tested | J57: Functional | K57: Web | L57: AIO (Jira) | M57: EMI-5302 | N57: No | P57: B2B
A58: EMI-B2B-6863 | B58: 5.2.0 | C58: EMI-TC-5799 | D58: My Wallet Links' accessible via side navigation | E58: Critical | G58: Locate 'My Wallet Links' in the side navigation menu. | H58: 'My Wallet Links' menu item is present in the side navigation. | I58: Not Tested | J58: Functional | K58: Web | L58: AIO (Jira) | M58: EMI-5302 | N58: No | P58: B2B
A59: EMI-B2B-6865 | B59: 5.2.0 | C59: EMI-TC-5801 | D59: Old modal no longer appears for 'My Wallet Links' | E59: Critical | G59: Navigate to the Home page and click the 'My Wallet Links' shortcut. | H59: No modal appears; user is routed to the new dedicated page. | I59: Not Tested | J59: Functional | K59: Web | L59: AIO (Jira) | M59: EMI-5302 | N59: No | P59: B2B
A60: EMI-B2B-6889 | B60: 5.2.0 | C60: EMI-TC-5825 | D60: Other application features unaffected by migration | E60: Critical | G60: Test core application flows: fund transfer, payment, account settings. | H60: All core flows work as expected; no unexpected modals appear; no routes are broken. | I60: Not Tested | J60: Functional | K60: Web | L60: AIO (Jira) | M60: EMI-5302 | N60: No | P60: B2B
A61: EMI-B2B-6905 | B61: 5.2.0 | C61: EMI-TC-5842 | D61: Bottom nav 'Home' navigates to Home page | E61: Critical | G61: Tap the 'Home' item in the bottom navigation. | H61: User is navigated to the Home page; Home item becomes active/highlighted. | I61: Not Tested | J61: Functional | K61: Web | L61: AIO (Jira) | M61: EMI-5265 | N61: No | P61: B2B
A62: EMI-B2B-6906 | B62: 5.2.0 | C62: EMI-TC-5843 | D62: Bottom nav 'Bills' navigates to Bills page | E62: Critical | G62: Tap the 'Bills' item in the bottom navigation. | H62: User is navigated to the Bills page; Bills item becomes active/highlighted. | I62: Not Tested | J62: Functional | K62: Web | L62: AIO (Jira) | M62: EMI-5265 | N62: No | P62: B2B
A63: EMI-B2B-6907 | B63: 5.2.0 | C63: EMI-TC-5844 | D63: Bottom nav 'Accounts' navigates to Accounts page | E63: Critical | G63: Tap the 'Accounts' item in the bottom navigation. | H63: User is navigated to the Accounts page; Accounts item becomes active/highlighted. | I63: Not Tested | J63: Functional | K63: Web | L63: AIO (Jira) | M63: EMI-5265 | N63: No | P63: B2B
A64: EMI-B2B-6778 | B64: 5.2.0 | C64: EMI-TC-5284 | D64: Customer app — resend OTP has correct expiry time | E64: High | G64: After receiving resent OTP, wait beyond the configured expiry time without entering it. | H64: OTP expires after the configured window. | I64: Not Tested | J64: Functional | K64: Web | L64: AIO (Jira) | M64: EMI-5270 | N64: No | P64: B2B
A65: EMI-B2B-6779 | B65: 5.2.0 | C65: EMI-TC-5285 | D65: Customer app — operation code is correct for login resend OTP | E65: High | G65: Trigger resend OTP during login flow. Inspect API request payload sent to backend: POST /otp/resend. | H65: Request body contains correct operation code for login (e.g. OP_LOGIN or configured equivalent). | I65: Not Tested | J65: Functional | K65: API | L65: AIO (Jira) | M65: EMI-5270 | N65: No | P65: B2B
A66: EMI-B2B-6780 | B66: 5.2.0 | C66: EMI-TC-5286 | D66: Customer app — operation code is correct for password reset resend OTP | E66: High | G66: Trigger resend OTP during password reset. Inspect POST /otp/resend payload. | H66: Request contains correct operation code for password reset (e.g. OP_PWD_RESET). | I66: Not Tested | J66: Functional | K66: API | L66: AIO (Jira) | M66: EMI-5270 | N66: No | P66: B2B
A67: EMI-B2B-6781 | B67: 5.2.0 | C67: EMI-TC-5287 | D67: Customer app — operation code is correct for transaction confirmation resend OTP | E67: High | G67: Trigger resend OTP during transaction confirmation. Inspect POST /otp/resend payload. | H67: Request contains correct operation code for transaction (e.g. OP_TXN_CONFIRM). | I67: Not Tested | J67: Functional | K67: API | L67: AIO (Jira) | M67: EMI-5270 | N67: No | P67: B2B
A68: EMI-B2B-6782 | B68: 5.2.0 | C68: EMI-TC-5288 | D68: Customer app — operation code is correct for registration resend OTP | E68: High | G68: Trigger resend OTP during registration flow. Inspect POST /otp/resend payload. | H68: Request contains correct operation code for registration (e.g. OP_REGISTRATION). | I68: Not Tested | J68: Functional | K68: API | L68: AIO (Jira) | M68: EMI-5270 | N68: No | P68: B2B
... A81: EMI-B2B-6883 | B81: 5.2.0 | C81: EMI-TC-5819 | D81: 5.2.0 — all checks from: Navigate to My Wallet Links page. (4 checks) | E81: High | G81: Navigate to My Wallet Links page. Then work through each numbered check in the Expected Result in turn, returning to this starting state whenever a check changes it. | H81: 1. Side navigation highlights 'My Wallet Links' when on that page — The 'My Wallet Links' item in the side navigation is visually highlighted/active (e.g., bold, accent colour, active indicator). 2. Page title updates in browser tab when on Wallet Links page — Browser tab title updates to include 'My Wallet Links' (e.g., 'My Wallet Links | Mjd Pay'). 3. Empty state shown when user has no wallet links — An empty state message is displayed (e.g., 'No wallet links found. Add a wallet link to get started.'); the page does not show a blank or broken layout. 4. QR code is displayed for each wallet link — Page is displayed. | I81: Not Tested | J81: Functional | K81: Web | L81: AIO (Jira) | M81: EMI-5302 | N81: No | P81: B2B
A82: EMI-B2B-6892 | B82: 5.2.0 | C82: EMI-TC-5828 | D82: Home page loads within acceptable time | E82: High | F82: A signed-in business account on an environment representative of production, with a defined acceptable load time and a way to measure it. | G82: Navigate to the Home page and start a timer. | H82: 1. The home page finishes loading within the agreed time. 2. The limit is met consistently across repeated runs, not only on the best one. 3. It still holds from a cold cache and under representative concurrent load. 4. The page is genuinely interactive when it appears — balances and panels are populated, not still resolving behind a spinner. 5. No panel is left permanently loading. 6. If the limit is exceeded, the shortfall is measurable and reportable rather than a subjective impression. | I82: Not Tested | J82: Functional | K82: Web | L82: AIO (Jira) | M82: EMI-5302 | N82: No | P82: B2B
A83: EMI-B2B-6894 | B83: 5.2.0 | C83: EMI-TC-5830 | D83: Login video plays once on first load | E83: High | G83: Navigate to the login page. | H83: Login page loads and the video begins playing automatically. | I83: Not Tested | J83: Functional | K83: Web | L83: AIO (Jira) | M83: EMI-5265 | N83: No | P83: B2B
A84: EMI-B2B-6899 | B84: 5.2.0 | C84: EMI-TC-5835 | D84: Progressive bar appears during all async operations | E84: High | G84: Throttle network to slow 3G using browser dev tools. | H84: Network is throttled. | I84: Not Tested | J84: Functional | K84: Web | L84: AIO (Jira) | M84: EMI-5265 | N84: No | P84: B2B
A85: EMI-B2B-6776 | B85: 5.2.0 | C85: EMI-TC-5282 | D85: Customer app — resend attempt counter resets for a new OTP session | E85: Medium | G85: Customer initiates a new login flow (new OTP session). | H85: Fresh OTP sent. Resend attempt counter reset to 0. | I85: Not Tested | J85: Functional | K85: Web | L85: AIO (Jira) | M85: EMI-5270 | N85: No | P85: B2B
A86: EMI-B2B-6840 | B86: 5.2.0 | C86: EMI-TC-5734 | D86: Font size reduction does not affect headings or titles unless specified | E86: Medium | G86: Compare heading and title font sizes to previous build. | H86: Headings and titles unchanged if not in scope. Only specified components reduced by 2. ⚠ Confirm exact scope with dev team. | I86: Not Tested | J86: Functional | K86: Web | L86: AIO (Jira) | M86: EMI-5264 | N86: No | P86: B2B
A87: EMI-B2B-6881 | B87: 5.2.0 | C87: EMI-TC-5817 | D87: Page scrolls vertically for multiple wallet links on mobile | E87: Medium | G87: Open My Wallet Links page at 375x812 with 3+ wallet links. | H87: Cards stack vertically; user can scroll down to view all entries; no card is hidden or unreachable. | I87: Not Tested | J87: Functional | K87: Web | L87: AIO (Jira) | M87: EMI-5302 | N87: No | P87: B2B
A88: EMI-B2B-6885 | B88: 5.2.0 | C88: EMI-TC-5821 | D88: My Wallet Links page matches premium design language of updated Home page | E88: Medium | G88: Open the Home page and take a visual note of the design language (card style, colours, spacing). | H88: Home page design is observed. | I88: Not Tested | J88: Functional | K88: Web | L88: AIO (Jira) | M88: EMI-5302 | N88: No | P88: B2B
A89: EMI-B2B-6897 | B89: 5.2.0 | C89: EMI-TC-5833 | D89: Login video plays correctly on new session | E89: Medium | G89: Open the application in a fresh session (after logout or cleared session). | H89: Login page loads. | I89: Not Tested | J89: Functional | K89: Web | L89: AIO (Jira) | M89: EMI-5265 | N89: No | P89: B2B
A90: EMI-B2B-6942 | B90: 5.2.0 | C90: EMI-TC-5899 | D90: Validate that the user is able to view and click on the bread crumb at the wallet configuration | E90: Low | F90: A signed-in account able to reach the wallet configuration screen through the normal navigation. | G90: 1. Navigate to the wallet configuration screen through the normal path 2. Check the breadcrumb shown 3. Compare it with the path actually taken 4. Click each level of the breadcrumb 5. Check where each click lands 6. Check both languages and themes | H90: 1. A breadcrumb is displayed on the wallet configuration screen. 2. It reflects the actual navigation path, ending with the current screen. 3. Each earlier level is clickable and the current level is not. 4. Clicking a level navigates to that screen, not to the home page or a wrong one. 5. Navigating back through the breadcrumb does not lose unsaved data without warning. 6. The breadcrumb renders and mirrors correctly in both languages and both themes. | I90: Not Tested | J90: Functional | K90: Web | L90: AIO (Jira) | M90: EMI-5303 | N90: No | P90: B2B
A91: EMI-B2B-6943 | B91: 5.2.0 | C91: EMI-TC-5900 | D91: Validate that the user is able to view and click on the bread crumb at the sub wallet | E91: Low | F91: A signed-in account able to reach the sub wallet screen through the normal navigation. | G91: 1. Navigate to the sub wallet screen through the normal path 2. Check the breadcrumb shown 3. Compare it with the path actually taken 4. Click each level of the breadcrumb 5. Check where each click lands 6. Check both languages and themes | H91: 1. A breadcrumb is displayed on the sub wallet screen. 2. It reflects the actual navigation path, ending with the current screen. 3. Each earlier level is clickable and the current level is not. 4. Clicking a level navigates to that screen, not to the home page or a wrong one. 5. Navigating back through the breadcrumb does not lose unsaved data without warning. 6. The breadcrumb renders and mirrors correctly in both languages and both themes. | I91: Not Tested | J91: Functional | K91: Web | L91: AIO (Jira) | M91: EMI-5303 | N91: No | P91: B2B
A92: EMI-B2B-6872 | B92: 5.2.0 | C92: EMI-TC-5808 | D92: 5.2.0 — all checks from: Navigate to the My Wallet Links page. (2 checks) | E92: Critical | G92: Navigate to the My Wallet Links page. Then work through each numbered check in the Expected Result in turn, returning to this starting state whenever a check changes it. | H92: 1. My Wallet Links page displays all wallet link entries — All wallet links associated with the user's account are displayed; no entries are missing. 2. Breadcrumb displays 'Home > My Wallet Links' — My Wallet Links page is displayed. | I92: Not Tested | J92: Negative | K92: Web | L92: AIO (Jira) | M92: EMI-5302 | N92: No | P92: B2B
A93: EMI-B2B-6764 | B93: 5.2.0 | C93: EMI-TC-5270 | D93: 5.2.0 — all checks from: Tap 'Resend OTP' on the login OTP screen. (3 checks) | E93: High | G93: Tap 'Resend OTP' on the login OTP screen. Then work through each numbered check in the Expected Result in turn, returning to this starting state whenever a check changes it. | H93: 1. Customer app — resend OTP via SMS during login — New OTP delivered to registered mobile number via SMS. Resend counter increments to 1. Previous OTP is invalidated. 2. Customer app — resend OTP via Email during login — New OTP delivered to registered email address. Previous OTP invalidated. Resend counter = 1. 3. Business app — resend OTP via Email during login — New OTP email delivered. Previous OTP invalidated. | I93: Not Tested | J93: Negative | K93: Web | L93: AIO (Jira) | M93: EMI-5270 | N93: No | P93: B2B
A94: EMI-B2B-6766 | B94: 5.2.0 | C94: EMI-TC-5272 | D94: Customer app — resend OTP via SMS during password reset | E94: High | G94: Tap 'Resend OTP' on password reset OTP screen. | H94: New OTP sent via SMS. Previous OTP invalidated. Resend counter increments. | I94: Not Tested | J94: Negative | K94: Web | L94: AIO (Jira) | M94: EMI-5270 | N94: No | P94: B2B
A95: EMI-B2B-6767 | B95: 5.2.0 | C95: EMI-TC-5273 | D95: 5.2.0 — all checks from: Tap 'Resend OTP' on password reset screen. (2 checks) | E95: High | G95: Tap 'Resend OTP' on password reset screen. Then work through each numbered check in the Expected Result in turn, returning to this starting state whenever a check changes it. | H95: 1. Customer app — resend OTP via Email during password reset — New OTP email delivered. Previous OTP invalidated. 2. Business app — resend OTP via Email during password reset — New OTP email delivered. Previous OTP invalidated. | I95: Not Tested | J95: Negative | K95: Web | L95: AIO (Jira) | M95: EMI-5270 | N95: No | P95: B2B
A96: EMI-B2B-6768 | B96: 5.2.0 | C96: EMI-TC-5274 | D96: 5.2.0 — all checks from: Tap 'Resend OTP' on transaction confirmation screen. (3 checks) | E96: High | G96: Tap 'Resend OTP' on transaction confirmation screen. Then work through each numbered check in the Expected Result in turn, returning to this starting state whenever a check changes it. | H96: 1. Customer app — resend OTP via SMS during transaction confirmation — New OTP sent via SMS. Previous OTP invalidated. Resend counter increments. 2. Customer app — resend OTP via Email during transaction confirmation — New OTP email delivered. Previous OTP invalidated. 3. Business app — resend OTP via Email during transaction confirmation — New OTP email delivered. Previous OTP invalidated. | I96: Not Tested | J96: Negative | K96: Web | L96: AIO (Jira) | M96: EMI-5270 | N96: No | P96: B2B
A97: EMI-B2B-6770 | B97: 5.2.0 | C97: EMI-TC-5276 | D97: Customer app — resend OTP via SMS during account registration | E97: High | G97: Tap 'Resend OTP' on registration OTP screen. | H97: New OTP sent via SMS. Previous OTP invalidated. Resend counter = 1. | I97: Not Tested | J97: Negative | K97: Web | L97: AIO (Jira) | M97: EMI-5270 | N97: No | P97: B2B
A98: EMI-B2B-6771 | B98: 5.2.0 | C98: EMI-TC-5277 | D98: 5.2.0 — all checks from: Tap 'Resend OTP' on registration screen. (2 checks) | E98: High | G98: Tap 'Resend OTP' on registration screen. Then work through each numbered check in the Expected Result in turn, returning to this starting state whenever a check changes it. | H98: 1. Customer app — resend OTP via Email during account registration — New OTP email delivered. Previous OTP invalidated. 2. Business app — resend OTP via Email during account registration — New OTP email delivered. Previous OTP invalidated. | I98: Not Tested | J98: Negative | K98: Web | L98: AIO (Jira) | M98: EMI-5270 | N98: No | P98: B2B
A99: EMI-B2B-6777 | B99: 5.2.0 | C99: EMI-TC-5283 | D99: Customer app — previous OTP invalidated after resend | E99: High | G99: Note the first OTP received. Tap 'Resend OTP' after cooldown. | H99: New OTP sent. Old OTP is now invalid. | I99: Not Tested | J99: Negative | K99: Web | L99: AIO (Jira) | M99: EMI-5270 | N99: No | P99: B2B
A100: EMI-B2B-6783 | B100: 5.2.0 | C100: EMI-TC-5289 | D100: Customer app — operation code mismatch rejected by backend | E100: High | G100: Send POST /otp/resend with a mismatched or tampered operation code (e.g. OP_TXN_CONFIRM during a login flow). | H100: HTTP 400 or 422. Error: invalid or mismatched operation code. No OTP sent. | I100: Not Tested | J100: Negative | K100: API | L100: AIO (Jira) | M100: EMI-5270 | N100: No | P100: B2B
A101: EMI-B2B-6784 | B101: 5.2.0 | C101: EMI-TC-5290 | D101: Customer app — resend OTP with missing operation code rejected | E101: High | G101: Send POST /otp/resend with operation_code field omitted from request body. | H101: HTTP 400. Validation error: operation_code is required. No OTP sent. | I101: Not Tested | J101: Negative | K101: API | L101: AIO (Jira) | M101: EMI-5270 | N101: No | P101: B2B
A102: EMI-B2B-6788 | B102: 5.2.0 | C102: EMI-TC-5294 | D102: Business app — resend OTP via SMS during login | E102: High | G102: Tap 'Resend OTP' on the login OTP screen in the business app. | H102: New OTP delivered to registered mobile number via SMS. Previous OTP invalidated. Resend counter = 1. | I102: Not Tested | J102: Negative | K102: Web | L102: AIO (Jira) | M102: EMI-5270 | N102: No | P102: B2B
A103: EMI-B2B-6790 | B103: 5.2.0 | C103: EMI-TC-5296 | D103: Business app — resend OTP via SMS during password reset | E103: High | G103: Tap 'Resend OTP' on password reset OTP screen in business app. | H103: New OTP sent via SMS. Previous OTP invalidated. | I103: Not Tested | J103: Negative | K103: Web | L103: AIO (Jira) | M103: EMI-5270 | N103: No | P103: B2B
... A107: EMI-B2B-6805 | B107: 5.2.0 | C107: EMI-TC-5311 | D107: Business app — operation code mismatch rejected by backend | E107: High | G107: Send POST /otp/resend with wrong operation code for the current flow (e.g. OP_LOGIN during transaction flow). | H107: HTTP 400 or 422. Error: invalid or mismatched operation code. No OTP sent. | I107: Not Tested | J107: Negative | K107: API | L107: AIO (Jira) | M107: EMI-5270 | N107: No | P107: B2B
A108: EMI-B2B-6806 | B108: 5.2.0 | C108: EMI-TC-5312 | D108: Business app — resend OTP with missing operation code rejected | E108: High | G108: Send POST /otp/resend with operation_code field omitted. | H108: HTTP 400. Validation error: operation_code is required. No OTP sent. | I108: Not Tested | J108: Negative | K108: API | L108: AIO (Jira) | N108: No | P108: B2B
A109: EMI-B2B-6813 | B109: 5.2.0 | C109: EMI-TC-5707 | D109: Stepper step text is centered on small screen sizes (Android SE/compact) | E109: High | G109: Open a multi-step form on a compact Android screen. | H109: Step text centered on all steps. Text does not overflow, truncate incorrectly, or misalign due to narrow viewport. | I109: Not Tested | J109: Negative | K109: Web | L109: AIO (Jira) | M109: EMI-5264 | N109: No | P109: B2B
A110: EMI-B2B-6828 | B110: 5.2.0 | C110: EMI-TC-5722 | D110: Components inherit fill color from parent container correctly | E110: High | G110: Open Home screen. Observe card and container backgrounds. | H110: Components display parent container's background color. No mismatched default white or grey fills that contrast incorrectly with the parent background. | I110: Not Tested | J110: Negative | K110: Web | L110: AIO (Jira) | M110: EMI-5264 | N110: No | P110: B2B
A111: EMI-B2B-6829 | B111: 5.2.0 | C111: EMI-TC-5723 | D111: Fill inheritance works correctly on all major screens | E111: High | G111: Navigate through Home, Bills, Accounts, Wallet Settings, Qattah, Money Request screens. | H111: No screen shows a component with incorrect default fill that does not match the parent's background. No floating white boxes on colored backgrounds. No visual inconsistency between parent and child fills. | I111: Not Tested | J111: Negative | K111: Web | L111: AIO (Jira) | M111: EMI-5264 | N111: No | P111: B2B
A112: EMI-B2B-6835 | B112: 5.2.0 | C112: EMI-TC-5729 | D112: Trailing text appears for all limit fields, not just some | E112: High | G112: Observe all limit amount and count fields on the Limits tab. | H112: Every limit field has a trailing text showing default. No fields missing the trailing text. Consistent implementation across all limit types (daily, monthly, per-transaction). | I112: Not Tested | J112: Negative | K112: Web | L112: AIO (Jira) | M112: EMI-5264 | N112: No | P112: B2B
A113: EMI-B2B-6861 | B113: 5.2.0 | C113: EMI-TC-5797 | D113: Home page shortcut card navigates to correct destination | E113: High | G113: Click each shortcut card on the Home page one at a time. | H113: Each card navigates to its correct corresponding page or section; no 404 errors or broken routes. | I113: Not Tested | J113: Negative | K113: Web | L113: AIO (Jira) | M113: EMI-5302 | N113: No | P113: B2B
A114: EMI-B2B-6887 | B114: 5.2.0 | C114: EMI-TC-5823 | D114: No broken links or 404 errors on new Wallet Links route | E114: High | G114: Navigate to the My Wallet Links page via each entry point: side nav, Home shortcut, direct URL. | H114: Page loads successfully via all entry points; no 404, error boundary, or broken route is encountered. | I114: Not Tested | J114: Negative | K114: Web | L114: AIO (Jira) | M114: EMI-5302 | N114: No | P114: B2B
A115: EMI-B2B-6918 | B115: 5.2.0 | C115: EMI-TC-5862 | D115: Allowed Transaction Types displays all available transaction types | E115: High | G115: Navigate to the Allowed Transaction Types section. | H115: All available transaction types are listed (e.g., Transfer, Payment, Top-Up, Withdrawal); no type is missing. | I115: Not Tested | J115: Negative | K115: Web | L115: AIO (Jira) | M115: EMI-5265 | N115: No | P115: B2B
...

Sheet Deep Payment
A1: TC ID | B1: Sub-Area | C1: Source ID | D1: Title | E1: Priority | F1: Preconditions | G1: Steps | H1: Expected Result | I1: Status | J1: Test Type | K1: Interface | L1: Source | M1: Jira Ref | N1: Automated | O1: Automated By | P1: Channel
A2: EMI-B2B-1043 | B2: Deep Payment | C2: EMI-TC-6637 | D2: Guest payment with OTP success | E2: Critical | F2: OTP required by risk rule for guest | G2: 1. Start guest payment. 2. Provide valid payer info. 3. Trigger OTP. 4. Enter correct OTP within allowed time. | H2: OTP is verified; otp_verified=true recorded. User continues to gateway. Flow same as D1 on success. | I2: Not Tested | J2: Functional | K2: Web | L2: AIO (Jira) | M2: EMI-5368 | N2: No | P2: B2B
A3: EMI-B2B-1052 | B3: Deep Payment | C3: EMI-TC-6646 | D3: Session expiry during payment | E3: Critical | F3: Logged-in user session times out mid-flow | G3: 1. Start wallet payment. 2. Let session expire before confirm. 3. Try to confirm payment. | H3: User is forced to re-authenticate. Payment not executed without valid session. No inconsistent attempts created. After login, user can retry. | I3: Not Tested | J3: Functional | K3: Web | L3: AIO (Jira) | M3: EMI-5368 | N3: No | P3: B2B
A4: EMI-B2B-1074 | B4: Deep Payment | C4: EMI-TC-6668 | D4: OTP requirement is skipped when risk config does not require it | E4: Critical | F4: A payable invoice/bill with an ACTIVE payment link exists. OTP is NOT required by the current risk configuration. | G4: 1. Open hosted payment page as a guest. 2. Enter valid payer info. 3. Observe whether OTP is requested. | H4: OTP step is not presented to the payer. Payment proceeds directly to gateway without OTP. No OTP record is created. payment_attempt.otp_verified reflects false/null per defined behavior. Flow is consistent with risk config setting. | I4: Not Tested | J4: Functional | K4: Web | L4: AIO (Jira) | M4: EMI-5368 | N4: No | P4: B2B
A5: EMI-B2B-1075 | B5: Deep Payment | C5: EMI-TC-6669 | D5: Partial payment via wallet — invoice remains open, link stays ACTIVE | E5: Critical | F5: An invoice/bill supports partial payment (per invoice/bill rules). A payment link exists. Logged-in payer pays less than the full outstanding amount. | G5: 1. Open hosted payment page as a logged-in user. 2. Choose 'Pay with Wallet'. 3. Submit a partial amount (less than full outstanding). 4. Verify payment is accepted. 5. Check invoice outstanding balance. 6. Check payment link status. | H5: Payment attempt is marked SUCCESS for the partial amount. Invoice outstanding balance is reduced by the paid amount (not closed). Invoice remains in partially-paid / open state per invoice/bill rules. payment_link status remains ACTIVE (not CONSUMED). Another payment can be initiated through the same link. | I5: Not Tested | J5: Functional | K5: Web | L5: AIO (Jira) | M5: EMI-5368 | N5: No | P5: B2B
A6: EMI-B2B-1107 | B6: Deep Payment | C6: EMI-TC-6874 | D6: Regenerate QR explicitly (if API supports regenerate) | E6: Critical | F6: Payment link is ACTIVE | G6: 1. Call QR regenerate endpoint/flag. 2. Decode new QR content. 3. Compare with old QR. | H6: Depending on design: either 1) New QR resource but still resolves to same payment session, or 2) Regeneration disabled and existing QR is returned with clear message. No inconsistent states. | I6: Not Tested | J6: Functional | K6: API | L6: AIO (Jira) | M6: EMI-5428 | N6: No | P6: B2B
A7: EMI-B2B-1120 | B7: Deep Payment | C7: EMI-TC-6887 | D7: Correct commission & VAT calculation for wallet payment | E7: Critical | F7: 1. Commission & VAT configuration for payment-link wallet transactions is defined. 2. Valid wallet payment link exists. | G7: 1. Initiate wallet payment via payment link for a known amount. | H7: 1. System calculates commission according to configuration. 2. System calculates VAT on commission/amount as defined. 3. Net amount credited/debited is correct. 4. Ledger entries reflect commission and VAT amounts correctly. | I7: Not Tested | J7: Functional | K7: Web | L7: AIO (Jira) | M7: EMI-5442 | N7: No | P7: B2B
A8: EMI-B2B-1121 | B8: Deep Payment | C8: EMI-TC-6888 | D8: Correct commission & VAT calculation for guest payment | E8: Critical | F8: 1. Commission & VAT configuration for payment-link guest/gateway transactions is defined. | G8: 1. Initiate guest payment via payment link for a known amount. | H8: 1. Commission and VAT values are calculated per configuration. 2. Business/net settlement amounts are correct. 3. Ledger entries reflect correct breakdown (principal, commission, VAT). | I8: Not Tested | J8: Functional | K8: Web | L8: AIO (Jira) | M8: EMI-5442 | N8: No | P8: B2B
A9: EMI-B2B-1129 | B9: Deep Payment | C9: EMI-TC-6896 | D9: Ledger entries for wallet payment – bank/reserve split | E9: Critical | F9: 1. Configuration exists for bank/reserve split for wallet transactions via payment link. 2. Valid wallet payment link. | G9: 1. Perform a successful wallet payment via link. | H9: 1. Ledger entries created for customer wallet debit, business/beneficiary credit. 2. Bank/reserve split entries are created as per rules. 3. All amounts balance correctly (accounting equation holds). | I9: Not Tested | J9: Functional | K9: Web | L9: AIO (Jira) | M9: EMI-5442 | N9: No | P9: B2B
A10: EMI-B2B-1130 | B10: Deep Payment | C10: EMI-TC-6897 | D10: Ledger entries for guest payment – bank/reserve split | E10: Critical | F10: 1. Configuration exists for bank/reserve split for gateway transactions. | G10: 1. Perform a successful guest payment via link. | H10: 1. Ledger entries reflect gateway/bank accounts and reserve postings correctly. 2. Commission and VAT are posted to correct GL accounts. 3. Entries fully balanced. | I10: Not Tested | J10: Functional | K10: Web | L10: AIO (Jira) | M10: EMI-5442 | N10: No | P10: B2B
A11: EMI-B2B-1187 | B11: Deep Payment | C11: EMI-TC-7033 | D11: Download action saves QR/link artifact successfully | E11: Critical | F11: Successful link generation; storage/photos permission allowed (if required) | G11: 1. Tap Download. 2. Approve permission prompts (if shown). | H11: File/image is saved successfully (Photos/Files per implementation). User gets a success confirmation (toast/snackbar) if designed. | I11: Not Tested | J11: Functional | K11: Web | L11: AIO (Jira) | M11: EMI-5461 | N11: No | P11: B2B
A12: EMI-B2B-1221 | B12: Deep Payment | C12: EMI-TC-7067 | D12: OTP – Successful Verification | E12: Critical | F12: On OTP screen; valid OTP delivered | G12: 1. Enter correct OTP 2. Submit | H12: OTP verified; user moves to Payment step and payment is triggered | I12: Not Tested | J12: Functional | K12: Web | L12: AIO (Jira) | M12: EMI-5463 | N12: No | P12: B2B
A13: EMI-B2B-1232 | B13: Deep Payment | C13: EMI-TC-7078 | D13: Full Navigation – Wallet | E13: Critical | F13: Valid wallet link | G13: 1. Link Entry → Summary → Payer Info (with amount) → [OTP] → Payment → Result | H13: Same as TC-32 but including amount field; all transitions correct and data preserved | I13: Not Tested | J13: Functional | K13: Web | L13: AIO (Jira) | M13: EMI-5463 | N13: No | P13: B2B
... A158: EMI-B2B-1111 | B158: Deep Payment | C158: EMI-TC-6878 | D158: Generate QR for invalid status link (EXPIRED/CANCELLED) | E158: High | F158: Payment link exists but not ACTIVE | G158: 1. Call QR generate for EXPIRED/CANCELLED link ID. | H158: API rejects with 4xx error indicating invalid link status; no QR created. | I158: Not Tested | J158: Negative | K158: Web | L158: AIO (Jira) | M158: EMI-5428 | N158: No | P158: B2B
A159: EMI-B2B-1112 | B159: Deep Payment | C159: EMI-TC-6879 | D159: Malformed request payload | E159: High | G159: 1. Call QR generate with missing mandatory fields / invalid JSON. | H159: API returns 400 Bad Request with validation errors; no QR generated. | I159: Not Tested | J159: Negative | K159: API | L159: AIO (Jira) | M159: EMI-5428 | N159: No | P159: B2B
A160: EMI-B2B-1132 | B160: Deep Payment | C160: EMI-TC-6899 | D160: Invoice/bill remains unchanged on payment failure | E160: High | F160: 1. Invoice/bill is “Pending/Unpaid”. | G160: 1. Attempt payment via link that fails (e.g. gateway decline). | H160: 1. Invoice/bill status remains “Pending/Unpaid”. 2. No partial updates to invoice financial fields occur. | I160: Not Tested | J160: Negative | K160: Web | L160: AIO (Jira) | M160: EMI-5442 | N160: No | P160: B2B
A161: EMI-B2B-1165 | B161: Deep Payment | C161: EMI-TC-7011 | D161: Error state – network error | E161: High | F161: Simulate network failure (e.g., offline mode) | G161: 1. Turn off network. 2. Open Payment Link Management screen or pull-to-refresh. | H161: Error state UI appears with proper message and retry option; no crash. | I161: Not Tested | J161: Negative | K161: Web | L161: AIO (Jira) | M161: EMI-5460 | N161: No | P161: B2B
A162: EMI-B2B-1166 | B162: Deep Payment | C162: EMI-TC-7012 | D162: Error state – API error (server 5xx) | E162: High | F162: Simulate server error from backend | G162: 1. Open screen while backend returns error. | H162: Error message is displayed; user can retry; previous data not incorrectly shown as updated. | I162: Not Tested | J162: Negative | K162: Web | L162: AIO (Jira) | M162: EMI-5460 | N162: No | P162: B2B
A163: EMI-B2B-1167 | B163: Deep Payment | C163: EMI-TC-7013 | D163: Retry from error state | E163: High | F163: User currently sees error state | G163: 1. On error state, tap “Retry”. 2. Ensure backend is healthy. | H163: System retries fetch; when successful, normal list is displayed. | I163: Not Tested | J163: Negative | K163: Web | L163: AIO (Jira) | M163: EMI-5460 | N163: No | P163: B2B
A164: EMI-B2B-1176 | B164: Deep Payment | C164: EMI-TC-7022 | D164: Payment Links module loads without crash | E164: High | F164: Business app installed; user logged in | G164: 1. Open Business app. 2. Navigate to Bills area and open any bill details (where feature is exposed). | H164: App does not crash. Payment Links feature area loads normally (no missing module/dependency errors). | I164: Not Tested | J164: Negative | K164: Web | L164: AIO (Jira) | M164: EMI-5461 | N164: No | P164: B2B
A165: EMI-B2B-1183 | B165: Deep Payment | C165: EMI-TC-7029 | D165: QR code is rendered successfully | E165: High | F165: Successful link generation | G165: 1. Open link creation screen. | H165: QR code is displayed (not blank/placeholder/error). | I165: Not Tested | J165: Negative | K165: Web | L165: AIO (Jira) | M165: EMI-5461 | N165: No | P165: B2B
A166: EMI-B2B-1193 | B166: Deep Payment | C166: EMI-TC-7039 | D166: Retry after generation failure works | E166: High | F166: Mock/backend can return failure then success | G166: 1. Configure failure response. 2. Tap Share Payment Link → observe error. 3. Configure success response. 4. Retry. | H166: On failure: user sees friendly error + can retry. On retry: link generation succeeds and screen opens. | I166: Not Tested | J166: Negative | K166: Web | L166: AIO (Jira) | M166: EMI-5461 | N166: No | P166: B2B
A167: EMI-B2B-1194 | B167: Deep Payment | C167: EMI-TC-7040 | D167: Offline/no network handling for generation | E167: High | F167: Device offline OR mock simulates no network | G167: 1. Disable network. 2. Tap Share Payment Link. | H167: Clear offline/network error shown. No crash; user can retry after reconnecting. | I167: Not Tested | J167: Negative | K167: Web | L167: AIO (Jira) | M167: EMI-5461 | N167: No | P167: B2B
A168: EMI-B2B-1195 | B168: Deep Payment | C168: EMI-TC-7041 | D168: Mock API support: all required endpoints used in flow | E168: High | F168: App configured to use mock environment | G168: 1. Run full flow (bill details → generate → copy/share/download). | H168: Flow completes using mock endpoints without missing/404 errors. | I168: Not Tested | J168: Negative | K168: Web | L168: AIO (Jira) | M168: EMI-5461 | N168: No | P168: B2B
A169: EMI-B2B-1196 | B169: Deep Payment | C169: EMI-TC-7042 | D169: Mock API error mapping: 4xx/5xx shows correct message | E169: High | F169: Mock returns 400/401/500 (as applicable) | G169: 1. Trigger link generation with each error response type. | H169: App shows appropriate error messaging and remains usable (no crash, no infinite loader). | I169: Not Tested | J169: Negative | K169: Web | L169: AIO (Jira) | M169: EMI-5461 | N169: No | P169: B2B
A170: EMI-B2B-1197 | B170: Deep Payment | C170: EMI-TC-7043 | D170: Bill “target types” coverage for link generation | E170: High | F170: Multiple bill target types exist per requirements | G170: 1. For each bill target type, open bill details. 2. Tap Share Payment Link. | H170: Link generation supported for each required target type (no unsupported/incorrect routing). | I170: Not Tested | J170: Negative | K170: Web | L170: AIO (Jira) | M170: EMI-5461 | N170: No | P170: B2B
A171: EMI-B2B-1212 | B171: Deep Payment | C171: EMI-TC-7058 | D171: Payer Info – Mobile Format | E171: High | F171: On Payer Info screen | G171: 1. Enter invalid mobile format (e.g., letters, too short/long) 2. Continue | H171: Field shows error; user cannot proceed until a valid mobile number is entered | I171: Not Tested | J171: Negative | K171: Web | L171: AIO (Jira) | M171: EMI-5463 | N171: No | P171: B2B
... A702: EMI-B2B-1718 | B702: Deep Payment | C702: EMI-TC-7663 | D702: Accessibility – VoiceOver labels | E702: Low | F702: VoiceOver enabled | G702: 1. Enable VoiceOver 2. Navigate to Payment Link Management screen 3. Focus on list items and controls | H702: All interactive elements (filters, list items, cancel button) have proper accessibility labels and hints; status, expiry, and access count are read meaningfully. | I702: Not Tested | J702: Usability | K702: Web | L702: AIO (Jira) | M702: EMI-5459 | N702: No | P702: B2B

Sheet PoS Transactions
A1: TC ID | B1: Sub-Area | C1: Source ID | D1: Title | E1: Priority | F1: Preconditions | G1: Steps | H1: Expected Result | I1: Status | J1: Test Type | K1: Interface | L1: Source | M1: Jira Ref | N1: Automated | O1: Automated By | P1: Channel
A2: EMI-B2B-3226 | B2: ACH & VIBAN per TID | C2: TC-ACH-01 | D2: Matched Aggregate – ACH Item Generation | E2: Critical | F2: Aggregate is matched and funded by Reconciliation; merchant is eligible | G2: 1. Handoff matched aggregate to settlement. 2. Build settlement batch. 3. Inspect generated ACH item. | H2: One settlement item is created per TID group. item_ref, batch_ref, TID, wallet, VIBAN and aggregate net amount are persisted. Item is AWAITING_APPROVAL. | I2: NA | J2: Functional | K2: Web | L2: New (this audit) | N2: No | P2: B2B
A3: EMI-B2B-3229 | B3: ACH & VIBAN per TID | C3: TC-ACH-04 | D3: Gate 2 – Business Eligibility and Sanctions Check | E3: Critical | F3: Aggregate matched; merchant status changes after initial screening | G3: 1. Change business eligibility before batch release. 2. Run Gate 2. 3. Repeat with a newly matched sanctions hit. | H3: Failed eligibility or sanctions screening excludes the item from release. Funds remain in the omnibus. No ACH instruction is released. | I3: NA | J3: Functional | K3: Web | L3: New (this audit) | N3: No | P3: B2B
A4: EMI-B2B-3230 | B4: ACH & VIBAN per TID | C4: TC-ACH-05 | D4: ACH Reference Propagation | E4: Critical | F4: Valid settlement item with known batch_ref | G4: 1. Generate ACH instruction. 2. Inspect ACH request. | H4: batch_ref is written to the ACH notes/remittance field unchanged. The same reference is available for subsequent clearing. | I4: NA | J4: Functional | K4: Web | L4: New (this audit) | N4: No | P4: B2B
A5: EMI-B2B-3231 | B5: ACH & VIBAN per TID | C5: TC-ACH-06 | D5: Maker-Checker Approval | E5: Critical | F5: Default automatic mode is disabled | G5: 1. Generate valid ACH items. 2. Review approval status. 3. Finance approves. 4. Release transfer. | H5: ACH item cannot be released before Finance approval. Approval and release are audit logged with actor and batch_ref. | I5: NA | J5: Functional | K5: Web | L5: New (this audit) | N5: No | P5: B2B
A6: EMI-B2B-3233 | B6: ACH & VIBAN per TID | C6: TC-ACH-08 | D6: Intraday Credit Clears Pending Cash-In | E6: Critical | F6: ACH executed; intraday statement contains credit with matching batch_ref; credit amount equals pending amount | G6: 1. Process intraday statement. 2. Find credit using batch_ref. 3. Check pending cash-in. | H6: Existing aggregated CASH IN changes from PENDING → SUCCESSFUL. Member per-TID entries settle accordingly. No new cash-in is created. | I6: NA | J6: Functional | K6: Web | L6: New (this audit) | N6: No | P6: B2B
A7: EMI-B2B-3234 | B7: ACH & VIBAN per TID | C7: TC-ACH-09 | D7: Intraday Credit Amount Mismatch | E7: Critical | F7: Credit reference matches batch_ref, but credited amount differs from pending amount | G7: 1. Process intraday statement. 2. Match reference. 3. Compare amounts. | H7: Pending cash-in remains unchanged/PENDING. Nothing is partially cleared. Item moves to discrepancy queue. No additional cash-in is booked. | I7: NA | J7: Functional | K7: Web | L7: New (this audit) | N7: No | P7: B2B
A8: EMI-B2B-3235 | B8: ACH & VIBAN per TID | C8: TC-ACH-10 | D8: Credit Without Valid Reference | E8: Critical | F8: Intraday credit has no recognizable batch_ref or contains a malformed/truncated reference | G8: 1. Process statement credit. 2. Run clearing job. | H8: Credit is parked for Ops. No matching by amount/date is attempted. No pending cash-in is cleared. Reference integrity issue is raised. | I8: NA | J8: Functional | K8: Web | L8: New (this audit) | N8: No | P8: B2B
A9: EMI-B2B-3238 | B9: ACH & VIBAN per TID | C9: TC-ACH-13 | D9: Transfer Returned After Successful Clearing | E9: Critical | F9: Pending cash-in was cleared successfully; bank subsequently returns the transfer | G9: 1. Process return notification. 2. Reverse the cleared cash-in. | H9: An explicit compensating reversal entry is created. Original entry is not deleted or amended. Reversal carries the same batch_ref. | I9: NA | J9: Functional | K9: Web | L9: New (this audit) | N9: No | P9: B2B
A10: EMI-B2B-3242 | B10: ACH & VIBAN per TID | C10: TC-ACH-17 | D10: Unmatched or Held Aggregate Excluded | E10: Critical | F10: Aggregate exists but is unmatched, unfunded, or in COMPLIANCE_HOLD (Gate 1) | G10: 1. Attempt to build settlement batch. 2. Inspect generated ACH items. | H10: No ACH instruction is generated at all for the unmatched/held aggregate. Funds are not moved. | I10: NA | J10: Functional | K10: Web | L10: New (this audit) | N10: No | P10: B2B
A11: EMI-B2B-3303 | B11: ACH & VIBAN per TID | C11: TC-ACH-78 | D11: Valid Payment ID and exact amount clears the matching pending aggregate | E11: Critical | F11: A pending POS settlement aggregate exists with a valid Payment id and known expected amount. An inbound bank statement credit is available. | G11: 1. Process the inbound statement. 2. Provide the matching Payment id. 3. Verify the credited amount equals the pending aggregate amount. 4. Run the intraday settlement job. | H11: The correct pending aggregate is identified and cleared. Settlement is completed against the existing aggregate. | I11: Not Tested | J11: Functional | K11: Web | L11: New (this audit) | N11: No | P11: B2B
A12: EMI-B2B-3304 | B12: ACH & VIBAN per TID | C12: TC-ACH-79 | D12: Intraday credit does not create a new CASH IN | E12: Critical | F12: A pending POS aggregate exists and its corresponding bank credit is available. | G12: 1. Record the ledger state before processing. 2. Process the inbound statement through the intraday job. 3. Review the ledger after processing. | H12: The existing pending aggregate is cleared. No additional/new CASH IN transaction is created for the same settlement. | I12: Not Tested | J12: Functional | K12: Web | L12: New (this audit) | N12: No | P12: B2B
A13: EMI-B2B-3305 | B13: ACH & VIBAN per TID | C13: TC-ACH-80 | D13: Successful aggregate settlement settles all member POS transactions | E13: Critical | F13: A settlement aggregate contains multiple POS member transactions. Matching bank credit is available. | G13: 1. Process the matching bank credit. 2. Run intraday settlement. 3. Review the aggregate and all member transactions. | H13: The aggregate is settled and all eligible member POS transactions are moved to the appropriate settled state. | I13: Not Tested | J13: Functional | K13: Web | L13: New (this audit) | N13: No | P13: B2B
... A180: EMI-B2B-3404 | B180: Non-Functional | C180: PT-NFR-01 | D180: Callback ingestion sustains terminal peak load | E180: Critical | F180: Peak terminal callback volume | G180: 1. Drive sustained callback load and measure ingestion latency and error rate | H180: Every callback is ingested exactly once within the agreed latency; none is dropped under load | I180: Not Tested | J180: Performance / NFR | K180: Web | L180: New (this audit) | N180: No | P180: B2B
A181: EMI-B2B-3466 | B181: POS | C181: EMI-TC-8481 | D181: Admin KPI cards | E181: High | G181: 1. Open PoS Orders | H181: Cards shown: Open orders, Awaiting export, With provider, Active | I181: Not Tested | J181: Functional | K181: Web | L181: AIO (Jira) | M181: EMI-5786 | N181: No | P181: B2B
A182: EMI-B2B-3475 | B182: POS | C182: EMI-TC-8490 | D182: Full provisioning lifecycle transitions | E182: High | G182: 1. Walk an order through: Validating → Approved → Sent to Provider → Shipping → Activating → Active | H182: Each transition succeeds; timeline logged | I182: Not Tested | J182: Functional | K182: Web | L182: AIO (Jira) | M182: EMI-5786 | N182: No | P182: B2B
A183: EMI-B2B-3478 | B183: POS | C183: EMI-TC-8493 | D183: Mark as Sent to Provider (bulk) | E183: High | G183: 1. After export, select exported orders 2. Click Mark as Sent to Provider | H183: Status updates for all selected orders | I183: Not Tested | J183: Functional | K183: Web | L183: AIO (Jira) | M183: EMI-5786 | N183: No | P183: B2B
A184: EMI-B2B-3486 | B184: POS | C184: EMI-TC-8501 | D184: Cancellation before Sent to Provider | E184: High | G184: 1. Cancel an Approved order | H184: Order cancelled successfully | I184: Not Tested | J184: Functional | K184: Web | L184: AIO (Jira) | M184: EMI-5786 | N184: No | P184: B2B
A185: EMI-B2B-3487 | B185: POS | C185: EMI-TC-8502 | D185: Cancellation after Sent to Provider blocked | E185: High | G185: 1. Attempt to cancel a Sent to Provider order | H185: Cancellation is blocked | I185: Not Tested | J185: Functional | K185: Web | L185: AIO (Jira) | M185: EMI-5786 | N185: No | P185: B2B
A186: EMI-B2B-3494 | B186: POS | C186: EMI-TC-8514 | D186: Workflow: full provisioning lifecycle | E186: High | G186: 1. Transition order through all states | H186: Each transition succeeds: Requesting → Validating → Approved → Sent to Provider → Shipping → Activating → Active | I186: Not Tested | J186: Functional | K186: Web | L186: AIO (Jira) | M186: EMI-5788 | N186: No | P186: B2B
A187: EMI-B2B-3405 | B187: POS | C187: EMI-TC-8420 | D187: POS product analysis report generates | E187: Medium | G187: 1. Trigger POS product analysis via admin | H187: Analysis report is generated with relevant PoS metrics | I187: Not Tested | J187: Functional | K187: Web | L187: AIO (Jira) | M187: EMI-5746 | N187: No | P187: B2B
A188: EMI-B2B-3406 | B188: POS | C188: EMI-TC-8421 | D188: Data accuracy validation | E188: Medium | G188: 1. Compare analysis output with raw PoS data | H188: All values match source data | I188: Not Tested | J188: Functional | K188: Web | L188: AIO (Jira) | M188: EMI-5746 | N188: No | P188: B2B
A189: EMI-B2B-3408 | B189: POS | C189: EMI-TC-8423 | D189: Bill Items rename | E189: Medium | G189: 1. Open More menu on iOS | H189: Old "Products" entry now reads "Bill Items" | I189: Not Tested | J189: Functional | K189: Web | L189: AIO (Jira) | M189: EMI-5782 | N189: No | P189: B2B
A190: EMI-B2B-3409 | B190: POS | C190: EMI-TC-8424 | D190: New Products section with tabs | E190: Medium | G190: 1. Tap Products in More menu | H190: Two tabs appear: "My Products" and "All Products" | I190: Not Tested | J190: Functional | K190: Web | L190: AIO (Jira) | M190: EMI-5782 | N190: No | P190: B2B
A191: EMI-B2B-3411 | B191: POS | C191: EMI-TC-8426 | D191: Manage CTA for active subscription | E191: Medium | G191: 1. Open All Products as user with active PoS | H191: CTA reads "Manage" instead of "Configure & Request" | I191: Not Tested | J191: Functional | K191: Web | L191: AIO (Jira) | M191: EMI-5782 | N191: No | P191: B2B
A192: EMI-B2B-3412 | B192: POS | C192: EMI-TC-8427 | D192: Order in Progress badge | E192: Medium | G192: 1. Open All Products with a pending PoS order | H192: "Order in Progress" badge shown on PoS card | I192: Not Tested | J192: Functional | K192: Web | L192: AIO (Jira) | M192: EMI-5782 | N192: No | P192: B2B
... A296: EMI-B2B-3516 | B296: POS | C296: EMI-TC-8629 | D296: Payer info removed (bill payment) - Android | E296: Low | G296: 1. Open Payment Link for bill payment on Android | H296: No payer info screen | I296: Not Tested | J296: Usability | K296: Web | L296: AIO (Jira) | M296: EMI-5791 | N296: No | P296: B2B
A297: EMI-B2B-3523 | B297: PoS Commission Config | C297: TC-Commission-03 | D297: PoS Settlement Cash-In Is Distinguished From a Wallet Top-Up | E297: High | F297: A PoS settlement cash-in and an ordinary wallet top-up, both standard CASH IN | G297: 1. Price both 2. Compare the schemes resolved and the fees charged | H297: The PoS settlement cash-in is priced by the PoS scheme and the top-up by its own; the Platform value is what separates them; a PoS settlement is never priced as a generic top-up | I297: Not Tested | J297: Functional | K297: Web | L297: New (this audit) | N297: No | P297: B2B
A298: EMI-B2B-3524 | B298: PoS Commission Config | C298: TC-Commission-04 | D298: The Priced Object Is the Aggregated Cash-In per Settlement Batch | E298: High | F298: A settlement batch created in EMI-5989 with Platform = PoS | G298: 1. Inspect the object passed to the commission engine at pricing time | H298: The priced object is the aggregated cash-in for the batch, carrying Platform = PoS; no individual card transaction is passed to the engine | I298: Not Tested | J298: Functional | K298: Web | L298: New (this audit) | N298: No | P298: B2B
A299: EMI-B2B-3526 | B299: PoS Commission Config | C299: TC-Commission-06 | D299: Commission Base Is the Net That Arrived, Not Gross | E299: High | F299: A settlement batch whose Net Settlement Amount is already net of ANB interchange, scheme fee and ANB VAT | G299: 1. Price the batch 2. Compare the commission base with the Net Settlement Amount and with the gross | H299: The base is the net amount that arrived; ANB's interchange, scheme fee, VAT and other charges are never recalculated, never added back and never priced on gross | I299: Not Tested | J299: Functional | K299: Web | L299: New (this audit) | N299: No | P299: B2B
A300: EMI-B2B-3528 | B300: PoS Commission Config | C300: TC-Commission-08 | D300: Business - Specific Scheme Wins Over the Default | E300: High | F300: A default PoS scheme and a merchant-specific PoS scheme for the same TXN type | G300: 1. Price a batch for that business | H300: The business-specific scheme is applied; most specific wins under the engine's existing precedence | I300: Not Tested | J300: Functional | K300: Web | L300: New (this audit) | N300: No | P300: B2B
A301: EMI-B2B-3531 | B301: PoS Commission Config | C301: TC-Commission-11 | D301: Business With No PoS Scheme Is Credited the Full Batch Net | E301: High | F301: Merchant with no PoS scheme at merchant, group or default level | G301: 1. Run a settlement batch for that business through ACH preparation 2. Inspect the credit and the fee entries | H301: The business is credited the full batch net with no fee entries; this is a normal outcome and not an error, and nothing is alarmed | I301: Not Tested | J301: Functional | K301: Web | L301: New (this audit) | N301: No | P301: B2B
A302: EMI-B2B-3527 | B302: PoS Commission Config | C302: TC-Commission-07 | D302: VAT Applied by the Existing Dual-Commission Machinery | E302: Medium | F302: PoS scheme configured with VAT treatment | G302: 1. Price a batch and inspect the VAT entry | H302: VAT is applied at the prevailing rate by the engine's existing dual-commission and VAT machinery; no VAT logic is introduced by this story | I302: Not Tested | J302: Functional | K302: Web | L302: New (this audit) | N302: No | P302: B2B
A303: EMI-B2B-3529 | B303: PoS Commission Config | C303: TC-Commission-09 | D303: Group Scheme Wins Over the Default When No Business Scheme Exists | E303: Medium | F303: A default and a group PoS scheme; merchant belongs to the group and has no merchant-level scheme | G303: 1. Price a batch for that business | H303: The group scheme is applied, ahead of the default and behind any business-level scheme | I303: Not Tested | J303: Functional | K303: Web | L303: New (this audit) | N303: No | P303: B2B
A304: EMI-B2B-3530 | B304: PoS Commission Config | C304: TC-Commission-10 | D304: Scheme Key Follows Business | Group | Default x Platform x TXN Type | E304: Medium | F304: Schemes configured at all three levels | G304: 1. Price batches for a business with each combination present and absent in turn | H304: Resolution follows the documented precedence in every combination; the most specific configured scheme always wins | I304: Not Tested | J304: Functional | K304: Web | L304: New (this audit) | N304: No | P304: B2B
A305: EMI-B2B-3546 | B305: PoS Commission Config | C305: TC-Commission-26 | D305: Business Sees Commission on the Cleared Cash-In, Rendered Elsewhere | E305: Medium | F305: A priced and cleared PoS settlement cash-in | G305: 1. Open the business view of the cleared cash-in (EMI-5916) 2. Check for a tax invoice from EMI-6018 | H305: The business sees the commission on the cleared cash-in rendered by EMI-5916 and receives the tax invoice from EMI-6018; this story builds no business-facing surface of its own | I305: Not Tested | J305: Functional | K305: Web | L305: New (this audit) | N305: No | P305: B2B
A306: EMI-B2B-3548 | B306: PoS Commission Config | C306: TC-Commission-28 | D306: Scheme Resolution Precedence Across the Full Key Matrix | E306: Medium | F306: Schemes configured across merchant, group and default levels and across the optional dimensions the engine supports | G306: 1. Price batches across every combination of the full scheme key, including any optional dimension such as MCC 2. Record which scheme resolves in each case | H306: Most-specific-wins holds across the whole key in every combination, not only the business-versus-default cases | I306: Not Tested | J306: Functional | K306: Web | L306: New (this audit) | N306: No | P306: B2B
A307: EMI-B2B-3549 | B307: PoS Commission Config | C307: TC-Commission-29 | D307: Wallet Instrument Resolves a Different Scheme From Card for the Same Business | E307: Medium | F307: One merchant with both a card PoS scheme and a wallet-payment scheme configured | G307: 1. Price a card settlement batch for the business 2. Price a wallet payment at terminal for the same business 3. Compare the schemes resolved | H307: Each instrument resolves its own scheme; a wallet payment is never priced by the card settlement scheme or the reverse | I307: Not Tested | J307: Functional | K307: Web | L307: New (this audit) | N307: No | P307: B2B
A308: EMI-B2B-3532 | B308: PoS Commission Config | C308: TC-Commission-12 | D308: PoS Settlement Credit Is Excluded From the Generic VIBAN Cash-In Fee | E308: High | F308: Generic VIBAN cash-in fee scheme active; PoS scheme configured; a settlement credit arriving as a VIBAN transfer | G308: 1. Run the settlement credit end to end 2. List every fee entry raised against it | H308: Only the PoS commission is charged; the generic VIBAN cash-in fee is not applied; the batch is priced once and only once | I308: Not Tested | J308: Negative | K308: Web | L308: New (this audit) | N308: No | P308: B2B
... A409: EMI-B2B-3632 | B409: POS Order Contact Details | C409: TC-Contact-13 | D409: Single-Group Order Still Works | E409: Medium | F409: A POS request with one delivery group | G409: 1. Create and submit a single-group order with contact details | H409: The single-group path is unaffected and the contact pair is stored and displayed correctly | I409: Not Tested | J409: Regression | K409: Web | L409: New (this audit) | N409: No | P409: B2B
A410: EMI-B2B-3634 | B410: PoS Refunds | C410: TC-Refund-01 | D410: Refund Captured Against a Known Settled Original | E410: High | F410: A PURCHASE for the same terminal has been captured and settled; refund endpoint reachable | G410: 1. Submit a REFUND event referencing the settled original 2. Inspect the per-TID ledger, the original record and the business wallet balance | H410: Refund written to the terminal's per-TID ledger with full detail and its terminal-reported status; original flagged refunded; business wallet balance unchanged | I410: Not Tested | J410: Functional | K410: Web | L410: New (this audit) | N410: Yes | O410: PosTransactions/api/PosRefunds.spec.ts | P410: B2B
A411: EMI-B2B-3636 | B411: PoS Refunds | C411: TC-Refund-03 | D411: No Wallet Entry, Pending, Fee or Balance Movement on Capture | E411: High | F411: Merchant wallet with a known balance | G411: 1. Capture a refund for that business 2. Query wallet entries, pending positions, fee entries and the balance | H411: No wallet entry, no pending, no fee and no balance movement is created; the ledger entry is the only artefact | I411: Not Tested | J411: Functional | K411: Web | L411: New (this audit) | N411: Yes | O411: PosTransactions/api/PosRefunds.spec.ts | P411: B2B
A412: EMI-B2B-3637 | B412: PoS Refunds | C412: TC-Refund-04 | D412: settlement_expected Is Derived False at Capture | E412: High | F412: Refund capture available | G412: 1. Capture a refund 2. Read settlement_expected on the stored record | H412: settlement_expected is derived as false at capture time, per EMI-5915 section H | I412: Not Tested | J412: Functional | K412: Web | L412: New (this audit) | N412: Yes | O412: PosTransactions/api/PosRefunds.spec.ts | P412: B2B
A413: EMI-B2B-3639 | B413: PoS Refunds | C413: TC-Refund-06 | D413: Refund Never Enters the E13 Candidate Set | E413: High | F413: A captured refund and a reconciliation run for the same date | G413: 1. Run reconciliation (EMI-5920) for the date 2. Inspect the E13 candidate set and the discrepancy queue | H413: The refund is absent from the E13 candidate set and from the discrepancy queue; it is never reported as money the bank failed to settle | I413: Not Tested | J413: Functional | K413: Web | L413: New (this audit) | N413: Yes | O413: PosTransactions/api/PosRefunds.spec.ts | P413: B2B
A414: EMI-B2B-3640 | B414: PoS Refunds | C414: TC-Refund-07 | D414: Refund Searched For in the Settlement Report | E414: High | F414: A captured refund and the corresponding ANB settlement report | G414: 1. Search the settlement report for the refund | H414: The refund is absent by ANB's settled-only contract; its absence raises no exception and creates no reconciliation discrepancy | I414: Not Tested | J414: Functional | K414: Web | L414: New (this audit) | N414: Yes | O414: PosTransactions/api/PosRefunds.spec.ts | P414: B2B
A415: EMI-B2B-3643 | B415: PoS Refunds | C415: TC-Refund-10 | D415: Refund Is Linked to Its Original Sale | E415: High | F415: A captured original PURCHASE | G415: 1. Capture a refund carrying original_provider_txn_id 2. Inspect the linkage on both records | H415: The refund resolves to and is linked with its original sale; the link is navigable from either side | I415: Not Tested | J415: Functional | K415: Web | L415: New (this audit) | N415: Yes | O415: PosTransactions/api/PosRefunds.spec.ts | P415: B2B
A416: EMI-B2B-3644 | B416: PoS Refunds | C416: TC-Refund-11 | D416: Linkage Is Enforced at Database Level | E416: High | F416: Direct database access available | G416: 1. Attempt to insert a refund row with an original reference that does not exist, bypassing the application | H416: The database rejects the write; linkage is enforced by constraint, not by application code alone | I416: Not Tested | J416: Functional | K416: Web | L416: New (this audit) | N416: No | P416: B2B
A417: EMI-B2B-3645 | B417: PoS Refunds | C417: TC-Refund-12 | D417: Original Flagged refunded on a Full Refund | E417: Medium | F417: A captured original with no prior refunds | G417: 1. Capture a refund for the original's full gross amount 2. Read the original's flag | H417: The original is flagged refunded | I417: Not Tested | J417: Functional | K417: Web | L417: New (this audit) | N417: Yes | O417: PosTransactions/api/PosRefunds.spec.ts | P417: B2B
A418: EMI-B2B-3646 | B418: PoS Refunds | C418: TC-Refund-13 | D418: Original Flagged partially_refunded on a Partial Refund | E418: Medium | F418: A captured original with no prior refunds | G418: 1. Capture a refund for part of the original's gross 2. Read the original's flag | H418: The original is flagged partially_refunded | I418: Not Tested | J418: Functional | K418: Web | L418: New (this audit) | N418: Yes | O418: PosTransactions/api/PosRefunds.spec.ts | P418: B2B
A419: EMI-B2B-3667 | B419: PoS Refunds | C419: TC-Refund-34 | D419: Refund Against an Original That Was Never Settled | E419: Medium | F419: An original captured but never settled by the bank | G419: 1. Capture a refund against it | H419: The refund is captured and linked, and flagged for Ops as an anomaly worth seeing | I419: Not Tested | J419: Functional | K419: Web | L419: New (this audit) | N419: No | P419: B2B
A420: EMI-B2B-3641 | B420: PoS Refunds | C420: TC-Refund-08 | D420: Mandatory Field Validation on Capture | E420: High | F420: Refund capture available | G420: 1. Submit refunds each missing one of rrn, amount, occurred_at, original_provider_txn_id | H420: Each is rejected with a clear validation reason and alarmed; capture rejections are never silent | I420: Not Tested | J420: Negative | K420: Web | L420: New (this audit) | N420: Yes | O420: PosTransactions/api/PosRefunds.spec.ts | P420: B2B
A421: EMI-B2B-3647 | B421: PoS Refunds | C421: TC-Refund-14 | D421: Cumulative Refunds May Not Exceed the Original Gross | E421: High | F421: A captured original with one partial refund already applied | G421: 1. Capture a second refund that would take the cumulative total above the original's gross | H421: The second refund is rejected at database level by constraint and alarmed as a feed-integrity defect; the exposure figure is not inflated | I421: Not Tested | J421: Negative | K421: Web | L421: New (this audit) | N421: Yes | O421: PosTransactions/api/PosRefunds.spec.ts | P421: B2B
A422: EMI-B2B-3649 | B422: PoS Refunds | C422: TC-Refund-16 | D422: Refund Arriving Before Its Original Is Parked, Not Rejected | E422: High | F422: No original present for the reference | G422: 1. Capture a refund whose original has not yet arrived 2. Inspect its state | H422: The refund is parked, not rejected; out-of-order arrival is treated as normal | I422: Not Tested | J422: Negative | K422: Web | L422: New (this audit) | N422: Yes | O422: PosTransactions/api/PosRefunds.spec.ts | P422: B2B
A423: EMI-B2B-3638 | B423: PoS Refunds | C423: TC-Refund-05 | D423: settlement_expected Is Immutable After Capture | E423: Medium | F423: A captured refund with settlement_expected = false | G423: 1. Attempt to update settlement_expected on the stored refund through every available path | H423: The field cannot be changed after capture; attempts are rejected and recorded | I423: Not Tested | J423: Negative | K423: Web | L423: New (this audit) | N423: Yes | O423: PosTransactions/api/PosRefunds.spec.ts | P423: B2B
A424: EMI-B2B-3648 | B424: PoS Refunds | C424: TC-Refund-15 | D424: Cap Breach Is Alarmed as a Feed-Integrity Defect | E424: Medium | F424: Ability to trigger a cumulative cap breach | G424: 1. Trigger a cap breach 2. Inspect the alarm channel and its classification | H424: The breach is alarmed and classified as a feed-integrity defect, not as a business rejection; the raw record is retained for Ops | I424: Not Tested | J424: Negative | K424: Web | L424: New (this audit) | N424: No | P424: B2B
A425: EMI-B2B-3650 | B425: PoS Refunds | C425: TC-Refund-17 | D425: Parked Refund Is Retried on Each Subsequent Arrival | E425: Medium | F425: A parked refund awaiting its original | G425: 1. Capture the original 2. Observe the parked refund | H425: The parked refund is retried on the arrival and links successfully; the original is flagged accordingly | I425: Not Tested | J425: Negative | K425: Web | L425: New (this audit) | N425: Yes | O425: PosTransactions/api/PosRefunds.spec.ts | P425: B2B
A426: EMI-B2B-3651 | B426: PoS Refunds | C426: TC-Refund-18 | D426: Parked Refund Escalates After 48 Hours | E426: Medium | F426: A parked refund whose original never arrives | G426: 1. Leave the refund parked past the 48 h window 2. Inspect the Ops queue and escalation | H426: The refund escalates at 48 h; it is never auto-rejected or discarded | I426: Not Tested | J426: Negative | K426: Web | L426: New (this audit) | N426: Yes | O426: PosTransactions/api/PosRefunds.spec.ts | P426: B2B
A427: EMI-B2B-3652 | B427: PoS Refunds | C427: TC-Refund-19 | D427: Ops Parked-Refund Queue Shows Time Remaining | E427: Medium | F427: One or more parked refunds of differing ages | G427: 1. Open the Ops parked-refund queue | H427: Parked refunds are listed with the 48 h window shown as time remaining and aged; cap breaches and window rejections are listed with the raw record | I427: Not Tested | J427: Negative | K427: Web | L427: New (this audit) | N427: No | P427: B2B
A428: EMI-B2B-3653 | B428: PoS Refunds | C428: TC-Refund-20 | D428: Refund Outside the Configured Window Is Rejected | E428: Medium | F428: An original older than the configured refund window | G428: 1. Capture a refund against it | H428: Rejected with a clear reason and alarmed | I428: Not Tested | J428: Negative | K428: Web | L428: New (this audit) | N428: Yes | O428: PosTransactions/api/PosRefunds.spec.ts | P428: B2B
A429: EMI-B2B-3655 | B429: PoS Refunds | C429: TC-Refund-22 | D429: Refund on a Business With Zero or Low Wallet Balance | E429: High | F429: Merchant wallet at or near zero balance | G429: 1. Capture a refund for that business 2. Inspect the outcome and the wallet | H429: The refund is captured normally with no rejection; no balance is touched so there is nothing to check; no insufficient-balance error is possible here | I429: Not Tested | J429: Edge / Boundary | K429: Web | L429: New (this audit) | N429: Yes | O429: PosTransactions/api/PosRefunds.spec.ts | P429: B2B
A430: EMI-B2B-3642 | B430: PoS Refunds | C430: TC-Refund-09 | D430: occurred_at Precision Is Preserved in Full | E430: Medium | F430: Refund carrying a high-precision timestamp | G430: 1. Submit the refund 2. Read occurred_at back from storage and compare with the source | H430: occurred_at is stored at full source precision with no truncation or rounding; amount and rrn likewise match the source exactly | I430: Not Tested | J430: Edge / Boundary | K430: Web | L430: New (this audit) | N430: Yes | O430: PosTransactions/api/PosRefunds.spec.ts | P430: B2B
A431: EMI-B2B-3654 | B431: PoS Refunds | C431: TC-Refund-21 | D431: Refund Window Is Configurable, Default 180 Days | E431: Medium | F431: Access to the refund-window configuration | G431: 1. Confirm the default is 180 days 2. Change it and capture a refund on either side of the new boundary | H431: The default is 180 days; the new value takes effect without a release and is applied at capture | I431: Not Tested | J431: Edge / Boundary | K431: Web | L431: New (this audit) | N431: Yes | O431: PosTransactions/api/PosRefunds.spec.ts | P431: B2B
A432: EMI-B2B-3660 | B432: PoS Refunds | C432: TC-Refund-27 | D432: Gate 1 Runs on Party State for Refund Events | E432: Medium | F432: Merchant under a compliance condition that Gate 1 evaluates | G432: 1. Capture a refund for that business 2. Inspect the Gate 1 evaluation on the ledger entry | H432: Gate 1 runs on party state exactly as it does for any other captured event; the outcome is recorded on the entry | I432: Not Tested | J432: Edge / Boundary | K432: Web | L432: New (this audit) | N432: No | P432: B2B
A433: EMI-B2B-3668 | B433: PoS Refunds | C433: TC-Refund-35 | D433: Refunds Appear in the Per-Device View, Visually Distinct | E433: Medium | F433: Merchant per-device view (EMI-5916) available with sales and refunds present | G433: 1. Open the per-device view for the terminal 2. Compare refund rows with sale rows and with declines | H433: Refunds appear alongside sales, visually distinct, showing the original they refund, and are excluded from every total on the screen that looks like money, exactly as declines are | I433: Not Tested | J433: Edge / Boundary | K433: Web | L433: New (this audit) | N433: No | P433: B2B
A434: EMI-B2B-3635 | B434: PoS Refunds | C434: TC-Refund-02 | D434: Refund Arrives Through the EMI-5915 Entry Point Only | E434: High | F434: Refund capture available | G434: 1. Trace the transport, authentication, hardening and idempotency handling of a REFUND event 2. Search for any refund-specific ingestion endpoint | H434: The refund uses EMI-5915's single entry point with event_type = REFUND; no separate ingestion path or second code path exists | I434: Not Tested | J434: Integration | K434: API | L434: New (this audit) | N434: Yes | O434: PosTransactions/api/PosRefunds.spec.ts | P434: B2B
A435: EMI-B2B-3656 | B435: PoS Refunds | C435: TC-Refund-23 | D435: No Wallet Debit Is Raised for a Refund | E435: High | F435: A merchant wallet with a recorded starting balance | G435: 1. Capture refunds across settled, unsettled and partially refunded originals 2. Run the settlement, reconciliation and ACH cycles 3. Compare the business wallet balance with its starting value | H435: No wallet debit is raised at any point - not immediate, not deferred, not on settlement; the business balance is untouched. Any debit found is a defect | I435: Not Tested | J435: Integration | K435: Web | L435: New (this audit) | N435: Yes | O435: PosTransactions/api/PosRefunds.spec.ts | P435: B2B
A436: EMI-B2B-3657 | B436: PoS Refunds | C436: TC-Refund-24 | D436: No Reserve, Hold or Balance Guard Is Created | E436: High | F436: A merchant wallet with a recorded starting position | G436: 1. Capture a refund 2. Query for reserves, holds and balance guards on the business | H436: None exist; there is nothing to reserve against because nothing will be taken | I436: Not Tested | J436: Integration | K436: Web | L436: New (this audit) | N436: Yes | O436: PosTransactions/api/PosRefunds.spec.ts | P436: B2B
A437: EMI-B2B-3658 | B437: PoS Refunds | C437: TC-Refund-25 | D437: No Netting Into Any Settlement Batch | E437: High | F437: A captured refund and a settlement batch for the same terminal and period | G437: 1. Run settlement grouping (EMI-5989) 2. Inspect the batch members and the aggregate amount for any refund contribution | H437: No refund is netted into the batch; the aggregate reflects settled sales only | I437: Not Tested | J437: Integration | K437: Web | L437: New (this audit) | N437: Yes | O437: PosTransactions/api/PosRefunds.spec.ts | P437: B2B
A438: EMI-B2B-3661 | B438: PoS Refunds | C438: TC-Refund-28 | D438: Duplicate Refund Event Delivered Twice | E438: High | F438: Refund capture available | G438: 1. Deliver the same refund event twice with the same idempotency key 2. Inspect records and the exposure total | H438: The duplicate is absorbed; a single record exists; the exposure is counted exactly once | I438: Not Tested | J438: Integration | K438: Web | L438: New (this audit) | N438: Yes | O438: PosTransactions/api/PosRefunds.spec.ts | P438: B2B
A439: EMI-B2B-3671 | B439: PoS Refunds | C439: TC-Refund-38 | D439: Cumulative Cap Holds Under Concurrent Partial Refunds | E439: High | F439: An original sale with capacity for further partial refunds | G439: 1. Submit several partial refunds concurrently whose combined total exceeds the original gross 2. Inspect which were admitted | H439: The database-level constraint, not application logic alone, admits only the refunds that keep the running total at or below the original gross; a race cannot inflate the exposure figure | I439: Not Tested | J439: Integration | K439: Web | L439: New (this audit) | N439: Yes | O439: PosTransactions/api/PosRefunds.spec.ts | P439: B2B
A440: EMI-B2B-3659 | B440: PoS Refunds | C440: TC-Refund-26 | D440: No Card-Scheme Refund Leg Is Produced by Us | E440: Medium | F440: A captured refund | G440: 1. Inspect all outbound integrations after capture | H440: We produce no card-scheme refund leg; the business refunds the customer through the terminal and the scheme, and we are not in that path | I440: Not Tested | J440: Integration | K440: Web | L440: New (this audit) | N440: Yes | O440: PosTransactions/api/PosRefunds.spec.ts | P440: B2B
A441: EMI-B2B-3669 | B441: PoS Refunds | C441: TC-Refund-36 | D441: Business Copy Must Not Imply a Balance Deduction | E441: High | F441: A captured refund visible to the merchant | G441: 1. Read every business-facing string and figure associated with the refund | H441: No copy, label, total or figure implies the refund has been deducted from the business's balance or from what they are owed today, because it has not been | I441: Not Tested | J441: Usability | K441: Web | L441: New (this audit) | N441: No | P441: B2B
A442: EMI-B2B-3670 | B442: PoS Refunds | C442: TC-Refund-37 | D442: Refund Observability Metrics Are Emitted | E442: Medium | F442: Monitoring accessible | G442: 1. Capture refunds, park one and trigger a cap breach 2. Inspect the emitted metrics | H442: Metrics cover refunds captured per business per day, exposure total and trend, parked-refund count and age, and cap breaches | I442: Not Tested | J442: Observability | K442: Web | L442: New (this audit) | N442: No | P442: B2B
A443: EMI-B2B-3662 | B443: PoS Refunds | C443: TC-Refund-29 | D443: Captured Refund Contributes to the E34 Exposure Total | E443: High | F443: One or more captured refunds with no settlement counterpart | G443: 1. Capture refunds for several businesses 2. Compute the day's exposure | H443: Each refund is included in the E34 total, reported per business, per wallet and in total | I443: Not Tested | J443: Reporting | K443: Web | L443: New (this audit) | N443: Yes | O443: PosTransactions/api/PosRefunds.spec.ts | P443: B2B
A444: EMI-B2B-3664 | B444: PoS Refunds | C444: TC-Refund-31 | D444: Exposure Over a Month of Trading Rises and Is Shown as a Trend | E444: High | F444: A month of refund activity with no settlement counterpart | G444: 1. Capture refunds across a month 2. Open the Finance exposure view | H444: The exposure rises monotonically and the trend is the primary display, not the daily number; this is the evidence for closing O43 | I444: Not Tested | J444: Reporting | K444: Web | L444: New (this audit) | N444: No | P444: B2B
A445: EMI-B2B-3665 | B445: PoS Refunds | C445: TC-Refund-32 | D445: Exposure Is a Memo Line Outside the Reconciling Total | E445: High | F445: Refunds present for the reporting period | G445: 1. Generate the Finance safeguarding report | H445: Exposure appears as a memo line outside the reconciling total; the reconciling line still reconciles with the exposure excluded | I445: Not Tested | J445: Reporting | K445: Web | L445: New (this audit) | N445: Yes | O445: PosTransactions/api/PosRefunds.spec.ts | P445: B2B
A446: EMI-B2B-3663 | B446: PoS Refunds | C446: TC-Refund-30 | D446: Exposure Is Aged and Recomputable From the Ledger | E446: Medium | F446: A ledger holding refunds of varying ages | G446: 1. Recompute exposure from the ledger at an arbitrary point 2. Compare with the stored figure and check the ageing buckets | H446: Exposure is recomputable at any time and matches; ageing is reported per business, per wallet and in total | I446: Not Tested | J446: Reporting | K446: Web | L446: New (this audit) | N446: No | P446: B2B
A447: EMI-B2B-3666 | B447: PoS Refunds | C447: TC-Refund-33 | D447: Finance Exposure View Drills Into Individual Refunds | E447: Medium | F447: A non-zero exposure total | G447: 1. Open the Finance exposure view and drill from the total | H447: The view drills into the individual refunds and their originals, per business and per wallet, and is legible to someone who has not read the epic | I447: Not Tested | J447: Reporting | K447: Web | L447: New (this audit) | N447: No | P447: B2B
A448: EMI-B2B-3672 | B448: PoS Refunds | C448: TC-Refund-39 | D448: Refund Against a Pre-Settlement Original - Behaviour to Be Confirmed | E448: Medium | F448: An original captured but not yet settled | G448: 1. Capture a REFUND against the pre-settlement original 2. Record the actual behaviour | H448: Current EMI-5918 acceptance criteria do not restrict refunds to settled originals; TC-Refund-34 expects capture with an Ops flag. An earlier suite expected rejection with USE_VOID. Confirm with Product which is correct, then keep one and retire the other | I448: Not Tested | J448: Open Question | K448: Web | L448: New (this audit) | N448: No | P448: B2B
A449: EMI-B2B-3673 | B449: PoS Refunds | C449: TC-Refund-40 | D449: Commission on a Refunded Sale - Blocked on O43 | E449: Medium | F449: A settled sale whose commission has been charged, then refunded | G449: 1. Capture the refund 2. Inspect the original commission and VAT entries | H449: EMI-5918 states refund of MJD Pay commission follows O43 and is not designed. Assert only that the existing commission entries are left untouched and nothing is reversed speculatively. Re-scope this case once O43 is answered | I449: Not Tested | J449: Open Question | K449: Web | L449: New (this audit) | N449: No | P449: B2B
A450: EMI-B2B-3674 | B450: PTS Retrieval & Parsing | C450: TC-PTS-01 | D450: Normal Window — File Parses Cleanly | E450: High | F450: A scheduled 2-hourly pull window runs against a well-formed ANB PTS file | G450: 1. Trigger the pull for the current date 2. Parse the returned file 3. Inspect the handed-off rows | H450: Validated rows are handed on to EMI-5989 with full lineage (source_pull_date, source_file_hash). | I450: NA | J450: Functional | K450: Web | L450: New (this audit) | N450: No | P450: B2B
A451: EMI-B2B-3677 | B451: PTS Retrieval & Parsing | C451: TC-PTS-04 | D451: API Unavailable for Three Consecutive Windows | E451: High | F451: The ANB PTS API is made unavailable across three consecutive 2-hourly windows | G451: 1. Simulate three consecutive failed windows 2. Inspect the cursor, alarms and notifications | H451: Backoff occurs; an Ops alarm AND a Finance notification are both raised (an unpulled statement stalls settlement silently otherwise); the per-date cursor is NOT advanced; catch-up re-pulls on recovery. | I451: NA | J451: Functional | K451: Web | L451: New (this audit) | N451: No | P451: B2B
A452: EMI-B2B-3683 | B452: PTS Retrieval & Parsing | C452: TC-PTS-10 | D452: Look-Back Window Picks Up a Late-Arriving D+1 Row | E452: High | F452: A transaction dated D appears only in the D+1 file (POSTING_DATE is T+1 in ANB's sample) | G452: 1. Pull date D — row absent 2. Pull date D+1 within the look-back window 3. Inspect which LOCALDATE the row is keyed on | H452: The row is picked up by the look-back window and keyed on its own LOCALDATE, not the pull date it happened to appear in. | I452: NA | J452: Functional | K452: Web | L452: New (this audit) | N452: No | P452: B2B
A453: EMI-B2B-3688 | B453: PTS Retrieval & Parsing | C453: TC-PTS-15 | D453: Date Closes Out After N Stable Pulls Into D+1 | E453: High | F453: A date's row content and count stop changing across N consecutive pulls, and D+1 has begun | G453: 1. Observe a date stabilise across N pulls 2. Confirm close-out 3. Inspect what is published to EMI-5989 | H453: The date is marked closed; row count and totals are frozen as the baseline; close-out state is published to EMI-5989. | I453: NA | J453: Functional | K453: Web | L453: New (this audit) | N453: No | P453: B2B
A454: EMI-B2B-3689 | B454: PTS Retrieval & Parsing | C454: TC-PTS-16 | D454: Whole-Day Outage Recovered by Catch-Up | E454: High | F454: The ANB PTS API is unavailable for an entire day | G454: 1. Simulate a full-day outage 2. Restore availability 3. Run the catch-up job | H454: Catch-up re-pulls the entire look-back window within one cut-off cycle, rate-limited so it does not starve the live window. | I454: NA | J454: Functional | K454: Web | L454: New (this audit) | N454: No | P454: B2B
A455: EMI-B2B-3694 | B455: PTS Retrieval & Parsing | C455: TC-PTS-21 | D455: Whole-Day Outage Recovered by Catch-Up | E455: High | F455: The ANB PTS API is unavailable for an entire day | G455: 1. Simulate a full-day outage 2. Restore availability 3. Run catch-up | H455: Catch-up re-pulls every date in the look-back window on recovery, rate-limited so it does not starve the live/current-night window, rather than waiting for the next scheduled 23:30 slot. | I455: Not Tested | J455: Functional | K455: Web | L455: New (this audit) | N455: No | P455: B2B
A456: EMI-B2B-3706 | B456: PTS Retrieval & Parsing | C456: TC-PTS-35 | D456: Refund Handling Path — BLOCKED (O43) | E456: High | F456: O43 (how a refund ever settles, given ANB confirm the PTS carries no refunded transactions) has not been answered by ANB | G456: 1. Once O43 is answered, verify refunds are handled via the confirmed mechanism (net-at-source, Adjustment Type columns, a separate file, or explicitly not at all) 2. Confirm the safeguarding line reconciles under the confirmed model | H456: BLOCKED until O43 is answered. Until then, a business refund's value is not visibly accounted for anywhere in this workstream, which is a live risk to the safeguarding reconciliation. | I456: Not Tested | J456: Functional | K456: Web | L456: New (this audit) | N456: No | P456: B2B
A457: EMI-B2B-3676 | B457: PTS Retrieval & Parsing | C457: TC-PTS-03 | D457: Date File Grows Between Windows | E457: Medium | F457: A date file has new rows added by ANB between two pull windows | G457: 1. Pull the date, capturing the row set 2. Pull again after new rows are added on ANB's side 3. Compare row sets | H457: New rows are accepted; existing rows are left untouched. | I457: NA | J457: Functional | K457: Web | L457: New (this audit) | N457: No | P457: B2B
... A651: EMI-B2B-3869 | B651: ZATCA e-invoicing | C651: TC-ZATCA-06 | D651: Clearance vs Reporting Model Routing — BLOCKED (Z3) | E651: High | F651: Z3 (are merchants VAT-registered B2B businesses in all cases, or can a merchant be an individual?) is unanswered | G651: 1. Once Z3 is answered, confirm invoices route through the clearance model (standard tax invoices) or the reporting model (simplified invoices) as applicable | H651: BLOCKED until Z3 is confirmed with Tax — the story explicitly states this determines which ZATCA regime applies. | I651: NA | J651: Compliance | K651: Web | L651: New (this audit) | N651: No | P651: B2B

Sheet Setup & Admin
A1: TC ID | B1: Sub-Area | C1: Source ID | D1: Title | E1: Priority | F1: Preconditions | G1: Steps | H1: Expected Result | I1: Status | J1: Test Type | K1: Interface | L1: Source | M1: Jira Ref | N1: Automated | O1: Automated By | P1: Channel
A2: EMI-B2B-5978 | B2: Account Commission | C2: EMI-TC-460 | D2: Verify No data retrieves incase searching for mismatch data | E2: Critical | F2: Admin user already logged in | G2: 1. Click on the arrow next to "Commission Management" 2. Click on Accounts Commissions 3. Click on "View Account Commissions" | H2: The site should not retrieved data | I2: Not Tested | J2: Functional | K2: Web | L2: AIO (Jira) | M2: EMI-2031 | N2: No | P2: B2B
A3: EMI-B2B-5995 | B3: Account Commission | C3: EMI-TC-484 | D3: Verify delete commission works correcty | E3: Critical | F3: Admin user already logged in | G3: 1. Click on the arrow next to "Commission Management" 2. Click on Accounts Commissions 3. Click on "View Account Commissions" 4. Click on "Delete" for the required commission | H3: 1. The commission should be deleted correctly 2. This commission should not use( the defualt commission should be applied on the transaction you deleted) | I3: Not Tested | J3: Functional | K3: Web | L3: AIO (Jira) | M3: EMI-2031 | N3: No | P3: B2B
A4: EMI-B2B-6003 | B4: Account Commission | C4: EMI-TC-493 | D4: Verify ability to edit the commission by adding a new transaction Type that is not defined in any another commission | E4: Critical | F4: 1. Admin user already logged in 2. User at Account Commission page | G4: 1. Click on "View Account Commissions" 2. Click on edit 3. Update the Transaction Type 4. Submit the form. | H4: The site should allow the user to add the transaction type correctly as well as the commission should be applied on the all matched transactions | I4: Not Tested | J4: Functional | K4: Web | L4: AIO (Jira) | M4: EMI-2031 | N4: No | P4: B2B
A5: EMI-B2B-6004 | B5: Account Commission | C5: EMI-TC-494 | D5: Verify ability to edit the commission by removing a new transaction Type | E5: Critical | F5: 1. Admin user already logged in 2. User at Account Commission page | G5: 1. Click on "View Account Commissions" 2. Click on edit 3. Delete the Transaction Type 4. Submit the form. | H5: The site should allow the user to remove the transaction type correctly as well as the commission should not be applied on the all deleted transactions | I5: Not Tested | J5: Functional | K5: Web | L5: AIO (Jira) | M5: EMI-2031 | N5: No | P5: B2B
A6: EMI-B2B-6005 | B6: Account Commission | C6: EMI-TC-495 | D6: Verify inability to remove all transactions type from Edit page | E6: Critical | F6: 1. Admin user already logged in 2. User at Account Commission page | G6: 1. Click on "View Account Commissions" 2. Click on edit 3. Delete all Transaction Types 4. Submit the form. | H6: The site should not allow the admin to edit the commission by removing all transactions | I6: Not Tested | J6: Functional | K6: Web | L6: AIO (Jira) | M6: EMI-2031 | N6: No | P6: B2B
A7: EMI-B2B-6006 | B7: Account Commission | C7: EMI-TC-496 | D7: Verify Edit the commission is not affected on any old matched transaction | E7: Critical | F7: 1. Admin user already logged in 2. User at Account Commission page | G7: 1. Click on "View Account Commissions" 2. Click on edit 3. Submit the form. 4. Check the old transactions | H7: Edit the commission should not affected on any old matched transaction | I7: Not Tested | J7: Functional | K7: Web | L7: AIO (Jira) | M7: EMI-2031 | N7: No | P7: B2B
A8: EMI-B2B-6007 | B8: Account Commission | C8: EMI-TC-497 | D8: Verfiy the Commissions records appears in Pagenation | E8: Critical | F8: 1. Admin user already logged in | G8: 1. Click on the arrow next to "Commission Management" 2. Click on Accounts Commissions 3. Click on "View Account Commissions" | H8: There's should be a pagenation in the list | I8: Not Tested | J8: Functional | K8: Web | L8: AIO (Jira) | M8: EMI-2031 | N8: No | P8: B2B
A9: EMI-B2B-5982 | B9: Account Commission | C9: EMI-TC-464 | D9: Verify the ability to prevent the user from adding commission for the overlapped value, for the same platform | E9: Critical | F9: 1. Admin user already logged in 2. Commission exist | G9: 1. Click on the arrow next to "Commission Management" 2. Click on Accounts Commissions 3. Click on "View Account Commissions" for a business account 4. Click on "Add New Commission" button 5. Select "Bank Transfer" as a commission Type 6. Expand "Choose Bank Transfer Transaction" 7. Select the platform as the existing commission 8. Add an overlapped minimum amount and maximum amount 9. Select the value type as the existing commission 10. Insert the value 11. Click on "Confirm" button | H9: Validation to inform user that the commission value already exists | I9: Not Tested | J9: Negative | K9: Web | L9: AIO (Jira) | M9: EMI-2031 | N9: No | P9: B2B
A10: EMI-B2B-5991 | B10: Account Commission | C10: EMI-TC-479 | D10: Ensure that the amount field rejects values exceeding 12 digits( for Fixed Commission) | E10: Critical | F10: Admin user already logged in | G10: 1. Click on the arrow next to "Commission Management" 2. Click on Accounts Commissions 3. Click on "View Account Commissions" 4. Click on "Add New Commission" button 5. Select a commission Type 6. Expand "Choose Bank Transfer Transaction" 7. Select the platform 8. Add the minimum amount 9. Add maximum amount (9,999,999 SAR) 10. Select the value type as the existing commission 11. Insert the value 12. Click on "Confirm" button 1.Enter a value of 999999999999 (the maximum 12-digit number) in the maximum amount field | H10: The form should not be submitted, and an appropriate validation error message should be displayed indicating that the amount cannot exceed 12 digits | I10: Not Tested | J10: Negative | K10: Web | L10: AIO (Jira) | M10: EMI-2031 | N10: No | P10: B2B
A11: EMI-B2B-5993 | B11: Account Commission | C11: EMI-TC-482 | D11: Ensure that the amount field rejects non-numeric input( for Fixed Commission) | E11: Critical | F11: Admin user already logged in | G11: 1. Click on the arrow next to "Commission Management" 2. Click on Accounts Commissions 3. Click on "View Account Commissions" 4. Click on "Add New Commission" button 5. Select a commission Type 6. Expand "Choose Bank Transfer Transaction" 7. Select the platform 8. Insert the minimum and the maximum amount as characters 9. Select the value type as the existing commission 10. Insert the value 11. Click on "Confirm" button | H11: User will not be able to insert the characters | I11: Not Tested | J11: Negative | K11: Web | L11: AIO (Jira) | M11: EMI-2031 | N11: No | P11: B2B
A12: EMI-B2B-5999 | B12: Account Commission | C12: EMI-TC-488 | D12: Ensure that the Value field rejects values exceeding 12 digits | E12: Critical | F12: 1. Admin user already logged in 2. User at Account Commission page | G12: 1. Click on "View Account Commissions" 2. Click on edit 3. Add the maximum value | H12: The form should not be submitted, and an appropriate validation error message should be displayed indicating that the amount cannot exceed 12 digits | I12: Not Tested | J12: Negative | K12: Web | L12: AIO (Jira) | M12: EMI-2031 | N12: No | P12: B2B
A13: EMI-B2B-6000 | B13: Account Commission | C13: EMI-TC-489 | D13: Verify that the amount field enforces the mandatory field requirement | E13: Critical | F13: 1. Admin user already logged in 2. User at Account Commission page | G13: 1. Click on "View Account Commissions" 2. Click on edit 3. Leave the Value and maximum amount fields empty. 4. Submit the form. | H13: The form should not be submitted, and a validation error message should be displayed for each mandatory field indicating that it is required | I13: Not Tested | J13: Negative | K13: Web | L13: AIO (Jira) | M13: EMI-2031 | N13: No | P13: B2B
... A150: EMI-B2B-6093 | B150: Business Products Management | C150: EMI-TC-2975 | D150: Edit VAT Value | E150: Critical | F150: Product with VAT = 15% exists | G150: 1. Edit product → Change VAT from 15 → 10 | H150: Product updated New VAT = 10% reflected in invoice line | I150: Not Tested | J150: Functional | K150: Web | L150: AIO (Jira) | M150: EMI-3020 | N150: No | P150: B2B
A151: EMI-B2B-6098 | B151: Business Products Management | C151: EMI-TC-2980 | D151: Add Product with Description and Discount | E151: Critical | G151: 1. Add product: Name = “Table”, Price = 50, VAT = 5, Description = “Wooden”, Discount Type = Percentage, Discount Value = 10 | H151: Product saved with all fields In invoice, discount applied correctly | I151: Not Tested | J151: Functional | K151: Web | L151: AIO (Jira) | M151: EMI-3020 | N151: No | P151: B2B
A152: EMI-B2B-6094 | B152: Business Products Management | C152: EMI-TC-2976 | D152: Delete Product (Soft Delete) | E152: Medium | F152: Product exists in My Products | G152: 1. Delete product “Monitor” | H152: Product removed from invoice dropdown Record retained in backend | I152: Not Tested | J152: Functional | K152: Web | L152: AIO (Jira) | M152: EMI-3020 | N152: No | P152: B2B
A153: EMI-B2B-6096 | B153: Business Products Management | C153: EMI-TC-2978 | D153: Dropdown with 1,000 Items | E153: Medium | F153: 1,000 products created for biller | G153: 1. Open invoice → Product selector dropdown 2. Start typing product name | H153: Dropdown loads quickly <1s Typeahead returns results correctly | I153: Not Tested | J153: Functional | K153: Web | L153: AIO (Jira) | M153: EMI-3020 | N153: No | P153: B2B
A154: EMI-B2B-6097 | B154: Business Products Management | C154: EMI-TC-2979 | D154: Add Product – Mandatory Fields Only | E154: Medium | G154: 1. Add product: Name = “Pen”, Price = 1 (no optional fields) | H154: Product saved successfully with default/null optional fields | I154: Not Tested | J154: Functional | K154: Web | L154: AIO (Jira) | M154: EMI-3020 | N154: No | P154: B2B
A155: EMI-B2B-6099 | B155: Business Products Management | C155: EMI-TC-2981 | D155: Edit Product Name and Price | E155: Medium | F155: Product exists | G155: 1. Edit Name = “Laptop Pro”, Price = 550 | H155: Changes saved Updated values shown in invoice dropdown and line | I155: Not Tested | J155: Functional | K155: Web | L155: AIO (Jira) | M155: EMI-3020 | N155: No | P155: B2B
A156: EMI-B2B-6103 | B156: Business Products Management | C156: EMI-TC-2985 | D156: Success Messages on Actions | E156: Medium | G156: 1. Add product 2. Edit product 3. Delete product | H156: Messages shown: “Product saved successfully”, “Product updated successfully”, “Product deleted successfully” | I156: Not Tested | J156: Functional | K156: Web | L156: AIO (Jira) | M156: EMI-3020 | N156: No | P156: B2B
A157: EMI-B2B-6092 | B157: Business Products Management | C157: EMI-TC-2974 | D157: Invalid VAT Input | E157: Critical | F157: Biller logged in, My Products screen available | G157: 1. Add product with VAT = -5 2. Add product with VAT = 120 | H157: Inline error shown: “VAT must be a number between 0–100” Product not saved | I157: Not Tested | J157: Negative | K157: Web | L157: AIO (Jira) | M157: EMI-3020 | N157: No | P157: B2B
A158: EMI-B2B-6100 | B158: Business Products Management | C158: EMI-TC-2982 | D158: Validation – Empty Product Name | E158: High | G158: 1. Add product leaving Name blank | H158: Inline error: “Product Name is required” | I158: Not Tested | J158: Negative | K158: Web | L158: AIO (Jira) | M158: EMI-3020 | N158: No | P158: B2B
A159: EMI-B2B-6101 | B159: Business Products Management | C159: EMI-TC-2983 | D159: Validation – Empty Price | E159: High | G159: 1. Add product leaving Price blank | H159: Inline error: “Price is required” | I159: Not Tested | J159: Negative | K159: Web | L159: AIO (Jira) | M159: EMI-3020 | N159: No | P159: B2B
A160: EMI-B2B-6095 | B160: Business Products Management | C160: EMI-TC-2977 | D160: Duplicate Name Error | E160: Critical | F160: Product “Desk” exists | G160: 1. Try adding new product with name = “desk” (case-insensitive) | H160: Inline error: “Product name already exists” Product not saved | I160: Not Tested | J160: Integration | K160: Web | L160: AIO (Jira) | M160: EMI-3020 | N160: No | P160: B2B
A161: EMI-B2B-6102 | B161: Business Products Management | C161: EMI-TC-2984 | D161: Performance under Load | E161: High | F161: Biller has 1,000 products | G161: 1. Navigate to My Products | H161: Page loads within acceptable performance limits (<2s) | I161: Not Tested | J161: Performance / NFR | K161: Web | L161: AIO (Jira) | M161: EMI-3020 | N161: No | P161: B2B
A162: EMI-B2B-6106 | B162: Card issuance | C162: EMI-TC-1583 | D162: Verify Admin can disable/enable products | E162: Medium | F162: Admin has access to product management | G162: 1. Admin disables a product. 2. Wallet User checks “Request Card” page | H162: Disabled product does not appear in customer list. Enabled ones appear normally. | I162: Not Tested | J162: Functional | K162: Web | L162: AIO (Jira) | M162: EMI-3133 | N162: No | P162: B2B
A163: EMI-B2B-6104 | B163: Card issuance | C163: EMI-TC-1581 | D163: Verify imported card products appear in Request Card UI | E163: Critical | F163: Admin has imported card products in the system | G163: 1. Login as Admin. 2. Import / sync products. 3. Verify product list in Admin panel. 4. Login as Wallet User and open “Request Card”. | H163: Products imported by Admin appear in Wallet User’s “Request Card” list. | I163: Not Tested | J163: Usability | K163: Web | L163: AIO (Jira) | M163: EMI-3133 | N163: No | P163: B2B
A164: EMI-B2B-6105 | B164: Card issuance | C164: EMI-TC-1582 | D164: Verify product attributes include fees | E164: Low | F164: Admin adds/updates card products | G164: 1. Admin configures a product with issuanceFee=0. 2. Admin configures another product with issuanceFee=5. 3. Check values in system. | H164: Products saved with correct fee attributes that are passed to customer UI. | I164: Not Tested | J164: Usability | K164: Web | L164: AIO (Jira) | M164: EMI-3133 | N164: No | P164: B2B
A165: EMI-B2B-6107 | B165: Card Management | C165: EMI-TC-1819 | D165: Successful import (all valid) | E165: Medium | F165: XLSX with 3 valid rows. | G165: Admin uploads → Import. | H165: 3 products created; success toast; 3 audit rows (+ 1 summary). | I165: Not Tested | J165: Functional | K165: Web | L165: AIO (Jira) | M165: EMI-3132 | N165: No | P165: B2B
A166: EMI-B2B-6114 | B166: Card Management | C166: EMI-TC-1826 | D166: Formatting & locale | E166: Medium | F166: Amounts with thousand separators or comma decimals (“1,234.50” / “123,45”). | G166: Import under en-US and ar-JO locales. | H166: Import under en-US and ar-JO locales. | I166: Not Tested | J166: Functional | K166: Web | L166: AIO (Jira) | M166: EMI-3132 | N166: No | P166: B2B
A167: EMI-B2B-6115 | B167: Card Management | C167: EMI-TC-1827 | D167: Multi-sheet workbook | E167: Medium | F167: Valid data on Products sheet; other sheets present. | G167: Import | H167: System reads configured sheet only; others ignored | I167: Not Tested | J167: Functional | K167: Web | L167: AIO (Jira) | M167: EMI-3132 | N167: No | P167: B2B
A168: EMI-B2B-6119 | B168: Card Management | C168: EMI-TC-1831 | D168: Create product (happy path) | E168: Medium | G168: Admin → “Create Product” → fill valid fields → Save. | H168: Admin → “Create Product” → fill valid fields → Save. | I168: Not Tested | J168: Functional | K168: Web | L168: AIO (Jira) | M168: EMI-3132 | N168: No | P168: B2B
A169: EMI-B2B-6122 | B169: Card Management | C169: EMI-TC-1834 | D169: Delete product (happy path) | E169: Medium | F169: An admin with permission to manage card products, and a product that is not referenced by any live card or transaction. | G169: 1. Open the card products list and locate the product 2. Select Delete 3. Confirm the prompt 4. Re-check the list 5. Attempt to use the product afterwards 6. Check the audit log | H169: 1. Delete is available for a product that can be removed. 2. A confirmation is asked for before anything is removed. 3. After confirming, the product disappears from the list and cannot be selected for new cards. 4. Cancelling the confirmation leaves the product untouched. 5. Historical records that referenced the product still show their original data — the deletion does not rewrite history. 6. The deletion is recorded in the audit log with the actor and the timestamp. | I169: Not Tested | J169: Functional | K169: Web | L169: AIO (Jira) | M169: EMI-3132 | N169: No | P169: B2B
A170: EMI-B2B-6123 | B170: Card Management | C170: EMI-TC-1835 | D170: Delete with references (policy) | E170: Medium | G170: Delete CP-002. | H170: either block with guidance (“Product in use”) or soft-delete + hidden from new requests while preserving references; audit reflects action. | I170: Not Tested | J170: Functional | K170: Web | L170: AIO (Jira) | M170: EMI-3132 | N170: No | P170: B2B
A171: EMI-B2B-6108 | B171: Card Management | C171: EMI-TC-1820 | D171: Partial success (some invalid rows) | E171: High | F171: File with 2 valid + 1 invalid (missing issuanceFee). | G171: Import. | H171: 2 products created; error panel lists row # and reason for the invalid row; audits for successes and a failure audit for the bad row. | I171: Not Tested | J171: Negative | K171: Web | L171: AIO (Jira) | M171: EMI-3132 | N171: No | P171: B2B
A172: EMI-B2B-6109 | B172: Card Management | C172: EMI-TC-1821 | D172: Missing required column (file-level invalid) | E172: High | F172: File missing limits.dailySpend column. | G172: Import | H172: Import blocked; clear message “Missing required column: limits.dailySpend”; no products created; single failure audit. | I172: Not Tested | J172: Negative | K172: Web | L172: AIO (Jira) | M172: EMI-3132 | N172: No | P172: B2B
A173: EMI-B2B-6110 | B173: Card Management | C173: EMI-TC-1822 | D173: Wrong data types | E173: High | F173: issuanceFee="abc" or limits.dailySpend=-10. | G173: Import | H173: Row(s) rejected with typed reasons: “issuanceFee must be a number”, “limits.dailySpend must be ≥ 0”; others commit. | I173: Not Tested | J173: Negative | K173: Web | L173: AIO (Jira) | M173: EMI-3132 | N173: No | P173: B2B
A174: EMI-B2B-6113 | B174: Card Management | C174: EMI-TC-1825 | D174: Extra/unknown columns | E174: High | F174: File has extra notes column | G174: Import. | H174: Ignored with warning (or mapped if configured); no failure. | I174: Not Tested | J174: Negative | K174: Web | L174: AIO (Jira) | M174: EMI-3132 | N174: No | P174: B2B
A175: EMI-B2B-6116 | B175: Card Management | C175: EMI-TC-1828 | D175: Invalid file | E175: High | F175: CSV, password-protected XLSX, or corrupted file. | G175: Import | H175: Clear error (“Unsupported format” / “Cannot read file”); no changes; failure audit. | I175: Not Tested | J175: Negative | K175: Web | L175: AIO (Jira) | M175: EMI-3132 | N175: No | P175: B2B
A176: EMI-B2B-6126 | B176: Card Management | C176: EMI-TC-1838 | D176: Immediate availability after import/add | E176: High | F176: Admin just imported/created a product. | G176: User opens/refreshes “Request Card”. | H176: New product appears instantly (within cache TTL = 0 or invalidated); values correct. | I176: Not Tested | J176: Negative | K176: Web | L176: AIO (Jira) | M176: EMI-3132 | N176: No | P176: B2B
A177: EMI-B2B-6117 | B177: Card Management | C177: EMI-TC-1829 | D177: Large import / limits | E177: High | F177: 10k rows valid. | G177: Import | H177: Completes within SLA; progress UI; pagination-ready in catalog; all created; audit summary includes counts. | I177: Not Tested | J177: Edge / Boundary | K177: Web | L177: AIO (Jira) | M177: EMI-3132 | N177: No | P177: B2B
A178: EMI-B2B-6120 | B178: Card Management | C178: EMI-TC-1832 | D178: Field validations | E178: High | G178: Leave name blank / issuanceFee negative / limits.dailySpend non-numeric | H178: Inline validation; save blocked; no audit “create”. | I178: Not Tested | J178: Edge / Boundary | K178: Web | L178: AIO (Jira) | M178: EMI-3132 | N178: No | P178: B2B
A179: EMI-B2B-6125 | B179: Card Management | C179: EMI-TC-1837 | D179: Catalog visible & correct | E179: High | F179: Catalog has diverse fees/limits. | G179: End user opens “Request Card”. | H179: All products listed with issuanceFee, renewalFee, limits.dailySpend; no edit controls. | I179: Not Tested | J179: Edge / Boundary | K179: Web | L179: AIO (Jira) | M179: EMI-3132 | N179: No | P179: B2B
A180: EMI-B2B-6128 | B180: Card Management | C180: EMI-TC-1840 | D180: Pricing consistency | E180: High | G180: Select a product → review screen → confirm. | H180: Fees/limits identical across steps; server authoritative; no client tampering. | I180: Not Tested | J180: Edge / Boundary | K180: Web | L180: AIO (Jira) | M180: EMI-3132 | N180: No | P180: B2B
A181: EMI-B2B-6111 | B181: Card Management | C181: EMI-TC-1823 | D181: Duplicate IDs in file | E181: Critical | F181: Two rows with cardProductId=CP-001. | G181: Import | H181: First creates; second rejected: “Duplicate cardProductId in file: CP-001”; no duplicate in DB. | I181: Not Tested | J181: Integration | K181: Web | L181: AIO (Jira) | M181: EMI-3132 | N181: No | P181: B2B
A182: EMI-B2B-6112 | B182: Card Management | C182: EMI-TC-1824 | D182: Duplicate vs existing catalog (policy) | E182: Critical | F182: DB already has CP-001. | G182: Import file containing CP-001. | H182: either (a) reject row “ID exists” or (b) update product; outcome audited; response explicitly states applied policy. | I182: Not Tested | J182: Integration | K182: Web | L182: AIO (Jira) | M182: EMI-3132 | N182: No | P182: B2B
A183: EMI-B2B-6118 | B183: Card Management | C183: EMI-TC-1830 | D183: Idempotent re-upload | E183: Critical | F183: Same file re-submitted with same content/idempotency key. | G183: Import again. | H183: No duplicates; report “0 new, N unchanged”; audit notes idempotent no-op. | I183: Not Tested | J183: Integration | K183: Web | L183: AIO (Jira) | M183: EMI-3132 | N183: No | P183: B2B
A184: EMI-B2B-6121 | B184: Card Management | C184: EMI-TC-1833 | D184: Duplicate ID on create | E184: Critical | F184: An admin with permission to create card products, and an existing product whose identifier is known. | G184: 1. Create a product using an identifier that already exists 2. Record the response 3. Check the products list afterwards 4. Send the same create request twice in quick succession 5. Create a product with a genuinely new identifier | H184: 1. Creating a product with an identifier that already exists is refused with a clear error naming the conflict — not accepted silently. 2. No second product is created and the existing one is not overwritten. 3. The products list is unchanged after the refused attempt. 4. Sending the same create request twice in quick succession produces one product, not two. 5. A genuinely new identifier is accepted and the product is created. 6. The refusal is a validation-level response, not a server error. | I184: Not Tested | J184: Integration | K184: Web | L184: AIO (Jira) | M184: EMI-3132 | N184: No | P184: B2B
A185: EMI-B2B-6124 | B185: Card Management | C185: EMI-TC-1836 | D185: Concurrent admin actions | E185: High | F185: Two admins operate on same ID. | G185: Admin A deletes while Admin B edits/creates. | H185: Backend enforces optimistic lock/uniqueness; one succeeds; the other gets a clear conflict message; consistent final state. | I185: Not Tested | J185: Integration | K185: Web | L185: AIO (Jira) | M185: EMI-3132 | N185: No | P185: B2B
A186: EMI-B2B-6127 | B186: Card Management | C186: EMI-TC-1839 | D186: Product removed mid-flow | E186: High | F186: User on selection screen; Admin deletes product. | G186: User proceeds with now-deleted product. | H186: Server rejects gracefully: “Product no longer available”; user routed back to selection; no stale pricing used | I186: Not Tested | J186: Integration | K186: Web | L186: AIO (Jira) | M186: EMI-3132 | N186: No | P186: B2B
A187: EMI-B2B-6129 | B187: Card Type Management | C187: EMI-TC-658 | D187: Add new card with valid data | E187: Medium | F187: User is logged in and on Card Type Management page | G187: 1. open EMI Admin Web 2.-Logged in 3. Select card Management from Home Bar. 4. Click “Add Card” 5. Fill required fields 6. Click “Save” | H187: Card is added and shown in the table | I187: Not Tested | J187: Functional | K187: Web | L187: AIO (Jira) | M187: EMI-2739,EMI-2729 | N187: No | P187: B2B
A188: EMI-B2B-6131 | B188: Card Type Management | C188: EMI-TC-660 | D188: Edit existing card | E188: Medium | F188: At least one card is added | G188: 1. open EMI Admin Web 2.-Logged in 3. Select card Management from Home Bar. 4. Click “Edit” for a card 5. Update name/type 6. Save changes | H188: Card is updated in the table | I188: Not Tested | J188: Functional | K188: Web | L188: AIO (Jira) | M188: EMI-2729,EMI-2739 | N188: No | P188: B2B
A189: EMI-B2B-6132 | B189: Card Type Management | C189: EMI-TC-661 | D189: Delete existing card | E189: Medium | F189: At least one card exists | G189: 1. open EMI Admin Web 2.-Logged in 3. Select card Management from Home Bar. 4. Click “Delete” on a card 5. Confirm deletion | H189: Card is removed from the table | I189: Not Tested | J189: Functional | K189: Web | L189: AIO (Jira) | M189: EMI-2739,EMI-2729 | N189: No | P189: B2B
A190: EMI-B2B-6135 | B190: Card Type Management | C190: EMI-TC-1590 | D190: Verify admin can activate a blocked card | E190: Medium | F190: Card exists in Blocked state; Admin logged in with valid token | G190: 1. Call PUT /admin/cards/{cardId} with status=Active .2. Verify response. 3. Fetch card status | H190: API returns 200 Success. Card status updated to Active | I190: Not Tested | J190: Functional | K190: API | L190: AIO (Jira) | M190: EMI-2605 | N190: No | P190: B2B
A191: EMI-B2B-6136 | B191: Card Type Management | C191: EMI-TC-1591 | D191: Verify admin can block an active card | E191: Medium | F191: Card exists in Active state; Admin logged in with valid token | G191: 1. Call PUT /admin/cards/{cardId} with status=Blocked. 2. Verify response. 3. Fetch card status. | H191: API returns 200 Success. Card status updated to Blocked. | I191: Not Tested | J191: Functional | K191: API | L191: AIO (Jira) | M191: EMI-2605 | N191: No | P191: B2B
A192: EMI-B2B-6130 | B192: Card Type Management | C192: EMI-TC-659 | D192: Add card with missing required fields | E192: High | F192: On Add Card form | G192: 1. open EMI Admin Web 2.-Logged in 3. Select card Management from Home Bar. 4. Click “Add Card” 5.Leave mandatory fields empty 6. Click “Save” | H192: Error message shown, card not saved | I192: Not Tested | J192: Negative | K192: Web | L192: AIO (Jira) | M192: EMI-2739,EMI-2729 | N192: No | P192: B2B
... A237: EMI-B2B-6180 | B237: Default Commission | C237: EMI-TC-450 | D237: Verfiy the Commissions records appears in Pagenation | E237: Critical | F237: The defualt commission already added from the DataBase | G237: 1. Navigate to the "Default Commissions" screen. | H237: There's should be a pagenation in the list | I237: Not Tested | J237: Usability | K237: Web | L237: AIO (Jira) | M237: EMI-2031 | N237: No | P237: B2B
A238: EMI-B2B-6181 | B238: Default Commission | C238: EMI-TC-451 | D238: Verify Total commission counter works correctly | E238: Critical | G238: Go to the" Default Commissions" screen | H238: Total Commission should display the correct counter | I238: Not Tested | J238: Usability | K238: Web | L238: AIO (Jira) | M238: EMI-2031 | N238: No | P238: B2B
A239: EMI-B2B-6193 | B239: Detailed Bill | C239: EMI-TC-2956 | D239: Close the calendar | E239: Critical | F239: 1. Admin activated the account. 2. User logged in. 3. The merchant is registered, active, and added as a beneficiary | G239: 1. Navigate to the Business app 2. Login with a valid username and password 4. Expand Create Bills 5. Click on Detailed Bill 6. Click on the calendar 7. Click away from the calendar | H239: The popup should be closed | I239: Not Tested | J239: Functional | K239: Web | L239: AIO (Jira) | M239: EMI-183 | N239: No | P239: B2B
A240: EMI-B2B-6196 | B240: Detailed Bill | C240: EMI-TC-2959 | D240: Verify that the system prevent the user from inserting invalid reference number | E240: Critical | F240: 1. Admin activated the account. 2. User logged in. 3. The merchant is registered, active, and added as a beneficiary 4. Biller added items to the bill | G240: 1. Navigate to the Business app 2. Login with a valid username and password 4. Expand Create Bills 5. Click on Detailed Bill 6. Fill the form 7. Click on the Go To Add Item popup | H240: A Validation should be displayed to the user to inform him that the reference number is not valid | I240: Not Tested | J240: Negative | K240: Web | L240: AIO (Jira) | M240: EMI-183 | N240: No | P240: B2B
A241: EMI-B2B-6197 | B241: Detailed Bill | C241: EMI-TC-2960 | D241: Verify that the system will prevent the business from creating a bill with an expiry date earlier than the creation date | E241: Critical | F241: 1. Admin activated the account. 2. User logged in. 3. The merchant is registered, active, and added as a beneficiary 4. The biller added items to the bill 5. Reference already used | G241: 1. Navigate to the Business app 2. Login with a valid username and password 3. Expand Create Bills 4. Click on Detailed Bill 5. Fill the form 6. Enter a Reference Number that is already used in another bill. 7. Fill in all other required fields with valid data. 8. Click the "Go to Add Items" button. | H241: The system should display an error message indicating that the "Reference Number already exist". | I241: Not Tested | J241: Negative | K241: Web | L241: AIO (Jira) | M241: EMI-183 | N241: No | P241: B2B
A242: EMI-B2B-6198 | B242: Detailed Bill | C242: EMI-TC-2961 | D242: Verify that the system will prevent the business from creating a bill with expiry date earlier than the creation date | E242: Critical | F242: 1. Admin activated the account. 2. User logged in. 3. The merchant is registered, active, and added as a beneficiary 4. The biller added items to the bill 5. Reference already used | G242: 1. Navigate to the Business app 2. Login with a valid username and password 3. Expand Create Bills 4. Click on Detailed Bill 5. Fill the form 6. Enter an expiry date earlier than the creation date 7. Fill in all other required fields with valid data. 8. Click the "Go to Add Items" button. | H242: The system should display an error message indicating that the expiry date must be after the issue date. | I242: Not Tested | J242: Negative | K242: Web | L242: AIO (Jira) | M242: EMI-183 | N242: No | P242: B2B
A243: EMI-B2B-6199 | B243: Detailed Bill | C243: EMI-TC-2962 | D243: Verify that the system prevents users from adding bill item quantity, not a boolean | E243: Critical | F243: 1. Admin activated the account. 2. User logged in. 3. The merchant is registered, active, and added as a beneficiary 4. The biller added items to the bill | G243: 1. Navigate to the Business app 2. Login with a valid username and password 3. Expand Create Bills 4. Click on Detailed Bill 5. Fill the form 6. Click the "Go to Add Items" button. 7. Add an item with a discount | H243: The user will not be able to add a bill item | I243: Not Tested | J243: Negative | K243: Web | L243: AIO (Jira) | M243: EMI-183 | N243: No | P243: B2B
A244: EMI-B2B-6200 | B244: Detailed Bill | C244: EMI-TC-2963 | D244: Verify that the user will not be able to create a bill leaving mandatory fiels empty | E244: Critical | F244: 1. Admin activated the account. 2. User logged in. 3. The merchant is registered, active, and added as a beneficiary 4. The biller added items to the bill | G244: 1. Navigate to the Business app 2. Login with a valid username and password 3. Expand Create Bills 4. Click on Detailed Bill 5. Leave mandatory fields empty | H244: The system should display an error message under required fields indicating that the feild is required, and can not navigate to the "Add Items" form. | I244: Not Tested | J244: Negative | K244: Web | L244: AIO (Jira) | M244: EMI-183 | N244: No | P244: B2B
A245: EMI-B2B-6182 | B245: Detailed Bill | C245: EMI-TC-2945 | D245: Verify Detailed Bill - First step | E245: Critical | F245: 1. Admin activated the account. 2. User logged in. 3. The merchant is registered, active, and added as a beneficiary | G245: 1. Navigate to the Business app 2. Login with a valid username and password 4. Expand Create Bills 5. Click on Detailed Bill | H245: 1. The user is redirected to the Create Detailed Bill page - first step with the following details: 1. First part "Bill Information" 1.1 Beneficiaries 1.2 Issue Date 1.3 Expiry Date 1.4 Discount Type 1.5 Discount 1.6 Reference Number 1.7 VAT 1.8 Description 1.9 Go To Add Items button | I245: Not Tested | J245: Usability | K245: Web | L245: AIO (Jira) | M245: EMI-183 | N245: No | P245: B2B
A246: EMI-B2B-6183 | B246: Detailed Bill | C246: EMI-TC-2946 | D246: Verify Detailed Bill - Second step - add products | E246: Critical | F246: 1. Admin activated the account. 2. User logged in. 3. The merchant is registered, active, and added as a beneficiary | G246: 1. Navigate to the Business app 2. Login with a valid username and password 4. Expand Create Bills 5. Click on Detailed Bill 6. Fill the form 7. Click on "Go To Add Items" button | H246: 1. The user is redirected to the Create Detailed Bill page - second page with the following details: 1. Adding Items 1.1 Item Name 1.2 Quantity 1.3 Discount Type 1.4 Discount 1.5 VAT 2. Unit Price 3. Add Item To List 4. Item List 4.1 Item Name 4.2 Quantity 4.3 Unit Price 4.4 Line Total 4.5 Actions (Edit/Delete) 4.6 Delete All 5. Go To Create Bill button 6. Back button | I246: Not Tested | J246: Usability | K246: Web | L246: AIO (Jira) | M246: EMI-183 | N246: No | P246: B2B
A247: EMI-B2B-6184 | B247: Detailed Bill | C247: EMI-TC-2947 | D247: Verify Detailed Bill - Third step | E247: Critical | F247: 1. Admin activated the account. 2. User logged in. 3. The merchant is registered, active, and added as a beneficiary | G247: 1. Navigate to the Business app 2. Login with a valid username and password 4. Expand Create Bills 5. Click on Detailed Bill 6. Fill the form 7. Click on the "Go To Add Items" button 8. Add an item 9. Click on Create Bill button | H247: 1. The user is redirected to the Create Detailed Bill page - third page with the following details: 1. Items List 1.1 Item Name 1.2 Quantity 1.3 Unit Price 1.4 Line Total 2. Bill Breakdown 2.1 Total Bill Amount 2.2 Discount 2.3 Total Amount After Discount 2.4 VAT 2.5 Total Amount After VAT 3. Create Bill button | I247: Not Tested | J247: Usability | K247: Web | L247: AIO (Jira) | M247: EMI-183 | N247: No | P247: B2B
A248: EMI-B2B-6185 | B248: Detailed Bill | C248: EMI-TC-2948 | D248: Create Detailed Bill with Valid Data | E248: Critical | F248: 1. Admin activated the account. 2. User logged in. 3. The merchant is registered, active, and added as a beneficiary | G248: 1. Navigate to the Business app 2. Login with a valid username and password 4. Expand Create Bills 5. Click on Detailed Bill 6. Fill the form 7. Click on the "Go To Add Items" button 8. Add an item 9. Click on the Create Bill button 10. Click on Create Bill | H248: 1. A Success message will be displayed to the user to inform him that the bill has been created successfully and uploaded to the bill report once the user clicks on the Create button from the popup 2. The user is redirected to the bills page with the created bill at the top of the table | I248: Not Tested | J248: Usability | K248: Web | L248: AIO (Jira) | M248: EMI-183 | N248: No | P248: B2B
A249: EMI-B2B-6186 | B249: Detailed Bill | C249: EMI-TC-2949 | D249: Add item to the Bill | E249: Critical | F249: 1. Admin activated the account. 2. User logged in. 3. The merchant is registered, active, and added as a beneficiary | G249: 1. Navigate to the Business app 2. Login with a valid username and password 4. Expand Create Bills 5. Click on Detailed Bill 6. Fill the form 7. Click on the "Go To Add Items" button 8. Add an item | H249: The item should appear in the items list under the item information form. | I249: Not Tested | J249: Usability | K249: Web | L249: AIO (Jira) | M249: EMI-183 | N249: No | P249: B2B
A250: EMI-B2B-6187 | B250: Detailed Bill | C250: EMI-TC-2950 | D250: Verify Editing Items in List | E250: Critical | F250: 1. Admin activated the account. 2. User logged in. 3. The merchant is registered, active, and added as a beneficiary 4. User added an item to the bill | G250: 1. Navigate to the Business app 2. Login with a valid username and password 4. Expand Create Bills 5. Click on Detailed Bill 6. Fill the form 7. Click on the "Go To Add Items" button 8. Add an item 9. Click on edit next to the item 10. Update the item 11. Click on Update | H250: 1. Adding item pop-up displays to the user 2. The user can edit the item name, quantity, and price. 3. A success message is displayed to the user to inform him that the changes have been updated. | I250: Not Tested | J250: Usability | K250: Web | L250: AIO (Jira) | M250: EMI-183 | N250: No | P250: B2B
... A258: EMI-B2B-6209 | B258: Device Management | C258: EMI-TC-3072 | D258: Unique Device Fingerprint Stored | E258: Critical | F258: First-time device login | G258: Submit login request | H258: Device fingerprint saved and linked to user | I258: Not Tested | J258: Functional | K258: Web | L258: AIO (Jira) | M258: EMI-810 | N258: No | P258: B2B
A259: EMI-B2B-6221 | B259: Device Management | C259: EMI-TC-3084 | D259: Automatic AML Ban | E259: Critical | G259: AML scenario triggers (e.g., fraud detected) | H259: Device automatically banned Status updated to Banned Admin notified with AML details | I259: Not Tested | J259: Functional | K259: Web | L259: AIO (Jira) | M259: EMI-810 | N259: No | P259: B2B
A260: EMI-B2B-6202 | B260: Device Management | C260: EMI-TC-709 | D260: Verify status dropdown appears | E260: Medium | F260: Admin Users page is open | G260: 1. Locate the Status column in the device table 2. Click the dropdown arrow | H260: Dropdown list appears with options: Ban, Unbanned | I260: Not Tested | J260: Functional | K260: Web | L260: AIO (Jira) | M260: EMI-810 | N260: No | P260: B2B
A261: EMI-B2B-6205 | B261: Device Management | C261: EMI-TC-712 | D261: Verify correct data shown in Device Details | E261: Medium | G261: 1. Note the UID/Owner from a row 2. Click "More Details" | H261: Device Details show matching UID, Platform, Owner, and Status | I261: Not Tested | J261: Functional | K261: Web | L261: AIO (Jira) | M261: EMI-810 | N261: No | P261: B2B
A262: EMI-B2B-6207 | B262: Device Management | C262: EMI-TC-3070 | D262: Request with Complete Device Metadata | E262: Medium | F262: Device sends request | G262: Send request with Device Name + Fingerprint | H262: Request processed successfully | I262: Not Tested | J262: Functional | K262: Web | L262: AIO (Jira) | M262: EMI-810 | N262: No | P262: B2B
A263: EMI-B2B-6210 | B263: Device Management | C263: EMI-TC-3073 | D263: Request with Geolocation Data | E263: Medium | G263: Send request with Lat+Lng | H263: Request processed successfully | I263: Not Tested | J263: Functional | K263: Web | L263: AIO (Jira) | M263: EMI-810 | N263: No | P263: B2B
A264: EMI-B2B-6213 | B264: Device Management | C264: EMI-TC-3076 | D264: Admin Views Devices List | E264: Medium | G264: Log in as Admin | H264: Open Device Management page | I264: Not Tested | J264: Functional | K264: Web | L264: AIO (Jira) | M264: EMI-810 | N264: No | P264: B2B
A265: EMI-B2B-6214 | B265: Device Management | C265: EMI-TC-3077 | D265: Admin Bans Device | E265: Medium | G265: Select device → Ban | H265: Device status updates to Banned; future requests blocked | I265: Not Tested | J265: Functional | K265: Web | L265: AIO (Jira) | M265: EMI-810 | N265: No | P265: B2B
A266: EMI-B2B-6215 | B266: Device Management | C266: EMI-TC-3078 | D266: Admin Unbans Device | E266: Medium | G266: Select banned device → Unban | H266: Select banned device → Unban | I266: Not Tested | J266: Functional | K266: Web | L266: AIO (Jira) | M266: EMI-810 | N266: No | P266: B2B
A267: EMI-B2B-6218 | B267: Device Management | C267: EMI-TC-3081 | D267: Valid Fingerprint | E267: Medium | G267: Send request with correct fingerprint | H267: Request accepted | I267: Not Tested | J267: Functional | K267: Web | L267: AIO (Jira) | M267: EMI-810 | N267: No | P267: B2B
A268: EMI-B2B-6226 | B268: Device Management | C268: EMI-TC-3090 | D268: Device List Table Format | E268: Medium | G268: Open Admin Portal | H268: Devices shown in tabular format (Name, Status, Banned, Fingerprint) | I268: Not Tested | J268: Functional | K268: Web | L268: AIO (Jira) | M268: EMI-810 | N268: No | P268: B2B
A269: EMI-B2B-6208 | B269: Device Management | C269: EMI-TC-3071 | D269: Missing Device Metadata | E269: High | F269: Request without Device Name + Fingerprint | G269: Send request without metadata | H269: Error: “Device information is required to access the system.” | I269: Not Tested | J269: Negative | K269: Web | L269: AIO (Jira) | M269: EMI-810 | N269: No | P269: B2B
A270: EMI-B2B-6211 | B270: Device Management | C270: EMI-TC-3074 | D270: Request Missing Geolocation | E270: High | G270: Send request without Lat/Lng | H270: Error: “Geolocation data is required to access the system.” | I270: Not Tested | J270: Negative | K270: Web | L270: AIO (Jira) | M270: EMI-810 | N270: No | P270: B2B
A271: EMI-B2B-6212 | B271: Device Management | C271: EMI-TC-3075 | D271: Geolocation Data Format Validation | E271: High | G271: Send request with invalid Lat/Lng (text instead of numbers) | H271: Error returned: Invalid geolocation format | I271: Not Tested | J271: Negative | K271: Web | L271: AIO (Jira) | M271: EMI-810 | N271: No | P271: B2B
A272: EMI-B2B-6219 | B272: Device Management | C272: EMI-TC-3082 | D272: Invalid Fingerprint | E272: High | G272: Send request with tampered fingerprint | H272: Error: “Invalid device fingerprint. Access denied.” | I272: Not Tested | J272: Negative | K272: Web | L272: AIO (Jira) | M272: EMI-810 | N272: No | P272: B2B
A273: EMI-B2B-6220 | B273: Device Management | C273: EMI-TC-3083 | D273: Replay Attack Attempt | E273: High | G273: Reuse same fingerprint from another device | H273: Request rejected, log entry created | I273: Not Tested | J273: Negative | K273: Web | L273: AIO (Jira) | M273: EMI-810 | N273: No | P273: B2B
A274: EMI-B2B-6223 | B274: Device Management | C274: EMI-TC-3086 | D274: Missing Device Info | E274: High | G274: Submit request without Device Name | H274: Error: “Device information is required to access the system.” | I274: Not Tested | J274: Negative | K274: Web | L274: AIO (Jira) | M274: EMI-810 | N274: No | P274: B2B
A275: EMI-B2B-6224 | B275: Device Management | C275: EMI-TC-3087 | D275: Missing Geolocation | E275: High | G275: Submit request without Lat/Lng | H275: Error: “Geolocation data is required to access the system.” | I275: Not Tested | J275: Negative | K275: Web | L275: AIO (Jira) | M275: EMI-810 | N275: No | P275: B2B
A276: EMI-B2B-6225 | B276: Device Management | C276: EMI-TC-3089 | D276: Error Logging | E276: High | G276: Trigger invalid request | H276: Error logged with full details (request, fingerprint, reason) | I276: Not Tested | J276: Negative | K276: Web | L276: AIO (Jira) | M276: EMI-810 | N276: No | P276: B2B
A277: EMI-B2B-6222 | B277: Device Management | C277: EMI-TC-3085 | D277: AML Ban Visibility | E277: Critical | G277: Admin checks banned list | H277: AML scenario details displayed in device record | I277: Not Tested | J277: Usability | K277: Web | L277: AIO (Jira) | M277: EMI-810 | N277: No | P277: B2B
A278: EMI-B2B-6228 | B278: Device Management | C278: EMI-TC-3092 | D278: AML Ban Details in UI | E278: Critical | G278: Admin views AML-banned device | H278: AML scenario reason displayed (e.g., “Suspicious multiple logins”) | I278: Not Tested | J278: Usability | K278: Web | L278: AIO (Jira) | M278: EMI-810 | N278: No | P278: B2B
A279: EMI-B2B-6201 | B279: Device Management | C279: EMI-TC-707 | D279: Verify device table columns display correctly | E279: Low | F279: Admin Users page is open | G279: 1. Open the page 2. Inspect the device table columns | H279: UID, Platform, Owner, and Status columns are displayed correctly | I279: Not Tested | J279: Usability | K279: Web | L279: AIO (Jira) | M279: EMI-810 | N279: No | P279: B2B
A280: EMI-B2B-6203 | B280: Device Management | C280: EMI-TC-710 | D280: Verify status change to Ban | E280: Low | F280: Admin Users page is open | G280: 1. Click on the Status dropdown 2. Select "Ban" | H280: Status changes to "Ban" and is reflected in the UI | I280: Not Tested | J280: Usability | K280: Web | L280: AIO (Jira) | M280: EMI-810 | N280: No | P280: B2B
A281: EMI-B2B-6204 | B281: Device Management | C281: EMI-TC-711 | D281: Verify status change to Unbanned | E281: Low | G281: 1. Click on the Status dropdown 2. Select "Unbanned" | H281: Status changes to "Unbanned" and is reflected in the UI | I281: Not Tested | J281: Usability | K281: Web | L281: AIO (Jira) | M281: EMI-810 | N281: No | P281: B2B
A282: EMI-B2B-6206 | B282: Device Management | C282: EMI-TC-714 | D282: Verify responsiveness of device table | E282: Low | G282: 1. Open the Device Management page on different screen sizes | H282: Table is readable and layout is not broken | I282: Not Tested | J282: Usability | K282: Web | L282: AIO (Jira) | M282: EMI-810 | N282: No | P282: B2B
A283: EMI-B2B-6216 | B283: Device Management | C283: EMI-TC-3079 | D283: Filter Devices by Status | E283: Low | G283: Apply filter = Banned | H283: Only banned devices displayed | I283: Not Tested | J283: Usability | K283: Web | L283: AIO (Jira) | M283: EMI-810 | N283: No | P283: B2B
A284: EMI-B2B-6217 | B284: Device Management | C284: EMI-TC-3080 | D284: Filter Devices by Active | E284: Low | G284: Apply filter = Active | H284: Only active devices displayed | I284: Not Tested | J284: Usability | K284: Web | L284: AIO (Jira) | M284: EMI-810 | N284: No | P284: B2B
A285: EMI-B2B-6227 | B285: Device Management | C285: EMI-TC-3091 | D285: Intuitive Ban/Unban Buttons | E285: Low | G285: Admin manages device | H285: Clear options for Ban / Unban available | I285: Not Tested | J285: Usability | K285: Web | L285: AIO (Jira) | M285: EMI-810 | N285: No | P285: B2B
A286: EMI-B2B-6231 | B286: Excel Bill | C286: EMI-TC-2967 | D286: Verify that the user can drag and drop the file with invalid data. | E286: Critical | F286: 1. Admin activated the account. 2. User logged in. 3. The merchant is registered, active, and added as a beneficiary 4. The Excel File has been downloaded and filled with invalid data and some are empty | G286: 1. Navigate to the Business app 2. Login with a valid username and password 3. Expand Create Bills 4. Click on Excel Template 5. Download excel template 6. Fill the file 7. Drag and Drop the file | H286: The File is uploaded successfully and a sample is displayed in the file Overview | I286: Not Tested | J286: Negative | K286: Web | L286: AIO (Jira) | M286: EMI-242 | N286: No | P286: B2B
A287: EMI-B2B-6233 | B287: Excel Bill | C287: EMI-TC-2969 | D287: Verify that the user is able to upload the excel file with invalid data. | E287: Critical | F287: 1. Admin activated the account. 2. User logged in. 3. The merchant is registered, active, and added as a beneficiary 4. The Excel File has been downloaded and filled with invalid data and some are empty | G287: 1. Navigate to the Business app 2. Login with a valid username and password 3. Expand Create Bills 4. Click on Excel Template 5. Download excel template 6. Fill the file 7. Upload the file | H287: The File is uploaded successfully and a sample is displayed in the file Overview | I287: Not Tested | J287: Negative | K287: Web | L287: AIO (Jira) | M287: EMI-242 | N287: No | P287: B2B
...

Sheet Transaction Operations
A1: TC ID | B1: Sub-Area | C1: Source ID | D1: Title | E1: Priority | F1: Preconditions | G1: Steps | H1: Expected Result | I1: Status | J1: Test Type | K1: Interface | L1: Source | M1: Jira Ref | N1: Automated | O1: Automated By | P1: Channel
A2: EMI-B2B-8214 | B2: A. Create Bill (Business — EMI-183, EMI-242, EMI-3020) | C2: CB-03 | D2: Discount type "None" is default and hides amount field | E2: High | G2: Open Add Bill form | H2: Discount type defaults to "No discount"; discount amount field is hidden; discount excluded from API payload | I2: Not Tested | J2: Functional | K2: Web | L2: Project docs | M2: EMI-183 | N2: Yes | O2: BillManagement/functional/CreateBillFlow.spec.ts | P2: B2B
A3: EMI-B2B-8217 | B3: A. Create Bill (Business — EMI-183, EMI-242, EMI-3020) | C3: CB-06 | D3: Detailed bill entry — add multiple items | E3: High | G3: Open Detailed Bill Entry, add ≥2 items with Name/Qty/Unit Price/Discount/VAT | H3: Bill Items list reflects all items; Section 3 confirmation shows per-item and aggregate totals | I3: Not Tested | J3: Functional | K3: Web | L3: Project docs | M3: EMI-183 | N3: Yes | O3: BillManagement/functional/CreateBillFlow.spec.ts | P3: B2B
A4: EMI-B2B-8220 | B4: A. Create Bill (Business — EMI-183, EMI-242, EMI-3020) | C4: CB-09 | D4: Add product from "My Products" to a detailed bill | E4: High | G4: On Section 2 (Bill Items), open the product multi-select and choose a saved product | H4: Selected product is added as a line item with its saved Name/Price/VAT/Discount pre-filled | I4: Not Tested | J4: Functional | K4: Web | L4: Project docs | M4: EMI-3020 | N4: Yes | O4: BillManagement/functional/CreateBillFlow.spec.ts | P4: B2B
A5: EMI-B2B-8225 | B5: A. Create Bill (Business — EMI-183, EMI-242, EMI-3020) | C5: CB-14 | D5: Bulk upload — valid Excel file | E5: High | G5: Upload a correctly filled, unmodified protected Excel template with N bill rows | H5: All N bills are created; checksum validated; no tampering detected | I5: Not Tested | J5: Functional | K5: Web | L5: Project docs | M5: EMI-242 | N5: Yes | O5: BillManagement/functional/CreateBillFlow.spec.ts | P5: B2B
A6: EMI-B2B-8229 | B6: A. Create Bill (Business — EMI-183, EMI-242, EMI-3020) | C6: CB-18 | D6: View Bills list — Business row/detail fields | E6: High | G6: Open "View Bills" as Business | H6: Row shows Bill Ref., Beneficiary brand name, Total Amount, Expiry Date, Status; detail view adds Bill type, Discount, VAT, amount breakdown, Bill Dates, QR image | I6: Not Tested | J6: Functional | K6: Web | L6: Project docs | M6: EMI-183 | N6: Yes | O6: BillManagement/functional/CreateBillFlow.spec.ts | P6: B2B
A7: EMI-B2B-8233 | B7: A. Create Bill (Business — EMI-183, EMI-242, EMI-3020) | C7: CB-22 | D7: Editing an approved bill re-triggers approval | E7: High | G7: Edit the amount on an already-Approved bill | H7: Bill flips back to Pending/unapproved and requires re-approval before it can be paid | I7: Not Tested | J7: Functional | K7: Web | L7: Project docs | M7: EMI-183 | N7: No | P7: B2B
A8: EMI-B2B-8234 | B8: A. Create Bill (Business — EMI-183, EMI-242, EMI-3020) | C8: CB-23 | D8: Edit restricted to unpaid bills only | E8: High | G8: Attempt to edit a bill already marked Paid | H8: Edit is blocked/disabled for Paid bills | I8: Not Tested | J8: Functional | K8: Web | L8: Project docs | M8: EMI-183 | N8: No | P8: B2B
A9: EMI-B2B-8218 | B9: A. Create Bill (Business — EMI-183, EMI-242, EMI-3020) | C9: CB-07 | D9: Detailed bill entry — item-level VAT/discount independent of master | E9: Medium | G9: Set different VAT/discount per item | H9: Each item's amount breakdown (Initial/Discount/After discount/VAT/Total) is computed independently and summed correctly at bill level | I9: Not Tested | J9: Functional | K9: Web | L9: Project docs | M9: EMI-183 | N9: No | P9: B2B
A10: EMI-B2B-8224 | B10: A. Create Bill (Business — EMI-183, EMI-242, EMI-3020) | C10: CB-13 | D10: Soft-deleted product removed from dropdown, not from history | E10: Medium | G10: Delete a product already used on a past bill | H10: Product disappears from the invoice item dropdown; historical bill still shows original item data | I10: Not Tested | J10: Functional | K10: Web | L10: Project docs | M10: EMI-3020 | N10: No | P10: B2B
A11: EMI-B2B-8231 | B11: A. Create Bill (Business — EMI-183, EMI-242, EMI-3020) | C11: CB-20 | D11: Filter bills by reference/date/status | E11: Medium | G11: On View Bills, filter by Bill Reference, Date Range, and Status | H11: List narrows to matching bills only; irrelevant bills excluded | I11: Not Tested | J11: Functional | K11: Web | L11: Project docs | M11: EMI-183 | N11: Yes | O11: BillManagement/functional/CreateBillFlow.spec.ts | P11: B2B
A12: EMI-B2B-8235 | B12: A. Create Bill (Business — EMI-183, EMI-242, EMI-3020) | C12: CB-24 | D12: Deleting all items shows confirmation dialog | E12: Medium | G12: On a detailed bill, delete the last remaining item | H12: Confirmation dialog: "By continuing with deletion process, bill amount will become 0, are you sure you want to proceed?" | I12: Not Tested | J12: Functional | K12: Web | L12: Project docs | M12: EMI-183 | N12: No | P12: B2B
A13: EMI-B2B-8236 | B13: A. Create Bill (Business — EMI-183, EMI-242, EMI-3020) | C13: CB-25 | D13: Delete a bill | E13: Medium | G13: Business deletes a bill they own | H13: Bill is removed from the active list | I13: Not Tested | J13: Functional | K13: Web | L13: Project docs | M13: EMI-183 | N13: No | P13: B2B
A14: EMI-B2B-8237 | B14: A. Create Bill (Business — EMI-183, EMI-242, EMI-3020) | C14: CB-26 | D14: Audit trail records lifecycle events | E14: Medium | G14: Create, edit, view, and delete a bill in sequence | H14: Audit log contains one entry per action with actor, timestamp, and description | I14: Not Tested | J14: Functional | K14: Web | L14: Project docs | M14: EMI-183 | N14: No | P14: B2B
A15: EMI-B2B-8221 | B15: A. Create Bill (Business — EMI-183, EMI-242, EMI-3020) | C15: CB-10 | D15: Product typeahead responsive at scale | E15: Low | G15: With ~1,000 saved products, open the product selector and type a partial name | H15: Matching results filter within ~1 second | I15: Not Tested | J15: Functional | K15: Web | L15: Project docs | M15: EMI-3020 | N15: No | P15: B2B
A16: EMI-B2B-8215 | B16: A. Create Bill (Business — EMI-183, EMI-242, EMI-3020) | C16: CB-04 | D16: Selecting Fixed/Percentage discount reveals amount field | E16: High | G16: Change discount type from None to Fixed (or Percentage) | H16: Discount amount field becomes visible and required; 0 is rejected as a value | I16: Not Tested | J16: Negative | K16: Web | L16: Project docs | M16: EMI-183 | N16: Yes | O16: BillManagement/functional/CreateBillFlow.spec.ts | P16: B2B
A17: EMI-B2B-8226 | B17: A. Create Bill (Business — EMI-183, EMI-242, EMI-3020) | C17: CB-15 | D17: Bulk upload — tampered file rejected | E17: High | G17: Modify the protected Excel template outside allowed cells, then upload | H17: Upload rejected — checksum mismatch detected, no bills created | I17: Not Tested | J17: Negative | K17: Web | L17: Project docs | M17: EMI-242 | N17: Yes | O17: BillManagement/functional/CreateBillFlow.spec.ts | P17: B2B
A18: EMI-B2B-8227 | B18: A. Create Bill (Business — EMI-183, EMI-242, EMI-3020) | C18: CB-16 | D18: Bulk upload — one invalid row rolls back the whole batch | E18: High | G18: Upload a file where row 5 of 10 fails bill-creation validation | H18: All 10 rows are rejected (atomic rollback); validation errors returned per failing row; zero bills created | I18: Not Tested | J18: Negative | K18: Web | L18: Project docs | M18: EMI-242 | N18: Yes | O18: BillManagement/functional/CreateBillFlow.spec.ts | P18: B2B
A19: EMI-B2B-8232 | B19: A. Create Bill (Business — EMI-183, EMI-242, EMI-3020) | C19: CB-21 | D19: Approve/Reject a bill | E19: High | G19: Reviewer opens a Pending bill and selects Approve (or Reject) | H19: Status updates in real time and persists to the DB; Business visibility follows the new status | I19: Not Tested | J19: Negative | K19: Web | L19: Project docs | M19: EMI-183 | N19: Yes | O19: BillManagement/functional/CreateBillFlow.spec.ts | P19: B2B
A20: EMI-B2B-8216 | B20: A. Create Bill (Business — EMI-183, EMI-242, EMI-3020) | C20: CB-05 | D20: Zero discount value rejected when a discount type is selected | E20: Medium | G20: Select Fixed discount, enter 0 as the amount | H20: Validation error — a non-zero value is required when a discount type is selected | I20: Not Tested | J20: Negative | K20: Web | L20: Project docs | M20: EMI-183 | N20: Yes | O20: BillManagement/functional/CreateBillFlow.spec.ts | P20: B2B
A21: EMI-B2B-8223 | B21: A. Create Bill (Business — EMI-183, EMI-242, EMI-3020) | C21: CB-12 | D21: Product VAT validation range | E21: Medium | G21: Enter VAT as -5 or 120 on a product | H21: Inline error: "VAT must be a number between 0–100" | I21: Not Tested | J21: Negative | K21: Web | L21: Project docs | M21: EMI-3020 | N21: No | P21: B2B
A22: EMI-B2B-8228 | B22: A. Create Bill (Business — EMI-183, EMI-242, EMI-3020) | C22: CB-17 | D22: Bulk upload — file processing error surfaced clearly | E22: Medium | G22: Upload a corrupted/unreadable file | H22: A user-friendly error is shown; no partial data is created | I22: Not Tested | J22: Negative | K22: Web | L22: Project docs | M22: EMI-242 | N22: No | P22: B2B
A23: EMI-B2B-8212 | B23: A. Create Bill (Business — EMI-183, EMI-242, EMI-3020) | C23: CB-01 | D23: Single bill entry — required fields only | E23: High | G23: Business opens "Add Bill" → Single Bill Entry, fills Beneficiary, Bill Ref., Amount, leaves Discount/VAT/Dates/Description empty, submits | H23: Bill is created; discount shows "-"/0, VAT default checkbox state respected, no expiry = infinite | I23: Not Tested | J23: Edge / Boundary | K23: Web | L23: Project docs | M23: EMI-183 | N23: Yes | O23: BillManagement/functional/CreateBillFlow.spec.ts | P23: B2B
A24: EMI-B2B-8213 | B24: A. Create Bill (Business — EMI-183, EMI-242, EMI-3020) | C24: CB-02 | D24: Single bill entry — full fields with VAT and discount | E24: High | G24: Fill all optional fields: Fixed discount (non-zero), "Apply 15% VAT" checked, Issue/Expiry dates, Description | H24: Bill Confirmation summary shows correct amount breakdown: Initial → Discount → Amount after discount → VAT → Total | I24: Not Tested | J24: Edge / Boundary | K24: Web | L24: Project docs | M24: EMI-183 | N24: Yes | O24: BillManagement/functional/CreateBillFlow.spec.ts | P24: B2B
A25: EMI-B2B-8238 | B25: A. Create Bill (Business — EMI-183, EMI-242, EMI-3020) | C25: CB-27 | D25: Bill Ref. uniqueness / required field enforcement | E25: High | G25: Attempt to submit a bill with an empty Bill Ref. or Amount | H25: Form blocks submission with a required-field validation message | I25: Not Tested | J25: Edge / Boundary | K25: Web | L25: Project docs | M25: EMI-183 | N25: Yes | O25: BillManagement/functional/CreateBillFlow.spec.ts | P25: B2B
A26: EMI-B2B-8219 | B26: A. Create Bill (Business — EMI-183, EMI-242, EMI-3020) | C26: CB-08 | D26: Optional expiry — bill never expires | E26: Medium | G26: Leave Expiry Date empty on creation | H26: Bill is created with no expiry and remains payable indefinitely (never auto-flagged Expired) | I26: Not Tested | J26: Edge / Boundary | K26: Web | L26: Project docs | M26: EMI-183 | N26: Yes | O26: BillManagement/functional/CreateBillFlow.spec.ts | P26: B2B
A27: EMI-B2B-8222 | B27: A. Create Bill (Business — EMI-183, EMI-242, EMI-3020) | C27: CB-11 | D27: Duplicate product name rejected | E27: Medium | G27: Add a new product using a name that already exists (case-insensitive) | H27: Inline validation: "Product name already exists"; product not saved | I27: Not Tested | J27: Integration | K27: Web | L27: Project docs | M27: EMI-3020 | N27: No | P27: B2B
A28: EMI-B2B-8230 | B28: A. Create Bill (Business — EMI-183, EMI-242, EMI-3020) | C28: CB-19 | D28: Unapproved / not-yet-issued bills hidden from Business | E28: High | G28: Create a bill with a future issue date or leave it unapproved | H28: Bill is not visible in the Business's received-bills list until issue date is reached and it is approved | I28: Not Tested | J28: Usability | K28: Web | L28: Project docs | M28: EMI-183 | N28: Yes | O28: BillManagement/functional/CreateBillFlow.spec.ts | P28: B2B
A29: EMI-B2B-8242 | B29: A. Money Request (EMI-834) | C29: MR-EC-01 | D29: Requester cancels before Accept | E29: High | G29: Requester taps Cancel while status is `REQUESTED` | H29: Status → `CANCELLED`; requested party notified; Accept afterwards returns `REQUEST_CANCELLED` | I29: Not Tested | J29: Functional | K29: Web | L29: Project docs | N29: No | P29: B2B
A30: EMI-B2B-8246 | B30: A. Money Request (EMI-834) | C30: MR-FP-01 | D30: Create a basic money request | E30: High | G30: Requester opens "Create Request," selects a requested profile, sets amount and optional note/TTL, taps Send | H30: `MoneyRequest` is created with status `REQUESTED`; requested party is notified; requester sees it in "Requests Sent" | I30: Not Tested | J30: Functional | K30: Web | L30: Project docs | N30: No | P30: B2B
A31: EMI-B2B-8247 | B31: A. Money Request (EMI-834) | C31: MR-FP-02 | D31: Requested party accepts and pays successfully | E31: High | G31: Requested party opens the request, taps Pay, confirms after reviewing the fee breakdown | H31: Request locks to `PROCESSING`; P2P validations pass; requester is credited, requested is debited (+ fees); status → `COMPLETED` with a transaction reference; both parties notified | I31: Not Tested | J31: Functional | K31: Web | L31: Project docs | N31: No | P31: B2B
A32: EMI-B2B-8249 | B32: A. Money Request (EMI-834) | C32: MR-INT-01 | D32: Ledger and fee postings are correct | E32: High | G32: Complete a payment | H32: Sender debited (amount + fees); requester credited (amount); commission/VAT wallets credited correctly; ledger balances reconcile | I32: Not Tested | J32: Functional | K32: Web | L32: Project docs | N32: No | P32: B2B
A33: EMI-B2B-8243 | B33: A. Money Request (EMI-834) | C33: MR-EC-02 | D33: Request expires automatically at TTL | E33: Medium | G33: Create a request with a short TTL and let it elapse before any action | H33: Status → `EXPIRED`; requested party sees expiry and cannot pay | I33: Not Tested | J33: Functional | K33: Web | L33: Project docs | N33: No | P33: B2B
A34: EMI-B2B-8244 | B34: A. Money Request (EMI-834) | C34: MR-EC-03 | D34: Payer with multiple wallets chooses which to debit | E34: Medium | G34: Requested party has 2 wallets, one with insufficient balance; selects the sufficient one when paying | H34: System validates and completes the transfer from the chosen wallet | I34: Not Tested | J34: Functional | K34: Web | L34: Project docs | N34: No | P34: B2B
A35: EMI-B2B-8250 | B35: A. Money Request (EMI-834) | C35: MR-INT-02 | D35: Notifications delivered at every lifecycle step | E35: Medium | G35: Create → Accept → Complete a request | H35: Push/in-app/email notifications sent to both parties at each step, with correct request ID and transaction reference | I35: Not Tested | J35: Functional | K35: Web | L35: Project docs | N35: No | P35: B2B
A36: EMI-B2B-8251 | B36: A. Money Request (EMI-834) | C36: MR-INT-03 | D36: Audit trail captures the full lifecycle | E36: Medium | G36: Inspect audit logs for a completed request | H36: Entries for create, notify, accept, validation results, ledger IDs, and completion, all sharing a correlation ID | I36: Not Tested | J36: Functional | K36: Web | L36: Project docs | N36: No | P36: B2B
A37: EMI-B2B-8262 | B37: A. Money Request (EMI-834) | C37: MR-UI-01 | D37: Requests Sent / Received lists render correctly | E37: Medium | G37: Create several requests in different states, open both lists | H37: Correct listing, status badges, timestamps; sortable/filterable by status | I37: Not Tested | J37: Functional | K37: Web | L37: Project docs | N37: No | P37: B2B
A38: EMI-B2B-8245 | B38: A. Money Request (EMI-834) | C38: MR-EC-04 | D38: High-precision / decimal amounts round correctly | E38: Low | G38: Request an amount with decimals appropriate to the currency; pay it | H38: Fee/rounding computed per currency rules; ledger entries balanced with no rounding loss | I38: Not Tested | J38: Functional | K38: Web | L38: Project docs | N38: No | P38: B2B
A39: EMI-B2B-8248 | B39: A. Money Request (EMI-834) | C39: MR-FP-03 | D39: Pay via QR scan | E39: High | G39: Requester generates a QR for the request; requested party scans it, previews the request, taps Pay, confirms | H39: QR validated (not expired/used); transfer executes as MR-FP-02; QR invalidated after use; status → `COMPLETED` | I39: Not Tested | J39: Negative | K39: Web | L39: Project docs | N39: No | P39: B2B
A40: EMI-B2B-8252 | B40: A. Money Request (EMI-834) | C40: MR-NE-01 | D40: Accept blocked by insufficient balance | E40: High | G40: Requested party has balance < amount + fees; taps Pay and confirms | H40: Validation fails with `INSUFFICIENT_FUNDS`; status → `FAILED`; both notified with the reason; no ledger entries applied | I40: Not Tested | J40: Negative | K40: Web | L40: Project docs | N40: No | P40: B2B
... A48: EMI-B2B-8260 | B48: A. Money Request (EMI-834) | C48: MR-SEC-03 | D48: Request-ID enumeration is rate-limited | E48: Low | G48: Attempt many rapid lookups of random request IDs | H48: Rate limiting triggers (429); suspicious pattern logged/alerted | I48: Not Tested | J48: Edge / Boundary | K48: Web | L48: Project docs | N48: No | P48: B2B
A49: EMI-B2B-8258 | B49: A. Money Request (EMI-834) | C49: MR-SEC-01 | D49: Only the intended requested profile can act on a request | E49: High | G49: A different, unrelated profile attempts to Accept using the request's ID | H49: Rejected with 403 Unauthorized; event logged | I49: Not Tested | J49: Security | K49: Web | L49: Project docs | N49: Yes | O49: MoneyRequest/functional/MoneyRequestFlow.spec.ts | P49: B2B
A50: EMI-B2B-8261 | B50: A. Money Request (EMI-834) | C50: MR-SEC-04 | D50: No sensitive data exposed in notifications/logs | E50: Medium | G50: Inspect request notifications and non-privileged logs | H50: No PII beyond amount and requester name; full details access-audited | I50: Not Tested | J50: Security | K50: Web | L50: Project docs | N50: No | P50: B2B
A51: EMI-B2B-8239 | B51: A. Money Request (EMI-834) | C51: MR-CC-01 | D51: Double-tap Pay does not double-charge (idempotency) | E51: High | G51: Requested party taps Pay twice in quick succession | H51: Locking/idempotency ensures only one transaction is created; the second attempt returns an idempotent/duplicate response | I51: Not Tested | J51: Integration | K51: Web | L51: Project docs | N51: No | P51: B2B
A52: EMI-B2B-8240 | B52: A. Money Request (EMI-834) | C52: MR-CC-02 | D52: Two devices race to pay the same QR | E52: Medium | G52: Simulate two near-simultaneous Pay attempts on the same QR | H52: Only the first is processed; the second returns `QR_ALREADY_USED` / `REQUEST_PROCESSING` with no debit | I52: Not Tested | J52: Integration | K52: Web | L52: Project docs | N52: No | P52: B2B
A53: EMI-B2B-8263 | B53: A. Money Request (EMI-834) | C53: MR-UI-02 | D53: Payment breakdown is accurate before confirming | E53: High | G53: Requested party opens the Pay screen | H53: Amount requested, commission, VAT, and total to debit are shown and match backend calculation; Confirm disabled if insufficient funds | I53: Not Tested | J53: Usability | K53: Web | L53: Project docs | N53: No | P53: B2B
A54: EMI-B2B-8264 | B54: A. Money Request (EMI-834) | C54: MR-UI-03 | D54: QR modal shows expiry, one-time flag, and share/download | E54: Medium | G54: Requester generates a QR | H54: QR image renders; Share and Download both work; expiry and "one-time use" flag are visible | I54: Not Tested | J54: Usability | K54: Web | L54: Project docs | N54: No | P54: B2B
A55: EMI-B2B-8257 | B55: A. Money Request (EMI-834) | C55: MR-REC-02 | D55: Notification-service outage doesn't block the request | E55: Low | G55: Create a request while the notification service is down | H55: Request is still persisted; notification is queued/retried; UI shows a pending-notification state until delivery | I55: Not Tested | J55: Usability | K55: Web | L55: Project docs | N55: No | P55: B2B
A56: EMI-B2B-8266 | B56: B. Pay Bill (Business/Customer — EMI-170) | C56: PB-01 | D56: Approved, due bill is payable | E56: High | G56: Open Received Bills, select a bill with status Approved and issue date reached, pay it | H56: Payment proceeds to summary/confirmation without blocking | I56: Not Tested | J56: Functional | K56: Web | L56: Project docs | M56: EMI-170 | N56: No | P56: B2B
A57: EMI-B2B-8267 | B57: B. Pay Bill (Business/Customer — EMI-170) | C57: PB-02 | D57: Pending/unapproved bill cannot be paid | E57: High | G57: Attempt to pay a bill that has not yet been approved | H57: Pay action is blocked/unavailable for the bill | I57: Not Tested | J57: Functional | K57: Web | L57: Project docs | M57: EMI-170 | N57: No | P57: B2B
A58: EMI-B2B-8270 | B58: B. Pay Bill (Business/Customer — EMI-170) | C58: PB-05 | D58: Successful payment updates bill status | E58: High | G58: Pay an eligible bill to completion | H58: Bill status updates to Paid; a payment confirmation is generated | I58: Not Tested | J58: Functional | K58: Web | L58: Project docs | M58: EMI-170 | N58: No | P58: B2B
A59: EMI-B2B-8271 | B59: B. Pay Bill (Business/Customer — EMI-170) | C59: PB-06 | D59: Wallet debited by exact bill amount | E59: High | G59: Note wallet balance before paying, pay a bill, check balance after | H59: `NewBalance = OldBalance − BillAmount` exactly | I59: Not Tested | J59: Functional | K59: Web | L59: Project docs | M59: EMI-170 | N59: No | P59: B2B
A60: EMI-B2B-8272 | B60: B. Pay Bill (Business/Customer — EMI-170) | C60: PB-07 | D60: Successful transaction appears with SUCCESS status | E60: High | G60: Pay a bill, open Transactions | H60: Newest transaction row shows the bill amount with a `SUCCESS` status (allow for a brief `Pending` → `Success` ledger-sync delay) | I60: Not Tested | J60: Functional | K60: Web | L60: Project docs | M60: EMI-170 | N60: No | P60: B2B
A61: EMI-B2B-8273 | B61: B. Pay Bill (Business/Customer — EMI-170) | C61: PB-08 | D61: Insufficient funds blocks payment | E61: High | G61: Drain wallet to below the bill amount, attempt payment | H61: "Insufficient fund" toast is shown; bill status/due date unaffected; no debit occurs | I61: Not Tested | J61: Functional | K61: Web | L61: Project docs | M61: EMI-170 | N61: No | P61: B2B
A62: EMI-B2B-8269 | B62: B. Pay Bill (Business/Customer — EMI-170) | C62: PB-04 | D62: Not-yet-due bill blocked from payment | E62: Medium | G62: Attempt to pay a bill whose issue date is in the future | H62: Payment is blocked until the issue date is reached | I62: Not Tested | J62: Functional | K62: Web | L62: Project docs | M62: EMI-170 | N62: No | P62: B2B
A63: EMI-B2B-8268 | B63: B. Pay Bill (Business/Customer — EMI-170) | C63: PB-03 | D63: Already-Paid bill cannot be paid again | E63: High | G63: Attempt to pay a bill already marked Paid | H63: System rejects — bill is not processed a second time | I63: Not Tested | J63: Negative | K63: Web | L63: Project docs | M63: EMI-170 | N63: No | P63: B2B
A64: EMI-B2B-8274 | B64: B. Pay Bill (Business/Customer — EMI-170) | C64: PB-09 | D64: Failed payment allows retry without side effects | E64: Medium | G64: Force a payment failure (e.g. gateway error) | H64: Clear error message shown; bill remains payable; due date/status unchanged; user can retry | I64: Not Tested | J64: Negative | K64: Web | L64: Project docs | M64: EMI-170 | N64: No | P64: B2B
A65: EMI-B2B-8275 | B65: B. Pay Bill (Business/Customer — EMI-170) | C65: PB-10 | D65: Bill detail shows full amount breakdown before paying | E65: Medium | G65: Open a bill's detail/summary before confirming payment | H65: Initial amount, discount, VAT, and total are all visible and correctly summed | I65: Not Tested | J65: Usability | K65: Web | L65: Project docs | M65: EMI-170 | N65: No | P65: B2B
A66: EMI-B2B-8276 | B66: B. Pay Bill (Business/Customer — EMI-170) | C66: PB-11 | D66: "Pay another bill" from success screen | E66: Low | G66: Complete a payment, tap "Pay another bill" on the success popup | H66: User is returned to the Received Bills list, able to select another bill | I66: Not Tested | J66: Usability | K66: Web | L66: Project docs | M66: EMI-170 | N66: No | P66: B2B
A67: EMI-B2B-8277 | B67: B. Pay Bill (Business/Customer — EMI-170) | C67: PB-12 | D67: "Go to Home" from success screen | E67: Low | G67: Complete a payment, tap "Go to Home" | H67: User lands on the dashboard/home page | I67: Not Tested | J67: Usability | K67: Web | L67: Project docs | M67: EMI-170 | N67: No | P67: B2B
A68: EMI-B2B-8279 | B68: B. Reconciliation (EMI-4537, epic EMI-2177) | C68: RCN-02 | D68: Amount/status/date discrepancy flagged | E68: High | G68: Import a statement where a matched TXN's amount, status, or date differs from the system record | H68: Mismatch report lists the discrepancy with both values | I68: Not Tested | J68: Functional | K68: Web | L68: Project docs | N68: Yes | O68: Reconciliation/api/ReconciliationFlow.spec.ts | P68: B2B
