Workbook

Sheet Overview
A1: Category | B1: Details
A2: Document Name | B2: EMI Manual Test Cases — Consolidated
A3: Epic / Story Ref | B3: EMI-5914 PoS Transactions · EMI-5944 Balances · EMI-5824 Device Mgmt · EMI-6031 Payments TTL · EMI Tasks
A4: Release Number | B4: V 6.6.0 / Sprint 74 and backlog
A5: Environment | B5: UAT
A6: Testing Period | B6: Sprint Test Execution Cycle
A9: EMI Manual Test Cases — Results by Suite
A11: Suite | B11: Passed | C11: Failed | D11: Partially Passed | E11: Not Tested | F11: Not Implemented | G11: Total Checks | H11: Pass Rate %
A12: PoS Transactions V6.6.0 (EMI-5914) | B12: =COUNTIFS('All Test Cases'!$A:$A,$A12,'All Test Cases'!$J:$J,"Passed") | C12: =COUNTIFS('All Test Cases'!$A:$A,$A12,'All Test Cases'!$J:$J,"Failed") | D12: =COUNTIFS('All Test Cases'!$A:$A,$A12,'All Test Cases'!$J:$J,"Partially Passed") | E12: =COUNTIFS('All Test Cases'!$A:$A,$A12,'All Test Cases'!$J:$J,"Not Tested") | F12: =COUNTIFS('All Test Cases'!$A:$A,$A12,'All Test Cases'!$J:$J,"Not Implemented") | G12: =SUM(B12:F12) | H12: =IF(G12>0, B12/G12, 0)
A13: Balances & Wallet Consistency (EMI-5944) | B13: =COUNTIFS('All Test Cases'!$A:$A,$A13,'All Test Cases'!$J:$J,"Passed") | C13: =COUNTIFS('All Test Cases'!$A:$A,$A13,'All Test Cases'!$J:$J,"Failed") | D13: =COUNTIFS('All Test Cases'!$A:$A,$A13,'All Test Cases'!$J:$J,"Partially Passed") | E13: =COUNTIFS('All Test Cases'!$A:$A,$A13,'All Test Cases'!$J:$J,"Not Tested") | F13: =COUNTIFS('All Test Cases'!$A:$A,$A13,'All Test Cases'!$J:$J,"Not Implemented") | G13: =SUM(B13:F13) | H13: =IF(G13>0, B13/G13, 0)
A14: PoS Device Management (EMI-5824) | B14: =COUNTIFS('All Test Cases'!$A:$A,$A14,'All Test Cases'!$J:$J,"Passed") | C14: =COUNTIFS('All Test Cases'!$A:$A,$A14,'All Test Cases'!$J:$J,"Failed") | D14: =COUNTIFS('All Test Cases'!$A:$A,$A14,'All Test Cases'!$J:$J,"Partially Passed") | E14: =COUNTIFS('All Test Cases'!$A:$A,$A14,'All Test Cases'!$J:$J,"Not Tested") | F14: =COUNTIFS('All Test Cases'!$A:$A,$A14,'All Test Cases'!$J:$J,"Not Implemented") | G14: =SUM(B14:F14) | H14: =IF(G14>0, B14/G14, 0)
A15: Payments TTL & Invalidation (EMI-6031) | B15: =COUNTIFS('All Test Cases'!$A:$A,$A15,'All Test Cases'!$J:$J,"Passed") | C15: =COUNTIFS('All Test Cases'!$A:$A,$A15,'All Test Cases'!$J:$J,"Failed") | D15: =COUNTIFS('All Test Cases'!$A:$A,$A15,'All Test Cases'!$J:$J,"Partially Passed") | E15: =COUNTIFS('All Test Cases'!$A:$A,$A15,'All Test Cases'!$J:$J,"Not Tested") | F15: =COUNTIFS('All Test Cases'!$A:$A,$A15,'All Test Cases'!$J:$J,"Not Implemented") | G15: =SUM(B15:F15) | H15: =IF(G15>0, B15/G15, 0)
A16: EMI Task Coverage | B16: =COUNTIFS('All Test Cases'!$A:$A,$A16,'All Test Cases'!$J:$J,"Passed") | C16: =COUNTIFS('All Test Cases'!$A:$A,$A16,'All Test Cases'!$J:$J,"Failed") | D16: =COUNTIFS('All Test Cases'!$A:$A,$A16,'All Test Cases'!$J:$J,"Partially Passed") | E16: =COUNTIFS('All Test Cases'!$A:$A,$A16,'All Test Cases'!$J:$J,"Not Tested") | F16: =COUNTIFS('All Test Cases'!$A:$A,$A16,'All Test Cases'!$J:$J,"Not Implemented") | G16: =SUM(B16:F16) | H16: =IF(G16>0, B16/G16, 0)
A17: Total | B17: =SUM(B12:B16) | C17: =SUM(C12:C16) | D17: =SUM(D12:D16) | E17: =SUM(E12:E16) | F17: =SUM(F12:F16) | G17: =SUM(G12:G16) | H17: =IF(G17>0, B17/G17, 0)
A19: Coverage by Test Type
A20: Test Type | B20: Test Cases | C20: Share
A21: Functional | B21: =COUNTIF('All Test Cases'!$K:$K,$A21) | C21: =IF($B$17>0,B21/1037,0)
A22: Negative | B22: =COUNTIF('All Test Cases'!$K:$K,$A22) | C22: =IF($B$17>0,B22/1037,0)
A23: Integration | B23: =COUNTIF('All Test Cases'!$K:$K,$A23) | C23: =IF($B$17>0,B23/1037,0)
A24: Edge / Boundary | B24: =COUNTIF('All Test Cases'!$K:$K,$A24) | C24: =IF($B$17>0,B24/1037,0)
A25: Security | B25: =COUNTIF('All Test Cases'!$K:$K,$A25) | C25: =IF($B$17>0,B25/1037,0)
A26: Performance / NFR | B26: =COUNTIF('All Test Cases'!$K:$K,$A26) | C26: =IF($B$17>0,B26/1037,0)
A27: Compliance | B27: =COUNTIF('All Test Cases'!$K:$K,$A27) | C27: =IF($B$17>0,B27/1037,0)
A28: Configuration | B28: =COUNTIF('All Test Cases'!$K:$K,$A28) | C28: =IF($B$17>0,B28/1037,0)
A29: Reporting | B29: =COUNTIF('All Test Cases'!$K:$K,$A29) | C29: =IF($B$17>0,B29/1037,0)
A30: Cross-Platform | B30: =COUNTIF('All Test Cases'!$K:$K,$A30) | C30: =IF($B$17>0,B30/1037,0)
A31: Usability | B31: =COUNTIF('All Test Cases'!$K:$K,$A31) | C31: =IF($B$17>0,B31/1037,0)
A32: Contract / API | B32: =COUNTIF('All Test Cases'!$K:$K,$A32) | C32: =IF($B$17>0,B32/1037,0)
... A38: Migration | B38: =COUNTIF('All Test Cases'!$K:$K,$A38) | C38: =IF($B$17>0,B38/1037,0)
A40: Test Execution Statuses & Definitions
A41: Status | B41: Definition / Criteria | C41: Allowed In Workflow
A42: Passed | B42: All test steps executed with actual result matching the expected result | C42: Yes
A43: Failed | B43: One or more test steps failed or produced an incorrect result | C43: Yes
A44: Partially Passed | B44: Core functionality works but a secondary assertion did not | C44: Yes
A45: Not Tested | B45: Test case is ready for execution in the current cycle | C45: Yes (Default)
A46: Not Implemented | B46: Feature or endpoint dependency is currently unavailable | C46: Yes
A47: NA | B47: Scenario is not applicable to the current scope or configuration | C47: Yes

Sheet All Test Cases
A1: Suite | B1: Feature / Story | C1: Subtopic | D1: TC ID | E1: Title | F1: Priority | G1: Preconditions | H1: Steps | I1: Expected Result | J1: Status | K1: Test Type
A2: PoS Transactions V6.6.0 (EMI-5914) | B2: Callback Ingestion & Valid | C2: Functional | D2: TC-Callback-01 | E2: Valid Purchase Callback | F2: High | G2: Callback endpoint reachable; TID linked to an active wallet | H2: 1. Submit a well-formed PURCHASE callback with all mandatory canonical fields (event_type, provider_txn_id, tid, mid, instrument, status, amount, currency, occurred_at) | I2: ACCEPTED; PosTransaction created; origin=TXN_CALLBACK; wallet_id snapshotted | J2: NA | K2: Functional
A3: PoS Transactions V6.6.0 (EMI-5914) | B3: Callback Ingestion & Valid | C3: Functional | D3: TC-Callback-02 | E3: Persisted Record Integrity | F3: Medium | G3: A purchase callback has been accepted (see Valid Purchase Callback) | H3: 1. Query the stored PosTransaction record for the accepted callback 2. Compare stored STAN, RRN, TID, MID, amount and masked_pan against the source payload | I3: Stored STAN, RRN, TID, MID, amount, masked PAN, etc. match the source payload | J3: NA | K3: Functional
A4: PoS Transactions V6.6.0 (EMI-5914) | B4: Callback Ingestion & Valid | C4: Functional | D4: TC-Callback-03 | E4: Per-TID Ledger Entry Written on Acceptance | F4: Medium | G4: A purchase callback has been accepted | H4: 1. Query the stored transaction's ledger status/reason field | I4: Exactly one per-TID ledger entry (EMI-5915's booking pipeline output) is written for the accepted transaction; the entry carries the callback's status/reason; no wallet balance effect occurs at this point. | J4: NA | K4: Edge / Boundary
A5: PoS Transactions V6.6.0 (EMI-5914) | B5: Callback Ingestion & Valid | C5: Functional | D5: TC-Callback-04 | E5: Failed Callback Persistence | F5: Medium | G5: Callback endpoint available | H5: 1. Submit a callback that fails validation or processing (e.g. terminal rejection) 2. Query the base transaction/callback table | I5: Failed callback is recorded in the required base transaction/callback table with the correct failure reason | J5: NA | K5: Negative
A6: PoS Transactions V6.6.0 (EMI-5914) | B6: Callback Ingestion & Valid | C6: Functional | D6: TC-Callback-05 | E6: Masked Archive & Retention (All Outcomes) | F6: Medium | G6: Ingestion log/archive accessible | H6: 1. Submit callbacks producing each outcome (ACCEPTED, TERMINAL, RETRYABLE, UNMATCHED, COMPLIANCE_HOLD, DUPLICATE) 2. Inspect the archived record for each outcome | I6: Every outcome type is archived masked with 7-year retention; no plaintext PAN appears in any archived record | J6: NA | K6: Integration
A7: PoS Transactions V6.6.0 (EMI-5914) | B7: Callback Ingestion & Valid | C7: Functional | D7: TC-Callback-06 | E7: wallet_id Snapshot Immutability | F7: Medium | G7: TID currently linked to a wallet | H7: 1. Submit an accepted callback for a linked TID 2. Re-link the TID to a different wallet in the registry 3. Query the original transaction's wallet_id | I7: wallet_id is snapshotted immutably at TID resolution time and does not change even if the TID's wallet link changes afterward | J7: NA | K7: Functional
A8: PoS Transactions V6.6.0 (EMI-5914) | B8: Callback Ingestion & Valid | C8: Functional | D8: TC-Callback-07 | E8: Direct Pipeline Invocation — Valid Booking | F8: High | G8: Shared booking pipeline exposed as a callable service entry point; a valid, well-formed transaction payload | H8: 1. Invoke the pipeline directly as EMI-5991 would, with origin=RECON_BACKFILL, for a valid transaction | I8: Transaction is validated, resolved, passed through Gate 1, and booked identically to the callback path; origin=RECON_BACKFILL is set; no branch bypasses a control | J8: NA | K8: Functional
A9: PoS Transactions V6.6.0 (EMI-5914) | B9: Callback Ingestion & Valid | C9: Functional | D9: TC-Callback-08 | E9: Direct Pipeline Invocation — Unknown TID | F9: High | G9: Shared booking pipeline exposed as a callable service entry point; TID with no wallet mapping | H9: 1. Invoke the pipeline directly as EMI-5991 would, with origin=RECON_BACKFILL, for a transaction whose TID is unknown/unregistered | I9: Transaction is accepted and parked UNMATCHED with Ops alarm, identical to the callback path; origin=RECON_BACKFILL is set | J9: NA | K9: Negative
A10: PoS Transactions V6.6.0 (EMI-5914) | B10: Callback Ingestion & Valid | C10: Functional | D10: TC-Callback-09 | E10: Direct Pipeline Invocation — Gate 1 Hold | F10: High | G10: Shared booking pipeline exposed as a callable service entry point; wallet flagged for AML/sanctions/SAMA breach | H10: 1. Invoke the pipeline directly as EMI-5991 would, with origin=RECON_BACKFILL, for a transaction that should trigger a Gate 1 hold | I10: Gate 1 produces COMPLIANCE_HOLD with no wallet ledger entries, identical to the callback path; no branch bypasses the compliance gate | J10: NA | K10: Functional
A11: PoS Transactions V6.6.0 (EMI-5914) | B11: Callback Ingestion & Valid | C11: Functional | D11: TC-Callback-10 | E11: Callback Header Validation | F11: Medium | G11: Published integration contract defines required headers | H11: 1. Submit a valid payload with a missing or incorrect required header (e.g. Content-Type, Accept-Language) | I11: Invalid/missing required headers are rejected according to the agreed integration contract | J11: NA | K11: Negative
A12: PoS Transactions V6.6.0 (EMI-5914) | B12: Callback Ingestion & Valid | C12: Functional | D12: TC-Callback-11 | E12: Empty/Malformed Request | F12: Medium | G12: Ingestion endpoint available | H12: 1. Submit a POST with an empty body 2. Submit a structurally broken/malformed transport payload | I12: Empty body or malformed transport payload returns a controlled validation error, not HTTP 500/unhandled exception | J12: NA | K12: Negative
... A1038: EMI Task Coverage | B1038: Customer App Updates | C1038: Platform | D1038: TC-App-17 | E1038: Design Alignment Is Consistent Between iOS and Android | F1038: Medium | G1038: Both business builds | H1038: 1. Compare the affected screens side by side | I1038: The two platforms align with the intended design and with each other; neither diverges into its own layout | J1038: Not Tested | K1038: Cross-Platform
