Workbook

Sheet Overview
A1: Category | B1: Details
A2: Document Name | B2: Balances & Wallet Consistency testcases
A3: Epic / Story Ref | B3: EMI-5944 Balances & Wallet Consistency Epic
A4: Release Number | B4: Backlog - not yet scheduled to a release
A5: Environment | B5: UAT
A6: Testing Period | B6: Sprint Test Execution Cycle
A9: EMI-5944 Balances & Wallet Consistency — Test Case Results by Category
A11: Category (Feature / Story) | B11: Passed | C11: Failed | D11: Partially Passed | E11: Not Tested | F11: Not Implemented | G11: Total Checks | H11: Pass Rate %
A12: EMI-5947 — Balance Consumer Partitioning by Wallet | B12: =COUNTIF('Consumer Partitioning'!H2:H400, "Passed") | C12: =COUNTIF('Consumer Partitioning'!H2:H400, "Failed") | D12: =COUNTIF('Consumer Partitioning'!H2:H400, "Partially Passed") | E12: =COUNTIF('Consumer Partitioning'!H2:H400, "Not Tested") | F12: =COUNTIF('Consumer Partitioning'!H2:H400, "Not Implemented") | G12: =SUM(B12:F12) | H12: =IF(G12>0, B12/G12, 0)
A13: EMI-5948 — Balance Consumer Idempotency | B13: =COUNTIF('Consumer Idempotency'!H2:H400, "Passed") | C13: =COUNTIF('Consumer Idempotency'!H2:H400, "Failed") | D13: =COUNTIF('Consumer Idempotency'!H2:H400, "Partially Passed") | E13: =COUNTIF('Consumer Idempotency'!H2:H400, "Not Tested") | F13: =COUNTIF('Consumer Idempotency'!H2:H400, "Not Implemented") | G13: =SUM(B13:F13) | H13: =IF(G13>0, B13/G13, 0)
A14: EMI-5949 — Transaction Lifecycle Ordering Guard | B14: =COUNTIF('Lifecycle Ordering Guard'!H2:H400, "Passed") | C14: =COUNTIF('Lifecycle Ordering Guard'!H2:H400, "Failed") | D14: =COUNTIF('Lifecycle Ordering Guard'!H2:H400, "Partially Passed") | E14: =COUNTIF('Lifecycle Ordering Guard'!H2:H400, "Not Tested") | F14: =COUNTIF('Lifecycle Ordering Guard'!H2:H400, "Not Implemented") | G14: =SUM(B14:F14) | H14: =IF(G14>0, B14/G14, 0)
A15: EMI-5945 — Statement History Rebuild | B15: =COUNTIF('Statement History Rebuild'!H2:H400, "Passed") | C15: =COUNTIF('Statement History Rebuild'!H2:H400, "Failed") | D15: =COUNTIF('Statement History Rebuild'!H2:H400, "Partially Passed") | E15: =COUNTIF('Statement History Rebuild'!H2:H400, "Not Tested") | F15: =COUNTIF('Statement History Rebuild'!H2:H400, "Not Implemented") | G15: =SUM(B15:F15) | H15: =IF(G15>0, B15/G15, 0)
A16: EMI-5946 — Wallet Balance Recompute | B16: =COUNTIF('Wallet Balance Recompute'!H2:H400, "Passed") | C16: =COUNTIF('Wallet Balance Recompute'!H2:H400, "Failed") | D16: =COUNTIF('Wallet Balance Recompute'!H2:H400, "Partially Passed") | E16: =COUNTIF('Wallet Balance Recompute'!H2:H400, "Not Tested") | F16: =COUNTIF('Wallet Balance Recompute'!H2:H400, "Not Implemented") | G16: =SUM(B16:F16) | H16: =IF(G16>0, B16/G16, 0)
A17: EMI-5950 — Bucket Identity Validation & Variance Detection | B17: =COUNTIF('Bucket Identity Validation'!H2:H400, "Passed") | C17: =COUNTIF('Bucket Identity Validation'!H2:H400, "Failed") | D17: =COUNTIF('Bucket Identity Validation'!H2:H400, "Partially Passed") | E17: =COUNTIF('Bucket Identity Validation'!H2:H400, "Not Tested") | F17: =COUNTIF('Bucket Identity Validation'!H2:H400, "Not Implemented") | G17: =SUM(B17:F17) | H17: =IF(G17>0, B17/G17, 0)
A18: EMI-5951 — Stuck Reserve Detection | B18: =COUNTIF('Stuck Reserve Detection'!H2:H400, "Passed") | C18: =COUNTIF('Stuck Reserve Detection'!H2:H400, "Failed") | D18: =COUNTIF('Stuck Reserve Detection'!H2:H400, "Partially Passed") | E18: =COUNTIF('Stuck Reserve Detection'!H2:H400, "Not Tested") | F18: =COUNTIF('Stuck Reserve Detection'!H2:H400, "Not Implemented") | G18: =SUM(B18:F18) | H18: =IF(G18>0, B18/G18, 0)
A19: EMI-5954 — Wallet Daily Close (EOD Snapshot & Anchor) | B19: =COUNTIF('Wallet Daily Close'!H2:H400, "Passed") | C19: =COUNTIF('Wallet Daily Close'!H2:H400, "Failed") | D19: =COUNTIF('Wallet Daily Close'!H2:H400, "Partially Passed") | E19: =COUNTIF('Wallet Daily Close'!H2:H400, "Not Tested") | F19: =COUNTIF('Wallet Daily Close'!H2:H400, "Not Implemented") | G19: =SUM(B19:F19) | H19: =IF(G19>0, B19/G19, 0)
A20: EMI-5955 — EMI_MISSING Hybrid Resolution | B20: =COUNTIF('EMI_MISSING Resolution'!H2:H400, "Passed") | C20: =COUNTIF('EMI_MISSING Resolution'!H2:H400, "Failed") | D20: =COUNTIF('EMI_MISSING Resolution'!H2:H400, "Partially Passed") | E20: =COUNTIF('EMI_MISSING Resolution'!H2:H400, "Not Tested") | F20: =COUNTIF('EMI_MISSING Resolution'!H2:H400, "Not Implemented") | G20: =SUM(B20:F20) | H20: =IF(G20>0, B20/G20, 0)
A21: EMI-5944 — End-to-End Balance Consistency Flows | B21: =COUNTIF('E2E Balances Flows'!H2:H400, "Passed") | C21: =COUNTIF('E2E Balances Flows'!H2:H400, "Failed") | D21: =COUNTIF('E2E Balances Flows'!H2:H400, "Partially Passed") | E21: =COUNTIF('E2E Balances Flows'!H2:H400, "Not Tested") | F21: =COUNTIF('E2E Balances Flows'!H2:H400, "Not Implemented") | G21: =SUM(B21:F21) | H21: =IF(G21>0, B21/G21, 0)
A22: Total | B22: =SUM(B12:B21) | C22: =SUM(C12:C21) | D22: =SUM(D12:D21) | E22: =SUM(E12:E21) | F22: =SUM(F12:F21) | G22: =SUM(G12:G21) | H22: =IF(G22>0, B22/G22, 0)
A24: Test Execution Statuses & Definitions
A25: Status | B25: Definition / Criteria | C25: Allowed In Workflow
A26: Passed | B26: All test steps executed with actual result matching the expected result | C26: Yes
A27: Failed | B27: One or more test steps failed or produced an incorrect result | C27: Yes
A28: Partially Passed | B28: Core functionality works but a secondary assertion did not | C28: Yes
A29: Not Tested | B29: Test case is ready for execution in the current cycle | C29: Yes (Default)
A30: Not Implemented | B30: Feature or endpoint dependency is currently unavailable | C30: Yes
A31: NA | B31: Scenario is not applicable to the current scope or configuration | C31: Yes
A33: Note
A34: Full epic coverage. The epic owns three things in priority order and each has its own sheets here: PREVENTION (EMI-5947 partitioning, EMI-5948 idempotency, EMI-5949 lifecycle ordering), DETECTION (EMI-5950 identity and conservation, EMI-5951 stuck reserves) and REPAIR (EMI-5946 recompute for balances, EMI-5945 rebuild for statements). EMI-5954 seals the day and EMI-5955 resolves bank-statement gaps by appended postings. EMI-5947, 5948 and 5949 are typed as Tasks rather than Stories in Jira, so a story-level coverage query will not see them — check issuetype = Task under this epic when re-running any gap analysis.

Sheet Consumer Partitioning
A1: Subtopic / Category | B1: TC ID | C1: Title | D1: Priority | E1: Preconditions | F1: Steps | G1: Expected Result | H1: Status | I1: Test Type
A2: Partitioning | B2: TC-Partition-01 | C2: Every CDC Event for a Wallet Lands on the Same Partition | D2: High | E2: Balance CDC topic re-keyed on wallet_id; a wallet with postings across many ledger entries | F2: 1. Generate a spread of postings for one wallet 2. Inspect the partition each resulting event was produced to | G2: Every event for that wallet is produced to a single partition; no event for the wallet appears on any other partition | H2: Not Tested | I2: Integration
A3: Partitioning | B3: TC-Partition-02 | C3: Topic Is Keyed on wallet_id, Not the Ledger Entry Primary Key | D3: High | E3: Access to the Debezium connector configuration and the produced messages | F3: 1. Inspect the message key on a sample of produced events 2. Inspect the re-keying stage in the connector configuration | G3: The message key is wallet_id, applied by an SMT or equivalent re-keying stage; it is no longer the source table primary key | H3: Not Tested | I3: Integration
A4: Partitioning | B4: TC-Partition-03 | C4: Different Wallets Distribute Across Partitions | D4: Medium | E4: Many wallets producing traffic | F4: 1. Generate traffic across a large set of wallets 2. Inspect the partition distribution | G4: Events spread across the available partitions by wallet, so per-wallet ordering does not collapse all traffic onto one partition | H4: Not Tested | I4: Integration
A5: Serialisation | B5: TC-Partition-04 | C5: Consumer Applies One Wallet's Events Strictly Serially | D5: High | E5: Consumer running under load with concurrent processing enabled | F5: 1. Drive concurrent postings for a single wallet 2. Instrument the consumer to record concurrent application per wallet | G5: No two entries for the same wallet are ever applied concurrently; a partition is processed serially or work is hashed to threads by wallet_id | H5: Not Tested | I5: Integration
A6: Serialisation | B6: TC-Partition-05 | C6: No Configuration Permits Concurrent Application for One Wallet | D6: High | E6: Access to the consumer configuration | F6: 1. Review every concurrency, threading and batching setting available 2. Attempt to configure a mode that would apply two entries for one wallet at once | G6: No reachable configuration permits it; the serial guarantee is structural rather than dependent on an operator setting it correctly | H6: Not Tested | I6: Integration
A7: Ordering | B7: TC-Partition-06 | C7: PENDING and SUCCESS for One Wallet Apply in Commit Order | D7: High | E7: A wallet with a reserve followed by a settlement | F7: 1. Produce the two postings in quick succession under load 2. Inspect the order in which the consumer applied them and the resulting buckets | G7: They are applied in commit order and the buckets are correct; the settlement is never applied before its reserve on this wallet | H7: Not Tested | I7: Integration
A8: Ordering | B8: TC-Partition-07 | C8: Load Test That Previously Reproduced Out-of-Order No Longer Does | D8: High | E8: The load profile that previously produced out-of-order application | F8: 1. Run the load test at the same volume and shape 2. Inspect for any out-of-order application per wallet | G8: No out-of-order application occurs for any wallet under the profile that previously reproduced it | H8: Not Tested | I8: Performance / NFR
A9: Ordering | B9: TC-Partition-08 | C9: Ordering Holds Under a Forced Consumer Rebalance | D9: High | E9: Consumer group running under sustained load | F9: 1. Force a consumer group rebalance mid-stream 2. Continue the load through the rebalance 3. Verify per-wallet ordering and final balances | G9: Per-wallet ordering holds across the rebalance and final balances are correct | H9: Not Tested | I9: Integration
A10: Ordering | B10: TC-Partition-09 | C10: Ordering Holds Across a Connector Restart | D10: High | E10: Debezium connector running under load | F10: 1. Restart the connector mid-stream 2. Verify per-wallet ordering and final balances after recovery | G10: Ordering holds across the restart; no wallet ends in an incorrect state | H10: Not Tested | I10: Integration
A11: Regression | B11: TC-Partition-10 | C11: EMI-2059 Sequence Replays With a Correct Cumulative Balance | D11: High | E11: The transaction sequence recorded on EMI-2059 | F11: 1. Replay the sequence through the re-keyed pipeline 2. Check available_balance after every entry, not only at the end | G11: The cumulative available_balance is correct at every entry; it neither jumps nor stays flat despite the debits and credits. This is the regression guard for the closed defect | H11: Not Tested | I11: Integration
A12: Regression | B12: TC-Partition-11 | C12: Balances Agree With History After Replay | D12: High | E12: A wallet replayed through the re-keyed pipeline | F12: 1. Compare the projected balance against the entry history | G12: Balance and history agree; the discrepancy signature recorded in the EMI-3506 QA trail does not reproduce | H12: Not Tested | I12: Integration
... A27: Ordering | B27: TC-Partition-26 | C27: Thread-Hashed Processing Keeps One Wallet on One Thread | D27: High | E27: Consumer configured to hash work to threads by wallet_id rather than one thread per partition | F27: 1. Send interleaved postings for several wallets sharing a partition 2. Trace which thread handles each wallet | G27: A wallet's events are always handled by the same thread and never processed concurrently. Serial application is a property of the wallet, not merely of the partition | H27: Not Tested | I27: Integration

Sheet Consumer Idempotency
A1: Subtopic / Category | B1: TC ID | C1: Title | D1: Priority | E1: Preconditions | F1: Steps | G1: Expected Result | H1: Status | I1: Test Type
A2: Idempotency | B2: TC-Idem-01 | C2: Applying the Same Ledger Entry Twice Has One Effect | D2: High | E2: Consumer running with the uniqueness guard in place | F2: 1. Deliver the same ledger entry event twice 2. Count projection rows and inspect the balance | G2: Exactly one projection row exists and exactly one balance effect is applied | H2: Not Tested | I2: Edge / Boundary
A3: Idempotency | B3: TC-Idem-02 | C3: Uniqueness Is Enforced by Constraint on Ledger Entry Identity | D3: High | E3: Direct database access | F3: 1. Attempt to insert a second projection row for the same ledger entry identity, bypassing the application | G3: The database rejects it; uniqueness is a constraint, not an application-level check | H3: Not Tested | I3: Integration
A4: Idempotency | B4: TC-Idem-03 | C4: Duplicate Is Discarded, Not Errored | D4: High | E4: A duplicate event delivered to the consumer | F4: 1. Deliver the duplicate 2. Observe the consumer outcome and the error channel | G4: The duplicate is detected and discarded through a conflict-tolerant insert path; it is neither applied nor raised as a processing error that would stall the consumer | H4: Not Tested | I4: Integration
A5: Idempotency | B5: TC-Idem-04 | C5: Duplicate Detection Introduces No Read-Modify-Write Race | D5: High | E5: High concurrency on the same wallet | F5: 1. Deliver duplicates concurrently under load 2. Inspect projection rows and balances | G5: Detection does not depend on a read-then-write round trip; concurrent duplicates cannot both pass the check and be applied | H5: Not Tested | I5: Integration
A6: Position | B6: TC-Idem-05 | C6: last_applied_position Is Recorded on the Wallet Snapshot | D6: High | E6: Consumer applying events for a wallet | F6: 1. Apply a series of events 2. Read last_applied_position on the wallet snapshot | G6: The position is recorded and advances monotonically in commit order, taken from the CDC commit position | H6: Not Tested | I6: Functional
A7: Position | B7: TC-Idem-06 | C7: Commit Position Requires No Ledger Schema Change | D7: High | E7: The ledger schema and a sample of Debezium events | F7: 1. Confirm the commit position is present on every Debezium event 2. Compare the transaction_log schema before and after | G7: The position is available on every event (Postgres source.lsn or MySQL binlog file and pos) and the ledger schema is unchanged | H7: Not Tested | I7: Functional
A8: Position | B8: TC-Idem-07 | C8: Stale Event Behind the Recorded Position Is Discarded | D8: High | E8: A wallet with an advanced last_applied_position | F8: 1. Deliver an event whose commit position is behind the recorded position 2. Inspect the balance, the discard counter and the log | G8: The event is discarded, counted and logged; it is never applied and never dropped without record | H8: Not Tested | I8: Functional
A9: Position | B9: TC-Idem-08 | C9: Event Exactly At the Recorded Position Is Discarded | D9: High | E9: A wallet whose last_applied_position matches an incoming event | F9: 1. Deliver an event whose commit position equals the recorded position | G9: It is discarded on the same path as a behind-position event; the comparison is at-or-behind, not strictly behind | H9: Not Tested | I9: Edge / Boundary
A10: Position | B10: TC-Idem-09 | C10: Conditional Write Is Enforced on the Write Path | D10: High | E10: Concurrent delivery of an in-order and a stale event | F10: 1. Deliver both concurrently 2. Inspect which was applied | G10: The position check is enforced on the conditional balance write itself, so a stale event cannot slip through between a check and a write | H10: Not Tested | I10: Integration
A11: Replay | B11: TC-Idem-10 | C11: Replaying an Arbitrary Topic Window Leaves Balances Unchanged | D11: High | E11: A set of wallets with known balances | F11: 1. Record all balances 2. Replay an arbitrary window of the topic 3. Re-read the balances | G11: Every balance is unchanged; the replay produces zero net effect | H11: Not Tested | I11: Integration
A12: Replay | B12: TC-Idem-11 | C12: Replaying a Full 24-Hour Window Produces Zero Net Balance Change | D12: High | E12: A day of consumed traffic and recorded balances | F12: 1. Deliberately replay the whole 24-hour window 2. Compare balances and projection row counts before and after | G12: Balances and row counts are identical; no money is moved by the replay | H12: Not Tested | I12: Integration
... A26: Observability | B26: TC-Idem-25 | C26: A Discarded Event Is Logged With Its Identity, Not Only Counted | D26: Medium | E26: Discarded-event metric in place | F26: 1. Cause a stale and a duplicate event to be discarded 2. Inspect the log record for each | G26: Each discard is recorded with the ledger entry identity, wallet, position and the reason. A counter alone cannot answer which event was dropped, which is what "never dropped without record" requires | H26: Not Tested | I26: Observability

Sheet Lifecycle Ordering Guard
A1: Subtopic / Category | B1: TC ID | C1: Title | D1: Priority | E1: Preconditions | F1: Steps | G1: Expected Result | H1: Status | I1: Test Type
A2: Guard | B2: TC-Lifecycle-01 | C2: SUCCESS Is Applied Only After Its PENDING | D2: High | E2: A transaction whose SUCCESS posting can be injected ahead of its PENDING | F2: 1. Inject the SUCCESS posting first 2. Inspect the wallet buckets and the parked queue 3. Deliver the PENDING 4. Re-inspect | G2: The SUCCESS is parked and the wallet is unchanged; once the PENDING arrives both apply and all four buckets are correct | H2: Not Tested | I2: Negative
A3: Guard | B3: TC-Lifecycle-02 | C3: FAILED Is Applied Only After Its PENDING | D3: High | E3: A transaction that reserved, with its FAILED posting injectable ahead of the PENDING | F3: 1. Inject the FAILED posting first 2. Inspect buckets and the parked queue 3. Deliver the PENDING 4. Re-inspect | G3: The FAILED is parked and nothing moves; once the PENDING arrives both apply and the reserve is correctly released back to available | H3: Not Tested | I3: Negative
A4: Guard | B4: TC-Lifecycle-03 | C4: Guard Is Enforced on the Write Path, Not as a Pre-Read Check | D4: High | E4: Concurrent delivery of a predecessor and its dependent posting | F4: 1. Deliver both concurrently under load 2. Inspect whether the dependent could be applied before the predecessor committed | G4: The condition is enforced on the write path itself; there is no window between a read-time check and the write in which a dependent posting can slip through | H4: Not Tested | I4: Integration
A5: Guard | B5: TC-Lifecycle-04 | C5: Lifecycle Stage Applied Is Recorded Per Transaction | D5: High | E5: A transaction part-way through its lifecycle | F5: 1. Apply the PENDING posting 2. Inspect the recorded applied stage for that transaction | G5: The stage already applied is recorded per transaction, so the guard does not have to infer it at read time | H5: Not Tested | I5: Negative
A6: Never Reserved | B6: TC-Lifecycle-05 | C6: FAILED for a Never-Reserved Transaction Is a No-Op, Not a Park | D6: High | E6: A transaction that never reserved, with a FAILED posting | F6: 1. Deliver the FAILED posting 2. Inspect the buckets, the entry log and the parked queue | G6: No balance change occurs and the entry is logged with change type only; it is not parked, because its predecessor never existed. This is the EMI-2013 regression guard | H6: Not Tested | I6: Negative
A7: Never Reserved | B7: TC-Lifecycle-06 | C7: Never Reserved Is Distinguished From Predecessor Not Yet Arrived | D7: High | E7: One transaction whose PENDING is delayed and one that never reserved | F7: 1. Deliver the dependent posting for each 2. Inspect how each is classified in the data | G7: The two are distinguished in the data rather than inferred at read time. Conflating them is exactly the EMI-2013 defect and must not be possible | H7: Not Tested | I7: Edge / Boundary
A8: Never Reserved | B8: TC-Lifecycle-07 | C8: A Reservation That Never Happened Is Never Reversed | D8: High | E8: The EMI-2013 scenario reproduced | F8: 1. Reproduce the scenario end to end 2. Check available before and after | G8: available is not deducted twice; no reversal is applied for a reservation that never took place | H8: Not Tested | I8: Negative
A9: Parking | B9: TC-Lifecycle-08 | C9: Parked Posting Is Never Applied and Never Silently Dropped | D9: High | E9: A posting whose predecessor has not arrived | F9: 1. Deliver it 2. Inspect the balance, the parked queue and the log | G9: The posting is parked with a record and an alert; it is neither applied nor discarded without trace | H9: Not Tested | I9: Integration
A10: Parking | B10: TC-Lifecycle-09 | C10: Parked Posting Resolves Automatically on Predecessor Arrival | D10: High | E10: A parked posting awaiting its predecessor | F10: 1. Deliver the missing predecessor 2. Observe the parked posting | G10: It resolves and applies automatically with no manual intervention, and the resulting buckets are correct | H10: Not Tested | I10: Negative
A11: Parking | B11: TC-Lifecycle-10 | C11: Posting Parked Beyond the Configured Age Is Escalated | D11: High | E11: A parked posting whose predecessor never arrives | F11: 1. Leave it parked past the configured escalation age 2. Inspect the alert channel | G11: It is escalated with an alert; a predecessor that is never coming is a genuine incident rather than a transient | H11: Not Tested | I11: Negative
A12: Parking | B12: TC-Lifecycle-11 | C12: Parked-Posting Count and Age Are Exposed as Metrics | D12: Medium | E12: Parked postings of varying ages | F12: 1. Inspect the exposed metrics and the alert threshold | G12: Count and age are exposed with a configurable alert threshold, so a systemic ordering failure is visible before it becomes an incident | H12: Not Tested | I12: Negative
... A28: Parking | B28: TC-Lifecycle-27 | C28: Guard State Survives a Consumer Restart | D28: High | E28: Transactions with postings parked awaiting a predecessor | F28: 1. Park several postings 2. Restart the consumer 3. Deliver the missing predecessors | G28: Parked postings and the per-transaction applied stage survive the restart and resolve normally. Guard state is durable, not held only in memory, or the restart would silently apply postings out of order | H28: Not Tested | I28: Integration

Sheet Statement History Rebuild
A1: Subtopic / Category | B1: TC ID | C1: Title | D1: Priority | E1: Preconditions | F1: Steps | G1: Expected Result | H1: Status | I1: Test Type
A2: Preflight | B2: TC-Rebuild-01 | C2: No-Op When Running Balance Already Matches the Ledger | D2: High | E2: A date range whose running_balance agrees with the ledger and no ledger postings created since the last successful rebuild | F2: 1. Trigger a rebuild for the range 2. Inspect running_balance, the archive table and every wallet balance in scope | G2: Run completes as NO_OP; nothing archived, no entry rewritten, no wallet balance changed; the run is still recorded in reconciliation_runs with its variance result | H2: Not Tested | I2: Functional
A3: Preflight | B3: TC-Rebuild-02 | C3: Variance Computed Before Any Mutation | D3: High | E3: A range where running_balance has drifted from the ledger | F3: 1. Trigger a rebuild 2. Trace the order of operations | G3: Variance between running_balance and the ledger-derived balance is computed before any archive or write occurs | H3: Not Tested | I3: Integration
A4: Functional | B4: TC-Rebuild-03 | C4: Rebuild Corrects a Drifted Range | D4: High | E4: A range where running_balance has drifted from the ledger | F4: 1. Trigger a rebuild for the range 2. Compare regenerated entries against ledger-derived values | G4: Entries are regenerated; all four buckets match the ledger-derived values; variance is reported per wallet and per bucket | H4: Not Tested | I4: Functional
A5: Idempotency | B5: TC-Rebuild-04 | C5: Repeated Rebuild Over an Unchanged Ledger | D5: High | E5: A completed rebuild over a range whose ledger has not changed since | F5: 1. Run the identical rebuild a second time 2. Compare the resulting running_balance state | G5: Second run completes as NO_OP; final state is identical to the state after the first run | H5: Not Tested | I5: Integration
A6: Anchor | B6: TC-Rebuild-05 | C6: Genesis Wallet Opens at Zero Across All Four Buckets | D6: Medium | E6: A wallet with no running_balance entries before from_date | F6: 1. Rebuild a range for that wallet 2. Inspect the opening balance and the run record | G6: Wallet opens at zero on available, reserve_debit, reserve_credit and current; the genesis condition is recorded on the run | H6: Not Tested | I6: Edge / Boundary
A7: Anchor | B7: TC-Rebuild-06 | C7: Mid-History Window Anchors on the Last Valid Prior Entry | D7: High | E7: A wallet with entries both before and after the chosen range | F7: 1. Rebuild only the mid-history window 2. Compare the opening balance with the after-values of the last entry strictly before from_date 3. Inspect entries after to_date | G7: Opening balance equals the after-values of the last valid entry before from_date across all four buckets; entries after to_date are untouched | H7: Not Tested | I7: Functional
A8: Replay | B8: TC-Rebuild-07 | C8: PENDING on the Source Moves Available to Reserve Debit | D8: High | E8: A range containing an outgoing PENDING posting | F8: 1. Rebuild the range 2. Inspect the replayed entry for the source wallet | G8: available decreases, reserve_debit increases by the same amount, and current is unchanged | H8: Not Tested | I8: Integration
A9: Replay | B9: TC-Rebuild-08 | C9: PENDING on the Destination Populates Reserve Credit Only | D9: High | E9: A range containing an incoming PENDING posting | F9: 1. Rebuild the range 2. Inspect the replayed entry for the destination wallet | G9: reserve_credit increases; available and current are both unchanged. This is the most commonly misread rule in the model | H9: Not Tested | I9: Integration
A10: Replay | B10: TC-Rebuild-09 | C10: SUCCESS Settles Both Sides Correctly | D10: High | E10: A range containing a PENDING followed by its SUCCESS | F10: 1. Rebuild the range 2. Inspect the source and destination entries at settlement | G10: Source: reserve_debit decreases and current decreases. Destination: reserve_credit decreases, available increases and current increases | H10: Not Tested | I10: Integration
A11: Replay | B11: TC-Rebuild-10 | C11: FAILED After a Reserve Returns the Money to Available | D11: High | E11: A range containing a PENDING followed by a FAILED where the amount was reserved | F11: 1. Rebuild the range 2. Inspect the source entry at failure | G11: reserve_debit decreases, available increases by the same amount, and current is unchanged | H11: Not Tested | I11: Negative
A12: Replay | B12: TC-Rebuild-11 | C12: FAILED on a Pending Credit Releases the Destination | D12: Medium | E12: A range containing a failed incoming payment that had populated reserve_credit | F12: 1. Rebuild the range 2. Inspect the destination entry at failure | G12: reserve_credit decreases; available and current are both unchanged | H12: Not Tested | I12: Negative
... A53: UI | B53: TC-Rebuild-52 | C53: Statement View Distinguishes Reserve Credit From Current | D53: Medium | E53: A wallet holding reserve_credit | F53: 1. Open the statement view | G53: All four buckets are shown before and after each entry, with reserve_credit visually distinguished from current so the exclusion is legible to the reader | H53: Not Tested | I53: Usability

Sheet Wallet Balance Recompute
A1: Subtopic / Category | B1: TC ID | C1: Title | D1: Priority | E1: Preconditions | F1: Steps | G1: Expected Result | H1: Status | I1: Test Type
A2: Derivation | B2: TC-Recompute-01 | C2: Buckets Derived From the Transaction Log Only | D2: High | E2: A wallet whose buckets have drifted | F2: 1. Trigger a recompute 2. Trace every table the job reads | G2: All four buckets are derived from transaction_log current state; running_balance is never read. Reading the projection to repair the projection is the defect this story removes | H2: Not Tested | I2: Integration
A3: Derivation | B3: TC-Recompute-02 | C3: Aggregate Grain Covers All Postings for a Transaction | D3: High | E3: A transaction with separate PENDING, SUCCESS and FAILED postings | F3: 1. Recompute the wallet 2. Inspect the aggregation grain used | G3: The aggregate is over all postings across the transaction lifecycle, not over a single mutable transaction row, per the append-only ledger model | H3: Not Tested | I3: Functional
A4: Derivation | B4: TC-Recompute-03 | C4: Status and Direction Mapping Consumed From the Shared Definition | D4: High | E4: Access to the implementation | F4: 1. Inspect where the status x direction to bucket mapping comes from | G4: The mapping is consumed from the single shared EMI-602 definition used by the live consumer and by EMI-5950 validation; it is not re-implemented here | H4: Not Tested | I4: Functional
A5: Derivation | B5: TC-Recompute-04 | C5: Order Invariance | D5: High | E5: A wallet whose ledger postings can be applied in an arbitrary order | F5: 1. Apply the postings in a deliberately shuffled order 2. Recompute 3. Repeat with a different shuffle | G5: The result is identical every time; the output does not depend on row order, insertion order or event arrival order | H5: Not Tested | I5: Functional
A6: Functional | B6: TC-Recompute-05 | C6: No-Op When Buckets Already Match | D6: High | E6: A wallet whose buckets agree with the ledger | F6: 1. Trigger a recompute | G6: Completes as NO_OP; no write is made; the run is still recorded so the check itself is auditable | H6: Not Tested | I6: Functional
A7: Functional | B7: TC-Recompute-06 | C7: Drifted Available Is Corrected | D7: High | E7: A wallet whose available has drifted from the ledger | F7: 1. Trigger a recompute 2. Compare before and after values per bucket | G7: Buckets are corrected to the ledger-derived values and variance is reported per bucket | H7: Not Tested | I7: Functional
A8: Idempotency | B8: TC-Recompute-07 | C8: Repeated Runs Over an Unchanged Ledger | D8: High | E8: A completed recompute | F8: 1. Run the same recompute again | G8: Second run is a NO_OP and the state is identical | H8: Not Tested | I8: Integration
A9: Functional | B9: TC-Recompute-08 | C9: Open Outgoing Pending Reflected in Reserve Debit | D9: High | E9: A wallet with an open outgoing pending transaction | F9: 1. Recompute the wallet 2. Inspect all four buckets | G9: reserve_debit reflects the hold, available is correspondingly reduced, and current is unchanged | H9: Not Tested | I9: Functional
A10: Functional | B10: TC-Recompute-09 | C10: Unsettled Incoming Payment Sits in Reserve Credit | D10: High | E10: A wallet holding an unsettled incoming payment | F10: 1. Recompute the wallet 2. Inspect current | G10: reserve_credit is populated and current excludes it. This guards the most commonly misread rule in the model | H10: Not Tested | I10: Functional
A11: Functional | B11: TC-Recompute-10 | C11: Commission and VAT Wallets Are Not Special-Cased | D11: High | E11: An open reserve window with commission and VAT legs | F11: 1. Recompute the commission and VAT wallets | G11: Amounts sit in reserve_credit, not available; both are treated as ordinary destination wallets | H11: Not Tested | I11: Functional
A12: Functional | B12: TC-Recompute-11 | C12: Recompute Across Settlement Moves Reserve Credit to Available | D12: High | E12: A destination wallet mid-reserve | F12: 1. Recompute before settlement 2. Settle the transaction 3. Recompute again | G12: First run: amount in reserve_credit with current unchanged. Second run: amount moved to available with current increased | H12: Not Tested | I12: Functional
... A31: Non-Functional | B31: TC-Recompute-30 | C31: Monetary Precision and Observability | D31: Medium | E31: A recompute across several transaction types | F31: 1. Inspect the arithmetic types used and the emitted logs | G31: The platform monetary type is used throughout with no float, currency SAR; every run emits structured logs carrying the run id | H31: Not Tested | I31: Performance / NFR

Sheet Bucket Identity Validation
A1: Subtopic / Category | B1: TC ID | C1: Title | D1: Priority | E1: Preconditions | F1: Steps | G1: Expected Result | H1: Status | I1: Test Type
A2: Constraint | B2: TC-Identity-01 | C2: Per-Wallet Identity Enforced as a Database Constraint | D2: High | E2: Direct database access available | F2: 1. Attempt to write a wallet row where current does not equal available + reserve_debit, bypassing the application | G2: The database rejects the write; the identity is enforced by constraint, not by an application check alone | H2: Not Tested | I2: Functional
A3: Constraint | B3: TC-Identity-02 | C3: Constraint Derived From the Shared EMI-602 Definition | D3: Medium | E3: Access to the implementation | F3: 1. Inspect where the constraint's definition originates | G3: It is derived from the single EMI-602 definition and is not restated or re-derived in this story's code | H3: Not Tested | I3: Functional
A4: Constraint | B4: TC-Identity-03 | C4: No Non-Negativity Constraint Exists | D4: High | E4: A wallet whose available would go negative with a satisfied identity | F4: 1. Search the schema for a CHECK forbidding a negative available 2. Write a negative available whose identity holds | G4: No non-negativity constraint exists and the write succeeds. A constraint rejecting negative available would fail against live data, because commission and VAT wallets go temporarily negative during the reserve window | H4: Not Tested | I4: Functional
A5: Assertion | B5: TC-Identity-04 | C5: Identity Asserted After Every Balance Write | D5: High | E5: Live transaction traffic | F5: 1. Perform balance writes across several transaction types 2. Trace the assertion | G5: The identity is asserted after every balance write with no gaps | H5: Not Tested | I5: Integration
A6: Assertion | B6: TC-Identity-05 | C6: Violation Writes a Variance Record and Raises an Alert | D6: High | E6: Ability to force an identity violation | F6: 1. Force a violation 2. Inspect the variance store and the alert channel | G6: A variance record is written and an alert raised; the violation does not silently roll back and disappear | H6: Not Tested | I6: Functional
A7: Assertion | B7: TC-Identity-06 | C7: Attempted State Is Captured for Diagnosis | D7: Medium | E7: A forced identity violation | F7: 1. Inspect the variance record | G7: The attempted state is captured in full, so the violation can be diagnosed without reproducing it | H7: Not Tested | I7: Functional
A8: Cross-Wallet | B8: TC-Identity-07 | C8: Conservation Holds Across All Destination Wallets | D8: High | E8: A transaction in an open reserve window with receiver, commission and VAT legs | F8: 1. Run the cross-wallet conservation check 2. Compare the source reserve_debit against the sum of reserve_credit across all destinations | G8: The source wallet's reserve_debit equals the sum of reserve_credit across the receiver, commission and VAT wallets | H8: Not Tested | I8: Functional
A9: Cross-Wallet | B9: TC-Identity-08 | C9: Missing VAT Leg Caught by Conservation but Not by the Per-Wallet Check | D9: High | E9: A transaction where the VAT leg was never created, leaving every wallet internally consistent | F9: 1. Run the per-wallet identity check 2. Run the cross-wallet conservation check | G9: The per-wallet identity passes and the cross-wallet conservation fails with a shortfall. This proves the stronger check earns its place and is the core value of this story | H9: Not Tested | I9: Negative
A10: Cross-Wallet | B10: TC-Identity-09 | C10: Shortfall and Surplus Recorded Distinctly | D10: High | E10: One transaction with a missing leg and another with a leg applied twice | F10: 1. Run the conservation check over both 2. Inspect how each is classified | G10: A shortfall is recorded as a missing leg and attributed to EMI-5949; a surplus is recorded as a duplicate application and attributed to EMI-5948. They are never collapsed into a single mismatch figure | H10: Not Tested | I10: Integration
A11: Cross-Wallet | B11: TC-Identity-10 | C11: Conservation Check Runs Even When the Per-Wallet Check Passes | D11: High | E11: A set of wallets that all pass the per-wallet identity | F11: 1. Run the validation cycle 2. Confirm the conservation check executed | G11: The conservation check runs independently and is never skipped because the per-wallet check passed | H11: Not Tested | I11: Functional
A12: Cross-Wallet | B12: TC-Identity-11 | C12: No False Positive When a Transaction Settles Mid-Sweep | D12: High | E12: A transaction settling while the sweep is running | F12: 1. Run the sweep across the settlement moment | G12: No false positive is raised from observing the reserve window partially closed | H12: Not Tested | I12: Functional
... A31: Non-Functional | B31: TC-Identity-30 | C31: Variance Records Are Immutable | D31: Medium | E31: Variance records present | F31: 1. Attempt to update or delete a variance record | G31: Both are rejected; records are immutable and retained per the platform audit retention policy | H31: Not Tested | I31: Negative

Sheet Stuck Reserve Detection
A1: Subtopic / Category | B1: TC ID | C1: Title | D1: Priority | E1: Preconditions | F1: Steps | G1: Expected Result | H1: Status | I1: Test Type
A2: Detection | B2: TC-Stuck-01 | C2: Reserve Released Within Threshold Is Never Flagged | D2: High | E2: A reserve taken and released normally inside its configured threshold | F2: 1. Run the detection job | G2: The reserve is not flagged; normal activity produces no noise | H2: Not Tested | I2: Functional
A3: Detection | B3: TC-Stuck-02 | C3: Reserve With No Releasing Event Past Threshold Is Flagged | D3: High | E3: A reserve_debit with no releasing ledger event, aged past its threshold | F3: 1. Run the detection job 2. Inspect the flagged item | G3: The reserve is flagged with the correct age and amount | H3: Not Tested | I3: Functional
A4: Detection | B4: TC-Stuck-03 | C4: Reserve Credit With No Releasing Event Is Flagged | D4: High | E4: A reserve_credit with no releasing ledger event past threshold | F4: 1. Run the detection job | G4: The flagged set covers reserve_credit as well as reserve_debit; both bucket types are detected | H4: Not Tested | I4: Functional
A5: Detection | B5: TC-Stuck-04 | C5: Type-Specific Threshold Overrides the Global Default | D5: High | E5: A reserve exceeding its transaction-type threshold but under the global default | F5: 1. Run the detection job | G5: It is flagged per the type-specific rule; a card authorisation and an EOD bank settlement have legitimately different lifetimes | H5: Not Tested | I5: Functional
A6: Detection | B6: TC-Stuck-05 | C6: Documented Defaults Exist Per Transaction Type | D6: Medium | E6: Threshold configuration accessible | F6: 1. Inspect the configured thresholds and their documentation | G6: A default is defined and documented for every transaction type; none is implicit | H6: Not Tested | I6: Functional
A7: Detection | B7: TC-Stuck-06 | C7: Failed EOD Bank Statement Leaves Reserve Debit Unreturned | D7: High | E7: The EMI-5771 scenario: a failed EOD bank statement where reserve_debit was never returned to available | F7: 1. Reproduce the scenario 2. Run the detection job | G7: The stuck reserve is flagged. This is the regression guard for the most frequent balance failure signature in the project history | H7: Not Tested | I7: Negative
A8: Detection | B8: TC-Stuck-07 | C8: Detection Runs on a Configurable Schedule | D8: Medium | E8: Schedule configuration accessible | F8: 1. Change the detection frequency 2. Observe the runs | G8: The job runs at the configured frequency and the change takes effect without a release | H8: Not Tested | I8: Functional
A9: Presentation | B9: TC-Stuck-08 | C9: Operations View Shows the Full Context Per Flagged Reserve | D9: High | E9: Flagged reserves present | F9: 1. Open the operations view | G9: Each row shows wallet, customer reference, transaction id, transaction type, amount, age and the originating ledger entry | H9: Not Tested | I9: Usability
A10: Presentation | B10: TC-Stuck-09 | C10: Ageing Buckets With Counts and SAR Totals | D10: Medium | E10: Flagged reserves of varying ages | F10: 1. Open the operations view | G10: Reserves are grouped into ageing buckets such as over 1 hour, over 24 hours and over 7 days, each with a count and a total value in SAR | H10: Not Tested | I10: Usability
A11: Presentation | B11: TC-Stuck-10 | C11: Sortable by Age and by Amount | D11: Medium | E11: A populated flagged list | F11: 1. Sort by age 2. Sort by amount | G11: Both sorts work so the oldest and largest exposures surface first | H11: Not Tested | I11: Usability
A12: Presentation | B12: TC-Stuck-11 | C12: Row Links Through to the Ledger Entry and the Recompute Action | D12: Medium | E12: A flagged reserve | F12: 1. Open the row and follow both links | G12: The row links through to the originating ledger entry and to the EMI-5946 recompute action for that wallet | H12: Not Tested | I12: Usability
... A22: Non-Functional | B22: TC-Stuck-21 | C22: Flagged and Resolution History Is Immutable | D22: Medium | E22: Flagged and resolved items present | F22: 1. Attempt to update or delete either | G22: Both are rejected; history is immutable and retained per audit policy | H22: Not Tested | I22: Negative

Sheet Wallet Daily Close
A1: Subtopic / Category | B1: TC ID | C1: Title | D1: Priority | E1: Preconditions | F1: Steps | G1: Expected Result | H1: Status | I1: Test Type
A2: Compute | B2: TC-Close-01 | C2: Normal Day With Zero Variance Seals Automatically | D2: High | E2: A trading day whose postings agree with the ledger; EOD cutoff configured | F2: 1. Let the EOD job run 2. Inspect the close record | G2: Opening, per-bucket day movement and closing are computed; the verification run passes and the close is sealed automatically | H2: Not Tested | I2: Edge / Boundary
A3: Compute | B3: TC-Close-02 | C3: Opening Equals the Prior Sealed Closing | D3: High | E3: A wallet with a sealed close for the prior day | F3: 1. Run the close for today 2. Compare today's opening against yesterday's sealed closing, bucket by bucket | G3: Today's opening is identical to yesterday's sealed closing on every bucket | H3: Not Tested | I3: Functional
A4: Compute | B4: TC-Close-03 | C4: Day Movement Derived From the Transaction Log via the Shared Mapping | D4: High | E4: A day with postings across several transaction types | F4: 1. Run the close 2. Trace the derivation of the day's per-bucket sums | G4: Sums are derived from transaction_log using the EMI-602 status x direction mapping, consumed from the shared definition rather than re-implemented | H4: Not Tested | I4: Integration
A5: Compute | B5: TC-Close-04 | C5: Identity Asserted on Every Close | D5: High | E5: Any close | F5: 1. Run the close 2. Assert current = available + reserve_debit on the closing figures | G5: The identity holds on every sealed close; a close that violates it is never sealed | H5: Not Tested | I5: Functional
A6: Continuity | B6: TC-Close-05 | C6: Continuity Violation Blocks Sealing and Raises an Exception | D6: High | E6: A wallet whose opening does not equal the prior sealed closing | F6: 1. Run the close 2. Inspect the outcome and the exception channel | G6: Sealing is blocked and an exception is raised; the discrepancy is never auto-corrected | H6: Not Tested | I6: Integration
A7: Seal | B7: TC-Close-06 | C7: Sealing Requires a Passing Verification Run or a Signed-Off Variance | D7: High | E7: A day with recorded variance against the ledger | F7: 1. Run the close with the variance present 2. Attempt to seal without sign-off 3. Sign off as Finance Lead | G7: Sealing is held until either verification passes with zero variance and estate tie-out, or the Finance Lead signs off the recorded variance; the variance is recorded on the close | H7: Not Tested | I7: Edge / Boundary
A8: Seal | B8: TC-Close-07 | C8: Sealed Records Are Immutable | D8: High | E8: A sealed close | F8: 1. Attempt to update the sealed close 2. Attempt to delete it | G8: Both are rejected; no update or delete path exists for a sealed close | H8: Not Tested | I8: Negative
A9: Cutoff | B9: TC-Close-08 | C9: Postings After Sealing Belong to the Next Business Day | D9: High | E9: A sealed close for the day | F9: 1. Post a transaction after the seal 2. Inspect the sealed record and the next day's opening | G9: The posting lands in the next business day; the sealed close is untouched and history is not mutated | H9: Not Tested | I9: Functional
A10: Cutoff | B10: TC-Close-09 | C10: EOD Cutoff Time Is Configurable | D10: Medium | E10: Cutoff configuration accessible | F10: 1. Change the EOD cutoff 2. Run the close | G10: The new cutoff takes effect and determines which postings fall into the day | H10: Not Tested | I10: Functional
A11: Anchor | B11: TC-Close-10 | C11: Rebuild Consumes the Sealed Close as Its Anchor | D11: High | E11: A sealed close and a rebuild window starting after it | F11: 1. Trigger an EMI-5945 rebuild 2. Inspect the anchor it uses | G11: The rebuild anchors on the sealed close rather than on a running-balance entry or on the live wallet balance, which would be circular | H11: Not Tested | I11: Functional
A12: Anchor | B12: TC-Close-11 | C12: Rebuild Across an Unsealed Boundary Is Rejected Without Override | D12: High | E12: A rebuild window crossing a day that has not been sealed | F12: 1. Request the rebuild without an override 2. Request it with a Finance Lead override | G12: The first is rejected; the second proceeds and the override is recorded on the run | H12: Not Tested | I12: Negative
... A30: Evidence | B30: TC-Close-29 | C30: Close Evidence Exports in Both CSV and PDF | D30: Medium | E30: Sealed closes for a date range | F30: 1. Export the range as CSV 2. Export the same range as PDF 3. Compare both against the sealed records | G30: Both formats are produced and agree with the sealed records and with each other on every bucket. Amounts carry the platform monetary precision in SAR with no float rounding | H30: Not Tested | I30: Reporting

Sheet EMI_MISSING Resolution
A1: Subtopic / Category | B1: TC ID | C1: Title | D1: Priority | E1: Preconditions | F1: Steps | G1: Expected Result | H1: Status | I1: Test Type
A2: Auto Path | B2: TC-Missing-01 | C2: Item Passing All Checks Is Auto-Inserted as an Adjustment Posting | D2: High | E2: An EMI_MISSING bank-statement item that passes limits, balance rules and wallet status/KYC checks | F2: 1. Run reconciliation over the statement 2. Inspect the resulting posting | G2: An appended adjustment posting is created with transaction type RECON_ADJUSTMENT, carrying the recon_id and the bank statement reference | H2: Not Tested | I2: Functional
A3: Auto Path | B3: TC-Missing-02 | C3: Adjustment Carries the Bank Statement Reference | D3: High | E3: An auto-inserted adjustment | F3: 1. Inspect the posting's references | G3: It carries both the recon_id and the bank statement reference (AcctSvcrRef or entry ref), so it is traceable back to the source statement line | H3: Not Tested | I3: Integration
A4: Auto Path | B4: TC-Missing-03 | C4: Ledger History Is Never Edited | D4: High | E4: An EMI_MISSING item resolved automatically | F4: 1. Compare the ledger before and after resolution | G4: No existing posting is edited or deleted; the resolution is purely an appended posting. The bank statement is the control we reconcile against, not a licence to edit our ledger | H4: Not Tested | I4: Functional
A5: Escalation | B5: TC-Missing-04 | C5: Item Failing a Limit Check Is Escalated, Not Auto-Inserted | D5: High | E5: An EMI_MISSING item that breaches a configured limit | F5: 1. Run reconciliation 2. Inspect the outcome | G5: The item goes to the exception queue for manual review; no posting is created automatically | H5: Not Tested | I5: Negative
A6: Escalation | B6: TC-Missing-05 | C6: Item Failing a Wallet Status or KYC Check Is Escalated | D6: High | E6: An EMI_MISSING item for a wallet in a non-transactable or KYC-incomplete state | F6: 1. Run reconciliation | G6: The item is escalated to the exception queue rather than auto-inserted | H6: Not Tested | I6: Negative
A7: Escalation | B7: TC-Missing-06 | C7: Item Failing a Balance Rule Is Escalated | D7: Medium | E7: An EMI_MISSING item that would breach a balance rule | F7: 1. Run reconciliation | G7: The item is escalated; the system does not resolve it silently | H7: Not Tested | I7: Negative
A8: Escalation | B8: TC-Missing-07 | C8: Manual Resolution Is Also by Adjustment Posting With Reviewer Recorded | D8: High | E8: An escalated item in the exception queue | F8: 1. Resolve it as a reviewer 2. Inspect the resulting posting and the audit record | G8: Resolution creates an appended adjustment posting like the auto path, and the reviewer's identity is recorded against it | H8: Not Tested | I8: Negative
A9: Projection | B9: TC-Missing-08 | C9: Inserted Postings Flow Through the Normal CDC Path | D9: High | E9: An auto-inserted adjustment posting | F9: 1. Trace how the posting reaches running_balance | G9: It flows through the normal CDC and consumer path; there is no direct running-balance write and no special-case code path | H9: Not Tested | I9: Integration
A10: Projection | B10: TC-Missing-09 | C10: Resulting Balance Matches a Recompute | D10: High | E10: A wallet with an inserted adjustment posting | F10: 1. Let the projection settle 2. Run an EMI-5946 recompute and compare | G10: The projected balance matches the ledger-derived recompute exactly; the adjustment is aggregated with no special-casing | H10: Not Tested | I10: Edge / Boundary
A11: Settled Corrections | B11: TC-Missing-10 | C11: Status Mismatch Uses the Four-Step Pair-Adjustment Unwind | D11: High | E11: A settled transaction with a STATUS_MISMATCH against the bank statement | F11: 1. Resolve the mismatch 2. Inspect the postings created | G11: The EMI-602 four-step pair-adjustment unwind is applied — reverse success, reverse pending, append new pending, append new success — as four appended entries with no edit | H11: Not Tested | I11: Functional
A12: Settled Corrections | B12: TC-Missing-11 | C12: Amount Mismatch Uses the Same Unwind | D12: High | E12: A settled transaction with an AMOUNT_MISMATCH against the bank statement | F12: 1. Resolve the mismatch 2. Inspect the postings and the resulting balance | G12: The four-step unwind is applied and the corrected amount is reflected; no posting is edited in place | H12: Not Tested | I12: Functional
... A19: Integration | B19: TC-Missing-18 | C19: Adjustment After a Sealed Close Belongs to the Next Business Day | D19: High | E19: A sealed EMI-5954 close and an adjustment resolving an item for that day | F19: 1. Insert the adjustment after the seal 2. Inspect the sealed close and the next day | G19: The adjustment lands in the next business day and the sealed close is untouched | H19: Not Tested | I19: Integration

Sheet E2E Balances Flows
A1: Subtopic / Category | B1: TC ID | C1: Title | D1: Priority | E1: Preconditions | F1: Steps | G1: Expected Result | H1: Status | I1: Test Type
A2: E2E - Detect to Repair | B2: TC-BalE2E-01 | C2: Drifted Wallet Detected, Quarantined, Recomputed and Cleared | D2: High | E2: A wallet whose buckets have drifted from the ledger; detection, recompute and reporting all enabled | F2: 1. Introduce the drift 2. Let the EMI-5950 sweep detect it 3. Observe the quarantine 4. Let EMI-5946 recompute run 5. Re-run the sweep | G2: The sweep detects the variance and records it per bucket; only that wallet is quarantined; recompute is invoked for that scope alone and corrects the buckets; the follow-up sweep is clean and the whole chain shares one run id | H2: Not Tested | I2: Functional
A3: E2E - Detect to Repair | B3: TC-BalE2E-02 | C3: Missing VAT Leg Found by Conservation and Traced to Its Cause | D3: High | E3: A transaction whose VAT leg was never applied, leaving every wallet internally consistent | F3: 1. Run the per-wallet identity check 2. Run the cross-wallet conservation check 3. Follow the attribution | G3: Per-wallet passes, conservation reports a shortfall, and the shortfall is attributed to lifecycle ordering (EMI-5949) rather than to duplicate application. The failure is diagnosable from the record alone | H3: Not Tested | I3: Integration
A4: E2E - Detect to Repair | B4: TC-BalE2E-03 | C4: Duplicated Leg Found as a Surplus and Attributed to Idempotency | D4: High | E4: A destination leg applied twice | F4: 1. Run the conservation check 2. Follow the attribution | G4: A surplus is recorded, distinguished from a shortfall, and attributed to consumer idempotency (EMI-5948). Recompute then restores the correct position | H4: Not Tested | I4: Integration
A5: E2E - Two Repair Modes | B5: TC-BalE2E-04 | C5: Balance Wrong but Statement Right Routes to Recompute Only | D5: High | E5: A wallet whose buckets are wrong while its statement rows are correct | F5: 1. Let detection classify the variance 2. Observe which repair runs 3. Compare the statement sequence before and after | G5: Recompute runs and completes in seconds; the statement rebuild is not invoked; the running_balance entry sequence is provably unchanged | H5: Not Tested | I5: Functional
A6: E2E - Two Repair Modes | B6: TC-BalE2E-05 | C6: Statement Wrong Routes to Rebuild After Explicit Confirmation | D6: High | E6: A wallet whose per-entry before and after values are wrong | F6: 1. Let detection flag that a statement rebuild is required 2. Confirm and trigger the rebuild explicitly 3. Verify the regenerated sequence | G6: The rebuild is flagged but never auto-invoked; once triggered it archives, replays in deterministic order and reports variance; the regenerated sequence is reproducible on a second run | H6: Not Tested | I6: Integration
A7: E2E - Two Repair Modes | B7: TC-BalE2E-06 | C7: The Two Repair Modes Never Run Concurrently on One Wallet | D7: High | E7: A repair in flight on a wallet | F7: 1. Start a recompute and request a rebuild for the same wallet 2. Reverse the order and repeat | G7: Whichever starts second is rejected with a conflict error in both directions; scope locking is mutually exclusive | H7: Not Tested | I7: Integration
A8: E2E - Lifecycle | B8: TC-BalE2E-07 | C8: Full Transaction Lifecycle Keeps the Identity at Every Step | D8: High | E8: A transaction with principal, commission and VAT legs | F8: 1. Reserve, then settle 2. After each posting, assert the per-wallet identity on every participating wallet and the cross-wallet conservation | G8: current = available + reserve_debit holds on every wallet after every posting; reserve_credit is excluded from current throughout; conservation holds for the whole reserve window and resolves to zero on settlement | H8: Not Tested | I8: Edge / Boundary
A9: E2E - Lifecycle | B9: TC-BalE2E-08 | C9: Failed Transaction Returns Every Party to Its Starting Position | D9: High | E9: A transaction that reserves then fails | F9: 1. Record all four buckets for every participating wallet 2. Reserve, then fail 3. Re-read all buckets | G9: Every wallet returns exactly to its starting position across all four buckets; no reserve is left behind on any leg including commission and VAT | H9: Not Tested | I9: Edge / Boundary
A10: E2E - Lifecycle | B10: TC-BalE2E-09 | C10: Adjustment of a Settled Transaction Flows Through Every Layer | D10: High | E10: A settled transaction requiring correction | F10: 1. Apply the four-step pair-adjustment unwind 2. Let the projection settle 3. Run a recompute 4. Run a rebuild over the range | G10: The four appended postings flow through the consumer, the recompute aggregate and the replay with no special-casing anywhere; all three layers agree on the corrected position and no history is edited | H10: Not Tested | I10: Integration
A11: E2E - Stuck Reserves | B11: TC-BalE2E-10 | C11: Stuck Reserve Detected, Traced and Resolved Through the Correction Path | D11: High | E11: A reserve with no releasing event, aged past its threshold | F11: 1. Let EMI-5951 detection flag it 2. Trace it to the absent releasing event 3. Resolve it through the existing correction path 4. Re-run detection and recompute | G11: The reserve is flagged with correct age and amount, traceable to its origin, resolved without any new money-movement path, and the item records its resolution; the follow-up detection run is clean | H11: Not Tested | I11: Integration
A12: E2E - Stuck Reserves | B12: TC-BalE2E-11 | C12: TTL Prevention and Stuck-Reserve Detection Never Double-Act | D12: High | E12: A pending item that both the Payments TTL job and stuck-reserve detection could act on | F12: 1. Let both run over the same item | G12: Exactly one acts. EMI-6031 prevents on a clock and EMI-5951 detects what slips through; neither double-acts on the same item and no duplicate compensating posting is created | H12: Not Tested | I12: Integration
... A21: E2E - Prevention | B21: TC-BalE2E-20 | C21: Full Epic Chain From Delivery to Sealed Close | D21: High | E21: All seven story and task behaviours active across one trading day | F21: 1. Run a day of traffic through the guarded pipeline 2. Let detection sweep and repair anything it finds 3. Run the EOD close and let it verify and seal 4. Rebuild a window of statement history and compare | G21: Postings apply in order, exactly once, with lifecycle respected; detection finds nothing or repairs what it finds; the close verifies against the ledger, passes the estate tie-out and seals; the statement rebuild over the sealed window reproduces the same sequence and reports no variance | H21: Not Tested | I21: Edge / Boundary
